Workbook
Name UPDATE: 'Data Sheet'!$E$1

Sheet Index
B2: ='Data Sheet'!$B$1 -> TATA CONSUMER PRODUCTS LTD
B4: Equity Research & Valuation Model
B6: Prepared by : | C6: Ashish Jha | L6: Metric | N6: Value
C7: NIT Surat
L8: CMP | N8: ='Investment Summary'!C8 -> ₹1,196.00
B9: Company : | C9: =B2 -> TATA CONSUMER PRODUCTS LTD
B10: Sector : | C10: FMCG | L10: DCF Value | N10: ='Investment Summary'!C10 -> ₹98.86
B11: Currency : | C11: INR ( ₹ )
B12: Valuation Date : | C12: =TODAY() -> 46193 | L12: Relative Valuation | N12: ='Investment Summary'!C12 -> ₹781 - ₹1,476
L14: View | N14: Fairly Valued
A15: # | B15: Navigation
L16: Recommendation | N16: HOLD
C17: Investment Summary
C19: Data Sheet
C21: Historical Financial Statement
C23: Ratio Analysis
C25: Forecasting
C27: WACC
C29: Beta Regression
C31: Return on Markets
C33: Common Size Statement
C35: Raw Financial Statement
C37: Intrinsic Growth Rate
C39: DCF Valuation
... C47: Monte Carlo Simulation
A49: # | B49: Model Flow
C51: Stage | E51: Purpose
C53: Data collection | D53: Gather historial financial and market data.
C56: Ratio Analysis | D56: Analyze trends, profitability & efficiency.
C59: Forecasting | D59: Project future operating performance.
C62: WACC | D62: Estimate cost of capital.
C65: DCF & Relative Valuation | D65: Determine intrinsic & relative value.
C68: Investment Conclusion | D68: Form investment view.
B70: Source: Screener, Yahoo Finance, Company Annual Reports, Valuation School

Sheet Investment Summary
B2: ='Data Sheet'!$B$1 -> TATA CONSUMER PRODUCTS LTD
B4: Equity Research & Valuation Model
A6: # | B6: Company Overiew
B8: CMP | C8: ="₹"&TEXT('Comps Val'!D8,"#,##0.00") -> ₹1,196.00
B10: DCF Value | C10: ="₹"&TEXT(DCF!D37, "#,##0.00") -> ₹98.86
B12: Relative Comps Value | C12: ="₹"&TEXT(MIN('Comps Val'!O32:Q32),"#,##0")&" - ₹"&TEXT(MAX('Comps Val'!O32:Q32),"#,##0") -> ₹781 - ₹1,476
A14: # | B14: DCF Valuation Summary
A22: # | B22: Relative Valuation Summary
A30: # | B30: Key Investment Positives
B32: 1. Strong portfolio of established consumer brands across beverages and food categories.
B33: 2. Backed by the Tata Group, providing strong brand equity and governance standards.
B34: 3. Consistent revenue growth and healthy operating margins over the historical period.
B35: 4. Long-term growth opportunities from premiumization and expansion of food products.
A37: # | B37: Key Investment Risks
B39: 1. Premium valuation relative to several FMCG peers on earnings-based multiples.
B40: 2. Raw material inflation may put pressure on operating margins.
B41: 3. DCF valuation remains sensitive to assumptions regarding reinvestment rates and long-term growth.
B42: 4. Intensifying competition from both established FMCG players and emerging brands.
A44: # | B44: Final Investment View
A53: # | B53: Football Field Analysis
A74: # | B74: Investment View
B76: Recommendation : | C76: HOLD
B78: CMP | C78: =Index!N8 -> ₹1,196.00
B80: Relative Valuation Range | C80: =Index!N12 -> ₹781 - ₹1,476
B82: Investment View | C82: =Index!N14 -> Fairly Valued

Sheet Profit & Loss
A1: ='Data Sheet'!B1 -> TATA CONSUMER PRODUCTS LTD | H1: =UPDATE | M1: SCREENER.IN
A3: Narration | B3: ='Data Sheet'!B16 -> 42460 | C3: ='Data Sheet'!C16 -> 42825 | D3: ='Data Sheet'!D16 -> 43190 | E3: ='Data Sheet'!E16 -> 43555 | F3: ='Data Sheet'!F16 -> 43921 | G3: ='Data Sheet'!G16 -> 44286 | H3: ='Data Sheet'!H16 -> 44651 | I3: ='Data Sheet'!I16 -> 45016 | ... K3: ='Data Sheet'!K16 -> 45747 | L3: Trailing | M3: Best Case | N3: Worst Case
A4: Sales | B4: ='Data Sheet'!B17 -> 6636.54 | C4: ='Data Sheet'!C17 -> 6779.55 | D4: ='Data Sheet'!D17 -> 6815.35 | E4: ='Data Sheet'!E17 -> 7251.5 | F4: ='Data Sheet'!F17 -> 9637.42 | G4: ='Data Sheet'!G17 -> 11602.03 | H4: ='Data Sheet'!H17 -> 12425.37 | I4: ='Data Sheet'!I17 -> 13783.16 | ... K4: ='Data Sheet'!K17 -> 17618.3 | L4: =SUM(Quarters!H4:K4) -> 19465.03 | M4: =$K4+M23*K4 -> 20413.492 | N4: =$K4+N23*L4 -> 19848.72
A5: Expenses | B5: =SUM('Data Sheet'!B18,'Data Sheet'!B20:B24, -1*'Data Sheet'!B19) -> 6270.63 | C5: =SUM('Data Sheet'!C18,'Data Sheet'!C20:C24, -1*'Data Sheet'!C19) -> 5988.42 | D5: =SUM('Data Sheet'!D18,'Data Sheet'!D20:D24, -1*'Data Sheet'!D19) -> 5976.44 | E5: =SUM('Data Sheet'!E18,'Data Sheet'!E20:E24, -1*'Data Sheet'!E19) -> 6465.59 | F5: =SUM('Data Sheet'!F18,'Data Sheet'!F20:F24, -1*'Data Sheet'!F19) -> 8345.27 | G5: =SUM('Data Sheet'!G18,'Data Sheet'!G20:G24, -1*'Data Sheet'!G19) -> 10058.27 | H5: =SUM('Data Sheet'!H18,'Data Sheet'!H20:H24, -1*'Data Sheet'!H19) -> 10706.59 | I5: =SUM('Data Sheet'!I18,'Data Sheet'!I20:I24, -1*'Data Sheet'!I19) -> 11926.69 | ... K5: =SUM('Data Sheet'!K18,'Data Sheet'!K20:K24, -1*'Data Sheet'!K19) -> 15138.95 | L5: =SUM(Quarters!H5:K5) -> 12453.36 | M5: =M4-M6 -> 17514.039 | N5: =N4-N6 -> 17277.908
A6: Operating Profit | B6: =B4-B5 -> 365.91 | C6: =C4-C5 -> 791.13 | D6: =D4-D5 -> 838.91 | E6: =E4-E5 -> 785.91 | F6: =F4-F5 -> 1292.15 | G6: =G4-G5 -> 1543.76 | H6: =H4-H5 -> 1718.78 | I6: =I4-I5 -> 1856.47 | ... K6: =K4-K5 -> 2479.35 | L6: =SUM(Quarters!H6:K6) -> 2620.34 | M6: =M4*M24 -> 2899.4525 | N6: =N4*N24 -> 2570.8124
A7: Other Income | B7: ='Data Sheet'!B25 -> 37.54 | C7: ='Data Sheet'!C25 -> 88.4 | D7: ='Data Sheet'!D25 -> 73.02 | E7: ='Data Sheet'!E25 -> 123.84 | F7: ='Data Sheet'!F25 -> -163.2 | G7: ='Data Sheet'!G25 -> 90.73 | H7: ='Data Sheet'!H25 -> 88 | I7: ='Data Sheet'!I25 -> 328.33 | ... K7: ='Data Sheet'!K25 -> 188.14 | L7: =SUM(Quarters!H7:K7) -> 191.16 | M7: 0 | N7: 0
A8: Depreciation | B8: ='Data Sheet'!B26 -> 116.79 | C8: ='Data Sheet'!C26 -> 126.04 | D8: ='Data Sheet'!D26 -> 116.04 | E8: ='Data Sheet'!E26 -> 122.57 | F8: ='Data Sheet'!F26 -> 241.71 | G8: ='Data Sheet'!G26 -> 254.74 | H8: ='Data Sheet'!H26 -> 278.01 | I8: ='Data Sheet'!I26 -> 304.08 | ... K8: ='Data Sheet'!K26 -> 600.74 | L8: =SUM(Quarters!H8:K8) -> 614.59 | M8: =+$L8 -> 614.59 | N8: =+$L8 -> 614.59
A9: Interest | B9: ='Data Sheet'!B27 -> 116.9 | C9: ='Data Sheet'!C27 -> 91.53 | D9: ='Data Sheet'!D27 -> 42.76 | E9: ='Data Sheet'!E27 -> 52.47 | F9: ='Data Sheet'!F27 -> 77.86 | G9: ='Data Sheet'!G27 -> 68.69 | H9: ='Data Sheet'!H27 -> 72.78 | I9: ='Data Sheet'!I27 -> 87.16 | ... K9: ='Data Sheet'!K27 -> 290.2 | L9: =SUM(Quarters!H9:K9) -> 138.6 | M9: =+$L9 -> 138.6 | N9: =+$L9 -> 138.6
A10: Profit before tax | B10: ='Data Sheet'!B28 -> 169.76 | C10: ='Data Sheet'!C28 -> 661.96 | D10: ='Data Sheet'!D28 -> 753.13 | E10: ='Data Sheet'!E28 -> 734.71 | F10: ='Data Sheet'!F28 -> 809.38 | G10: ='Data Sheet'!G28 -> 1311.06 | H10: ='Data Sheet'!H28 -> 1455.99 | I10: ='Data Sheet'!I28 -> 1793.56 | ... K10: ='Data Sheet'!K28 -> 1776.55 | L10: =SUM(Quarters!H10:K10) -> 2058.31 | M10: =M6+M7-SUM(M8:M9) -> 2146.2625 | N10: =N6+N7-SUM(N8:N9) -> 1817.6224
A11: Tax | B11: ='Data Sheet'!B29 -> 200.01 | C11: ='Data Sheet'!C29 -> 198.31 | D11: ='Data Sheet'!D29 -> 185.87 | E11: ='Data Sheet'!E29 -> 260.88 | F11: ='Data Sheet'!F29 -> 274.19 | G11: ='Data Sheet'!G29 -> 317.27 | H11: ='Data Sheet'!H29 -> 377.04 | I11: ='Data Sheet'!I29 -> 447.04 | ... K11: ='Data Sheet'!K29 -> 396.24 | L11: =SUM(Quarters!H11:K11) -> 504.96 | M11: =IF($L10>0,$L11/$L10,0) -> 0.24532748 | N11: =IF($L10>0,$L11/$L10,0) -> 0.24532748
A12: Net profit | B12: ='Data Sheet'!B30 -> -5.52 | C12: ='Data Sheet'!C30 -> 389.44 | D12: ='Data Sheet'!D30 -> 495.56 | E12: ='Data Sheet'!E30 -> 408.19 | F12: ='Data Sheet'!F30 -> 459.76 | G12: ='Data Sheet'!G30 -> 856.69 | H12: ='Data Sheet'!H30 -> 935.78 | I12: ='Data Sheet'!I30 -> 1203.77 | ... K12: ='Data Sheet'!K30 -> 1278.47 | L12: =SUM(Quarters!H12:K12) -> 1468.07 | M12: =M10-M11*M10 -> 1619.7254 | N12: =N10-N11*N10 -> 1371.7097
A13: EPS | B13: =IF('Data Sheet'!B93>0,B12/'Data Sheet'!B93,0) -> -0.084223375 | C13: =IF('Data Sheet'!C93>0,C12/'Data Sheet'!C93,0) -> 5.9420201 | D13: =IF('Data Sheet'!D93>0,D12/'Data Sheet'!D93,0) -> 7.561184 | E13: =IF('Data Sheet'!E93>0,E12/'Data Sheet'!E93,0) -> 6.228105 | F13: =IF('Data Sheet'!F93>0,F12/'Data Sheet'!F93,0) -> 4.8041797 | G13: =IF('Data Sheet'!G93>0,G12/'Data Sheet'!G93,0) -> 8.9518286 | H13: =IF('Data Sheet'!H93>0,H12/'Data Sheet'!H93,0) -> 9.7782654 | I13: =IF('Data Sheet'!I93>0,I12/'Data Sheet'!I93,0) -> 12.47818 | ... K13: =IF('Data Sheet'!K93>0,K12/'Data Sheet'!K93,0) -> 12.920364 | L13: =IF('Data Sheet'!$B6>0,'Profit & Loss'!L12/'Data Sheet'!$B6,0) -> 14.886717 | M13: =IF('Data Sheet'!$B6>0,'Profit & Loss'!M12/'Data Sheet'!$B6,0) -> 16.424553 | N13: =IF('Data Sheet'!$B6>0,'Profit & Loss'!N12/'Data Sheet'!$B6,0) -> 13.909592
A14: Price to earning | B14: =IF(B15>0,B15/B13,"") -> -1421.933 | C14: =IF(C15>0,C15/C13,"") -> 25.025159 | D14: =IF(D15>0,D15/D13,"") -> 33.800262 | E14: =IF(E15>0,E15/E13,"") -> 32.345312 | F14: =IF(F15>0,F15/F13,"") -> 60.62013 | G14: =IF(G15>0,G15/G13,"") -> 70.495094 | H14: =IF(H15>0,H15/H13,"") -> 78.52722 | I14: =IF(I15>0,I15/I13,"") -> 56.109947 | ... K14: =IF(K15>0,K15/K13,"") -> 77.544256 | L14: =IF(L13>0,L15/L13,0) -> 76.524594 | M14: =M25 -> 76.524594 | N14: =N25 -> 60.412796
A15: Price | B15: ='Data Sheet'!B90 -> 119.76 | C15: ='Data Sheet'!C90 -> 148.7 | D15: ='Data Sheet'!D90 -> 255.57 | E15: ='Data Sheet'!E90 -> 201.45 | F15: ='Data Sheet'!F90 -> 291.23 | G15: ='Data Sheet'!G90 -> 631.06 | H15: ='Data Sheet'!H90 -> 767.86 | I15: ='Data Sheet'!I90 -> 700.15 | ... K15: ='Data Sheet'!K90 -> 1001.9 | L15: ='Data Sheet'!B8 -> 1139.2 | M15: =M13*M14 -> 1256.8823 | N15: =N13*N14 -> 840.31732
A17: RATIOS:
A18: Dividend Payout | B18: =IF('Data Sheet'!B30>0, 'Data Sheet'!B31/'Data Sheet'!B30, 0) -> 0 | C18: =IF('Data Sheet'!C30>0, 'Data Sheet'!C31/'Data Sheet'!C30, 0) -> 0.38082888 | D18: =IF('Data Sheet'!D30>0, 'Data Sheet'!D31/'Data Sheet'!D30, 0) -> 0.29927758 | E18: =IF('Data Sheet'!E30>0, 'Data Sheet'!E31/'Data Sheet'!E30, 0) -> 0.38653568 | F18: =IF('Data Sheet'!F30>0, 'Data Sheet'!F31/'Data Sheet'!F30, 0) -> 0.54121716 | G18: =IF('Data Sheet'!G30>0, 'Data Sheet'!G31/'Data Sheet'!G30, 0) -> 0.43568852 | H18: =IF('Data Sheet'!H30>0, 'Data Sheet'!H31/'Data Sheet'!H30, 0) -> 0.59583449 | I18: =IF('Data Sheet'!I30>0, 'Data Sheet'!I31/'Data Sheet'!I30, 0) -> 0.65211793 | ... K18: =IF('Data Sheet'!K30>0, 'Data Sheet'!K31/'Data Sheet'!K30, 0) -> 0.63852887
A19: OPM | B19: =IF(B6>0,B6/B4,0) -> 0.055135658 | C19: =IF(C6>0,C6/C4,0) -> 0.11669359 | D19: =IF(D6>0,D6/D4,0) -> 0.12309126 | E19: =IF(E6>0,E6/E4,0) -> 0.10837896 | F19: =IF(F6>0,F6/F4,0) -> 0.13407634 | G19: =IF(G6>0,G6/G4,0) -> 0.13305947 | H19: =IF(H6>0,H6/H4,0) -> 0.13832828 | I19: =IF(I6>0,I6/I4,0) -> 0.13469117 | ... L19: =IF(L6>0,L6/L4,0) -> 0.13461782
G22: TRENDS: | H22: 10 YEARS | I22: 7 YEARS | J22: 5 YEARS | K22: 3 YEARS | L22: RECENT | M22: BEST | N22: WORST
G23: Sales Growth | H23: =IF(B4=0,"",POWER($K4/B4,1/9)-1) -> 0.11458601 | I23: =IF(D4=0,"",POWER($K4/D4,1/7)-1) -> 0.14531545 | J23: =IF(F4=0,"",POWER($K4/F4,1/5)-1) -> 0.12823779 | K23: =IF(H4=0,"",POWER($K4/H4, 1/3)-1) -> 0.12344433 | L23: =IF(ISERROR(MAX(IF(J4=0,"",(K4-J4)/J4),IF(K4=0,"",(L4-K4)/K4))),"",MAX(IF(J4=0,"",(K4-J4)/J4),IF(K4=0,"",(L4-K4)/K4))) -> 0.15865276 | M23: =MAX(K23:L23) -> 0.15865276 | N23: =MIN(H23:L23) -> 0.11458601
G24: OPM | H24: =IF(SUM(B4:$K$4)=0,"",SUMPRODUCT(B19:$K$19,B4:$K$4)/SUM(B4:$K$4)) -> 0.12952031 | I24: =IF(SUM(E4:$K$4)=0,"",SUMPRODUCT(E19:$K$19,E4:$K$4)/SUM(E4:$K$4)) -> 0.13665475 | J24: =IF(SUM(G4:$K$4)=0,"",SUMPRODUCT(G19:$K$19,G4:$K$4)/SUM(G4:$K$4)) -> 0.1399094 | K24: =IF(SUM(I4:$K$4)=0, "", SUMPRODUCT(I19:$K$19,I4:$K$4)/SUM(I4:$K$4)) -> 0.14203609 | L24: =L19 -> 0.13461782 | M24: =MAX(K24:L24) -> 0.14203609 | N24: =MIN(H24:L24) -> 0.12952031
G25: Price to Earning | H25: =IF(ISERROR(AVERAGEIF(B14:$L14,">0")),"",AVERAGEIF(B14:$L14,">0")) -> 60.412796 | I25: =IF(ISERROR(AVERAGEIF(E14:$L14,">0")),"",AVERAGEIF(E14:$L14,">0")) -> 68.162818 | J25: =IF(ISERROR(AVERAGEIF(G14:$L14,">0")),"",AVERAGEIF(G14:$L14,">0")) -> 75.389517 | K25: =IF(ISERROR(AVERAGEIF(I14:$L14,">0")),"",AVERAGEIF(I14:$L14,">0")) -> 75.828696 | L25: =L14 -> 76.524594 | M25: =MAX(K25:L25) -> 76.524594 | N25: =MIN(H25:L25) -> 60.412796

Sheet Quarters
A1: ='Profit & Loss'!A1 -> TATA CONSUMER PRODUCTS LTD | E1: =UPDATE | J1: SCREENER.IN
A3: Narration | B3: ='Data Sheet'!B41 -> 45199 | C3: ='Data Sheet'!C41 -> 45291 | D3: ='Data Sheet'!D41 -> 45382 | E3: ='Data Sheet'!E41 -> 45473 | F3: ='Data Sheet'!F41 -> 45565 | G3: ='Data Sheet'!G41 -> 45657 | H3: ='Data Sheet'!H41 -> 45747 | I3: ='Data Sheet'!I41 -> 45838 | ... K3: ='Data Sheet'!K41 -> 46022
A4: Sales | B4: ='Data Sheet'!B42 -> 3733.78 | C4: ='Data Sheet'!C42 -> 3803.92 | D4: ='Data Sheet'!D42 -> 3926.94 | E4: ='Data Sheet'!E42 -> 4352.07 | F4: ='Data Sheet'!F42 -> 4214.45 | G4: ='Data Sheet'!G42 -> 4443.56 | H4: ='Data Sheet'!H42 -> 4608.22 | I4: ='Data Sheet'!I42 -> 4778.91 | ... K4: ='Data Sheet'!K42 -> 5112
A5: Expenses | B5: ='Data Sheet'!B43 -> 3196.69 | C5: ='Data Sheet'!C43 -> 3231.54 | D5: ='Data Sheet'!D43 -> 3297.34 | E5: ='Data Sheet'!E43 -> 3684.69 | F5: ='Data Sheet'!F43 -> 3588.16 | G5: ='Data Sheet'!G43 -> 3878.83 | H5: ='Data Sheet'!H43 -> 3987.27 | I5: ='Data Sheet'!I43 -> 4171.97 | J5: ='Data Sheet'!J43 -> 4294.12
A6: Operating Profit | B6: ='Data Sheet'!B50 -> 537.09 | C6: ='Data Sheet'!C50 -> 572.38 | D6: ='Data Sheet'!D50 -> 629.6 | E6: ='Data Sheet'!E50 -> 667.38 | F6: ='Data Sheet'!F50 -> 626.29 | G6: ='Data Sheet'!G50 -> 564.73 | H6: ='Data Sheet'!H50 -> 620.95 | I6: ='Data Sheet'!I50 -> 606.94 | ... K6: ='Data Sheet'!K50 -> 720.67
A7: Other Income | B7: ='Data Sheet'!B44 -> 75.28 | C7: ='Data Sheet'!C44 -> -31.94 | D7: ='Data Sheet'!D44 -> -177.35 | E7: ='Data Sheet'!E44 -> 22.07 | F7: ='Data Sheet'!F44 -> 18.8 | G7: ='Data Sheet'!G44 -> 45.44 | H7: ='Data Sheet'!H44 -> 101.83 | I7: ='Data Sheet'!I44 -> 41.17 | ... K7: ='Data Sheet'!K44 -> 10.15
A8: Depreciation | B8: ='Data Sheet'!B45 -> 93.93 | C8: ='Data Sheet'!C45 -> 85.51 | D8: ='Data Sheet'!D45 -> 115.76 | E8: ='Data Sheet'!E45 -> 148 | F8: ='Data Sheet'!F45 -> 149.33 | G8: ='Data Sheet'!G45 -> 150.32 | H8: ='Data Sheet'!H45 -> 153.09 | I8: ='Data Sheet'!I45 -> 148.93 | ... K8: ='Data Sheet'!K45 -> 159.29
A9: Interest | B9: ='Data Sheet'!B46 -> 27.56 | C9: ='Data Sheet'!C46 -> 33.19 | D9: ='Data Sheet'!D46 -> 42.83 | E9: ='Data Sheet'!E46 -> 93.6 | F9: ='Data Sheet'!F46 -> 98.69 | G9: ='Data Sheet'!G46 -> 57.92 | H9: ='Data Sheet'!H46 -> 39.99 | I9: ='Data Sheet'!I46 -> 33.76 | ... K9: ='Data Sheet'!K46 -> 31.62
A10: Profit before tax | B10: ='Data Sheet'!B47 -> 490.88 | C10: ='Data Sheet'!C47 -> 421.74 | D10: ='Data Sheet'!D47 -> 293.66 | E10: ='Data Sheet'!E47 -> 447.85 | F10: ='Data Sheet'!F47 -> 397.07 | G10: ='Data Sheet'!G47 -> 401.93 | H10: ='Data Sheet'!H47 -> 529.7 | I10: ='Data Sheet'!I47 -> 465.42 | ... K10: ='Data Sheet'!K47 -> 539.91
A11: Tax | B11: ='Data Sheet'!B48 -> 131.7 | C11: ='Data Sheet'!C48 -> 106.21 | D11: ='Data Sheet'!D48 -> 25.95 | E11: ='Data Sheet'!E48 -> 133.7 | F11: ='Data Sheet'!F48 -> 37.73 | G11: ='Data Sheet'!G48 -> 102.18 | H11: ='Data Sheet'!H48 -> 122.63 | I11: ='Data Sheet'!I48 -> 118.98 | ... K11: ='Data Sheet'!K48 -> 137.12
A12: Net profit | B12: ='Data Sheet'!B49 -> 338.24 | C12: ='Data Sheet'!C49 -> 278.87 | D12: ='Data Sheet'!D49 -> 216.63 | E12: ='Data Sheet'!E49 -> 290.32 | F12: ='Data Sheet'!F49 -> 364.42 | G12: ='Data Sheet'!G49 -> 278.88 | H12: ='Data Sheet'!H49 -> 344.85 | I12: ='Data Sheet'!I49 -> 334.15 | ... K12: ='Data Sheet'!K49 -> 384.61
A14: OPM | B14: =IF(B4>0,B6/B4,"") -> 0.14384618 | C14: =IF(C4>0,C6/C4,"") -> 0.15047109 | D14: =IF(D4>0,D6/D4,"") -> 0.1603284 | E14: =IF(E4>0,E6/E4,"") -> 0.15334772 | F14: =IF(F4>0,F6/F4,"") -> 0.14860539 | G14: =IF(G4>0,G6/G4,"") -> 0.12708954 | H14: =IF(H4>0,H6/H4,"") -> 0.13474834 | I14: =IF(I4>0,I6/I4,"") -> 0.12700386 | ... K14: =IF(K4>0,K6/K4,"") -> 0.14097613

Sheet Balance Sheet
A1: ='Profit & Loss'!A1 -> TATA CONSUMER PRODUCTS LTD | E1: =UPDATE | J1: SCREENER.IN
A3: Narration | B3: ='Data Sheet'!B56 -> 42460 | C3: ='Data Sheet'!C56 -> 42825 | D3: ='Data Sheet'!D56 -> 43190 | E3: ='Data Sheet'!E56 -> 43555 | F3: ='Data Sheet'!F56 -> 43921 | G3: ='Data Sheet'!G56 -> 44286 | H3: ='Data Sheet'!H56 -> 44651 | I3: ='Data Sheet'!I56 -> 45016 | ... K3: ='Data Sheet'!K56 -> 45747
A4: Equity Share Capital | B4: ='Data Sheet'!B57 -> 63.11 | C4: ='Data Sheet'!C57 -> 63.11 | D4: ='Data Sheet'!D57 -> 63.11 | E4: ='Data Sheet'!E57 -> 63.11 | F4: ='Data Sheet'!F57 -> 92.16 | G4: ='Data Sheet'!G57 -> 92.16 | H4: ='Data Sheet'!H57 -> 92.16 | I4: ='Data Sheet'!I57 -> 92.9 | ... K4: ='Data Sheet'!K57 -> 98.95
A5: Reserves | B5: ='Data Sheet'!B58 -> 6184.06 | C5: ='Data Sheet'!C58 -> 6202.39 | D5: ='Data Sheet'!D58 -> 6968.49 | E5: ='Data Sheet'!E58 -> 7268.58 | F5: ='Data Sheet'!F58 -> 13722.7 | G5: ='Data Sheet'!G58 -> 14442.35 | H5: ='Data Sheet'!H58 -> 15049.78 | I5: ='Data Sheet'!I58 -> 16183.81 | ... K5: ='Data Sheet'!K58 -> 19902.13
A6: Borrowings | B6: ='Data Sheet'!B59 -> 1354.05 | C6: ='Data Sheet'!C59 -> 786.56 | D6: ='Data Sheet'!D59 -> 1067.58 | E6: ='Data Sheet'!E59 -> 1141.1 | F6: ='Data Sheet'!F59 -> 1586.32 | G6: ='Data Sheet'!G59 -> 1633.55 | H6: ='Data Sheet'!H59 -> 1412.01 | I6: ='Data Sheet'!I59 -> 1600.04 | ... K6: ='Data Sheet'!K59 -> 2392.68
A7: Other Liabilities | B7: ='Data Sheet'!B60 -> 2293.54 | C7: ='Data Sheet'!C60 -> 2499.35 | D7: ='Data Sheet'!D60 -> 2361.58 | E7: ='Data Sheet'!E60 -> 2407.89 | F7: ='Data Sheet'!F60 -> 3071.86 | G7: ='Data Sheet'!G60 -> 4049.76 | H7: ='Data Sheet'!H60 -> 4520.92 | I7: ='Data Sheet'!I60 -> 4885.74 | ... K7: ='Data Sheet'!K60 -> 9436.86
A8: Total | B8: ='Data Sheet'!B61 -> 9894.76 | C8: ='Data Sheet'!C61 -> 9551.41 | D8: ='Data Sheet'!D61 -> 10460.76 | E8: ='Data Sheet'!E61 -> 10880.68 | F8: ='Data Sheet'!F61 -> 18473.04 | G8: ='Data Sheet'!G61 -> 20217.82 | H8: ='Data Sheet'!H61 -> 21074.87 | I8: ='Data Sheet'!I61 -> 22762.49 | ... K8: ='Data Sheet'!K61 -> 31830.62
A10: Net Block | B10: ='Data Sheet'!B62 -> 4661.8 | C10: ='Data Sheet'!C62 -> 4572.59 | D10: ='Data Sheet'!D62 -> 4798.18 | E10: ='Data Sheet'!E62 -> 4913.31 | F10: ='Data Sheet'!F62 -> 11656.04 | G10: ='Data Sheet'!G62 -> 12023.13 | H10: ='Data Sheet'!H62 -> 12599.35 | I10: ='Data Sheet'!I62 -> 13070.04 | ... K10: ='Data Sheet'!K62 -> 21476.84
A11: Capital Work in Progress | B11: ='Data Sheet'!B63 -> 39.42 | C11: ='Data Sheet'!C63 -> 63.19 | D11: ='Data Sheet'!D63 -> 135.16 | E11: ='Data Sheet'!E63 -> 424.41 | F11: ='Data Sheet'!F63 -> 95.35 | G11: ='Data Sheet'!G63 -> 112.85 | H11: ='Data Sheet'!H63 -> 246.97 | I11: ='Data Sheet'!I63 -> 294.9 | ... K11: ='Data Sheet'!K63 -> 218.1
A12: Investments | B12: ='Data Sheet'!B64 -> 1365.94 | C12: ='Data Sheet'!C64 -> 1451.04 | D12: ='Data Sheet'!D64 -> 1161.33 | E12: ='Data Sheet'!E64 -> 1187.66 | F12: ='Data Sheet'!F64 -> 1322.85 | G12: ='Data Sheet'!G64 -> 805.89 | H12: ='Data Sheet'!H64 -> 797.28 | I12: ='Data Sheet'!I64 -> 1432.97 | ... K12: ='Data Sheet'!K64 -> 968.67
A13: Other Assets | B13: ='Data Sheet'!B65 -> 3827.6 | C13: ='Data Sheet'!C65 -> 3464.59 | D13: ='Data Sheet'!D65 -> 4366.09 | E13: ='Data Sheet'!E65 -> 4355.3 | F13: ='Data Sheet'!F65 -> 5398.8 | G13: ='Data Sheet'!G65 -> 7275.95 | H13: ='Data Sheet'!H65 -> 7431.27 | I13: ='Data Sheet'!I65 -> 7964.58 | ... K13: ='Data Sheet'!K65 -> 9167.01
A14: Total | B14: ='Data Sheet'!B66 -> 9894.76 | C14: ='Data Sheet'!C66 -> 9551.41 | D14: ='Data Sheet'!D66 -> 10460.76 | E14: ='Data Sheet'!E66 -> 10880.68 | F14: ='Data Sheet'!F66 -> 18473.04 | G14: ='Data Sheet'!G66 -> 20217.82 | H14: ='Data Sheet'!H66 -> 21074.87 | I14: ='Data Sheet'!I66 -> 22762.49 | ... K14: ='Data Sheet'!K66 -> 31830.62
A16: Working Capital | B16: =B13-B7 -> 1534.06 | C16: =C13-C7 -> 965.24 | D16: =D13-D7 -> 2004.51 | E16: =E13-E7 -> 1947.41 | F16: =F13-F7 -> 2326.94 | G16: =G13-G7 -> 3226.19 | H16: =H13-H7 -> 2910.35 | I16: =I13-I7 -> 3078.84 | ... K16: =K13-K7 -> -269.85
A17: Debtors | B17: ='Data Sheet'!B67 -> 592.43 | C17: ='Data Sheet'!C67 -> 592.45 | D17: ='Data Sheet'!D67 -> 648.28 | E17: ='Data Sheet'!E67 -> 680.55 | F17: ='Data Sheet'!F67 -> 922.41 | G17: ='Data Sheet'!G67 -> 761.32 | H17: ='Data Sheet'!H67 -> 835.15 | I17: ='Data Sheet'!I67 -> 798.33 | ... K17: ='Data Sheet'!K67 -> 869.79
A18: Inventory | B18: ='Data Sheet'!B68 -> 1629.01 | C18: ='Data Sheet'!C68 -> 1452.96 | D18: ='Data Sheet'!D68 -> 1448.31 | E18: ='Data Sheet'!E68 -> 1608.54 | F18: ='Data Sheet'!F68 -> 1712.03 | G18: ='Data Sheet'!G68 -> 2249.16 | H18: ='Data Sheet'!H68 -> 2266.51 | I18: ='Data Sheet'!I68 -> 2701.67 | ... K18: ='Data Sheet'!K68 -> 3599.91
A20: Debtor Days | B20: =IF('Profit & Loss'!B4>0,'Balance Sheet'!B17/('Profit & Loss'!B4/365),0) -> 32.582784 | C20: =IF('Profit & Loss'!C4>0,'Balance Sheet'!C17/('Profit & Loss'!C4/365),0) -> 31.896549 | D20: =IF('Profit & Loss'!D4>0,'Balance Sheet'!D17/('Profit & Loss'!D4/365),0) -> 34.719009 | E20: =IF('Profit & Loss'!E4>0,'Balance Sheet'!E17/('Profit & Loss'!E4/365),0) -> 34.255085 | F20: =IF('Profit & Loss'!F4>0,'Balance Sheet'!F17/('Profit & Loss'!F4/365),0) -> 34.934625 | G20: =IF('Profit & Loss'!G4>0,'Balance Sheet'!G17/('Profit & Loss'!G4/365),0) -> 23.951136 | H20: =IF('Profit & Loss'!H4>0,'Balance Sheet'!H17/('Profit & Loss'!H4/365),0) -> 24.532851 | I20: =IF('Profit & Loss'!I4>0,'Balance Sheet'!I17/('Profit & Loss'!I4/365),0) -> 21.141048 | ... K20: =IF('Profit & Loss'!K4>0,'Balance Sheet'!K17/('Profit & Loss'!K4/365),0) -> 18.019522
A21: Inventory Turnover | B21: =IF('Balance Sheet'!B18>0,'Profit & Loss'!B4/'Balance Sheet'!B18,0) -> 4.0739713 | C21: =IF('Balance Sheet'!C18>0,'Profit & Loss'!C4/'Balance Sheet'!C18,0) -> 4.6660266 | D21: =IF('Balance Sheet'!D18>0,'Profit & Loss'!D4/'Balance Sheet'!D18,0) -> 4.705726 | E21: =IF('Balance Sheet'!E18>0,'Profit & Loss'!E4/'Balance Sheet'!E18,0) -> 4.5081254 | F21: =IF('Balance Sheet'!F18>0,'Profit & Loss'!F4/'Balance Sheet'!F18,0) -> 5.6292355 | G21: =IF('Balance Sheet'!G18>0,'Profit & Loss'!G4/'Balance Sheet'!G18,0) -> 5.1583836 | H21: =IF('Balance Sheet'!H18>0,'Profit & Loss'!H4/'Balance Sheet'!H18,0) -> 5.4821598 | I21: =IF('Balance Sheet'!I18>0,'Profit & Loss'!I4/'Balance Sheet'!I18,0) -> 5.1017186 | ... K21: =IF('Balance Sheet'!K18>0,'Profit & Loss'!K4/'Balance Sheet'!K18,0) -> 4.8940946
A23: Return on Equity | B23: =IF(SUM('Balance Sheet'!B4:B5)>0,'Profit & Loss'!B12/SUM('Balance Sheet'!B4:B5),"") -> -0.00088360009 | C23: =IF(SUM('Balance Sheet'!C4:C5)>0,'Profit & Loss'!C12/SUM('Balance Sheet'!C4:C5),"") -> 0.062156252 | D23: =IF(SUM('Balance Sheet'!D4:D5)>0,'Profit & Loss'!D12/SUM('Balance Sheet'!D4:D5),"") -> 0.070476136 | E23: =IF(SUM('Balance Sheet'!E4:E5)>0,'Profit & Loss'!E12/SUM('Balance Sheet'!E4:E5),"") -> 0.055674749 | F23: =IF(SUM('Balance Sheet'!F4:F5)>0,'Profit & Loss'!F12/SUM('Balance Sheet'!F4:F5),"") -> 0.033280106 | G23: =IF(SUM('Balance Sheet'!G4:G5)>0,'Profit & Loss'!G12/SUM('Balance Sheet'!G4:G5),"") -> 0.058941788 | H23: =IF(SUM('Balance Sheet'!H4:H5)>0,'Profit & Loss'!H12/SUM('Balance Sheet'!H4:H5),"") -> 0.061800535 | I23: =IF(SUM('Balance Sheet'!I4:I5)>0,'Profit & Loss'!I12/SUM('Balance Sheet'!I4:I5),"") -> 0.073956592 | ... K23: =IF(SUM('Balance Sheet'!K4:K5)>0,'Profit & Loss'!K12/SUM('Balance Sheet'!K4:K5),"") -> 0.063920048
A24: Return on Capital Emp | C24: =IF((B4+B5+B6+C4+C5+C6)>0,('Profit & Loss'!C10+'Profit & Loss'!C9)*2/(B4+B5+B6+C4+C5+C6),"") -> 0.1028425 | D24: =IF((C4+C5+C6+D4+D5+D6)>0,('Profit & Loss'!D10+'Profit & Loss'!D9)*2/(C4+C5+C6+D4+D5+D6),"") -> 0.10505939 | E24: =IF((D4+D5+D6+E4+E5+E6)>0,('Profit & Loss'!E10+'Profit & Loss'!E9)*2/(D4+D5+D6+E4+E5+E6),"") -> 0.095001379 | F24: =IF((E4+E5+E6+F4+F5+F6)>0,('Profit & Loss'!F10+'Profit & Loss'!F9)*2/(E4+E5+E6+F4+F5+F6),"") -> 0.074326976 | G24: =IF((F4+F5+F6+G4+G5+G6)>0,('Profit & Loss'!G10+'Profit & Loss'!G9)*2/(F4+F5+F6+G4+G5+G6),"") -> 0.087411037 | H24: =IF((G4+G5+G6+H4+H5+H6)>0,('Profit & Loss'!H10+'Profit & Loss'!H9)*2/(G4+G5+G6+H4+H5+H6),"") -> 0.093439859 | I24: =IF((H4+H5+H6+I4+I5+I6)>0,('Profit & Loss'!I10+'Profit & Loss'!I9)*2/(H4+H5+H6+I4+I5+I6),"") -> 0.10924669 | J24: =IF((I4+I5+I6+J4+J5+J6)>0,('Profit & Loss'!J10+'Profit & Loss'!J9)*2/(I4+I5+I6+J4+J5+J6),"") -> 0.097593847

Sheet Cash Flow
A1: ='Balance Sheet'!A1 -> TATA CONSUMER PRODUCTS LTD | E1: =UPDATE | J1: SCREENER.IN
A3: Narration | B3: ='Data Sheet'!B81 -> 42460 | C3: ='Data Sheet'!C81 -> 42825 | D3: ='Data Sheet'!D81 -> 43190 | E3: ='Data Sheet'!E81 -> 43555 | F3: ='Data Sheet'!F81 -> 43921 | G3: ='Data Sheet'!G81 -> 44286 | H3: ='Data Sheet'!H81 -> 44651 | I3: ='Data Sheet'!I81 -> 45016 | ... K3: ='Data Sheet'!K81 -> 45747
A4: Cash from Operating Activity | B4: ='Data Sheet'!B82 -> 115.98 | C4: ='Data Sheet'!C82 -> 741.2 | D4: ='Data Sheet'!D82 -> 355.58 | E4: ='Data Sheet'!E82 -> 209.87 | F4: ='Data Sheet'!F82 -> 1082.23 | G4: ='Data Sheet'!G82 -> 1656.37 | H4: ='Data Sheet'!H82 -> 1515.81 | I4: ='Data Sheet'!I82 -> 1461.29 | ... K4: ='Data Sheet'!K82 -> 2056.65
A5: Cash from Investing Activity | B5: ='Data Sheet'!B83 -> 144.62 | C5: ='Data Sheet'!C83 -> 145.05 | D5: ='Data Sheet'!D83 -> -31.1 | E5: ='Data Sheet'!E83 -> 53.17 | F5: ='Data Sheet'!F83 -> -622.04 | G5: ='Data Sheet'!G83 -> -346.5 | H5: ='Data Sheet'!H83 -> -1317.11 | I5: ='Data Sheet'!I83 -> -833.61 | ... K5: ='Data Sheet'!K83 -> -2303.48
A6: Cash from Financing Activity | B6: ='Data Sheet'!B84 -> -281.8 | C6: ='Data Sheet'!C84 -> -815.84 | D6: ='Data Sheet'!D84 -> -30.39 | E6: ='Data Sheet'!E84 -> -223.73 | F6: ='Data Sheet'!F84 -> -308.33 | G6: ='Data Sheet'!G84 -> -426.03 | H6: ='Data Sheet'!H84 -> -994.77 | I6: ='Data Sheet'!I84 -> -714.4 | ... K6: ='Data Sheet'!K84 -> 452.7
A7: Net Cash Flow | B7: ='Data Sheet'!B85 -> -21.2 | C7: ='Data Sheet'!C85 -> 70.41 | D7: ='Data Sheet'!D85 -> 294.09 | E7: ='Data Sheet'!E85 -> 39.31 | F7: ='Data Sheet'!F85 -> 151.86 | G7: ='Data Sheet'!G85 -> 883.84 | H7: ='Data Sheet'!H85 -> -796.07 | I7: ='Data Sheet'!I85 -> -86.72 | ... K7: ='Data Sheet'!K85 -> 205.87

Sheet Customization
A1: How to use it?
A3: You can customize this workbook as you want.
B4: You can add custom formating, add conditional formating, add your own formulas… do ANYTHING.
B5: Please don't edit the "Data Sheet" only.
A7: After customization, you can upload this back on Screener.
B8: Upload on: | C8: https://www.screener.in/excel/
A10: Download your customized workbooks now onwards.
B11: Now whenever you will "Export to excel" from Screener, it will export your customized file.
A14: TESTING:
B15: This is a testing feature currently.
B16: You can report any formula errors on the worksheet at: support@screener.in

Sheet Cash Flow Data
C2: 41609 | D2: 41974 | E2: 42339 | F2: 42705 | G2: 43070 | H2: 43435 | I2: 43800 | J2: 44166 | K2: 44531 | L2: 44896 | M2: 45261 | N2: 45627
B3: Cash from Operating Activity - | C3: 297 | D3: 431 | E3: 555 | F3: 826 | G3: 620 | H3: 1000 | I3: 1308 | J3: 1012 | K3: 1231 | L3: 1790 | M3: 2391 | N3: 3381
B4: Profit from operations | C4: 313 | D4: 397 | E4: 645 | F4: 820 | G4: 873 | H4: 1123 | I4: 1513 | J4: 1200 | K4: 1624 | L4: 2749 | M4: 3732 | N4: 4778
B5: Receivables | C5: 21 | D5: -38 | E5: 0 | F5: 7 | G5: -34 | H5: -13 | I5: -32 | J5: -76 | K5: 15 | L5: -123 | M5: -73 | N5: -133
B6: Inventory | C6: -16 | D6: -43 | E6: -135 | F6: -39 | G6: 45 | H6: -151 | I6: -185 | J6: -47 | K6: -519 | L6: -557 | M6: -160 | N6: -479
B7: Payables | C7: -49 | D7: 86 | E7: 149 | F7: 0 | G7: 0 | H7: 0 | I7: 0 | J7: 0 | K7: 0 | L7: 0 | M7: 0 | N7: 0
B8: Loans Advances | C8: 32 | D8: 39 | E8: -56 | F8: 0 | G8: 0 | H8: 0 | I8: 0 | J8: 0 | K8: 0 | L8: 0 | M8: 0 | N8: 0
B9: Other WC items | C9: 0 | D9: 0 | E9: 0 | F9: 95 | G9: -207 | H9: 114 | I9: 132 | J9: 12 | K9: 236 | L9: 95 | M9: -440 | N9: -57
B10: Working capital changes | C10: -12 | D10: 44 | E10: -42 | F10: 64 | G10: -197 | H10: -50 | I10: -85 | J10: -111 | K10: -269 | L10: -585 | M10: -673 | N10: -669
B11: Direct taxes | C11: -4 | D11: -11 | E11: -48 | F11: -58 | G11: -57 | H11: -73 | I11: -120 | J11: -78 | K11: -124 | L11: -373 | M11: -668 | N11: -728
B12: Cash from Investing Activity - | C12: -574 | D12: -500 | E12: -300 | F12: -1048 | G12: -746 | H12: -937 | I12: -2320 | J12: -472 | K12: -1008 | L12: -1769 | M12: -3288 | N12: -4311
B13: Fixed assets purchased | C13: -578 | D13: -220 | E13: -269 | F13: -792 | G13: -533 | H13: -859 | I13: -754 | J13: -560 | K13: -835 | L13: -1801 | M13: -3264 | N13: -3779
B14: Fixed assets sold | C14: 0 | D14: 0 | E14: 4 | F14: 12 | G14: 17 | H14: 50 | I14: 21 | J14: 24 | K14: 19 | L14: 51 | M14: 70 | N14: 39
... B34: Net Cash Flow | C34: -2 | D34: -11 | E34: 19 | F34: 8 | G34: 32 | H34: -22 | I34: 95 | J34: -33 | K34: 46 | L34: 4 | M34: 88 | N34: 2024
B39: Operating Activities
B40: Profit from operations | C40: 645 | D40: 820 | E40: 873 | F40: 1123 | G40: 1513 | H40: 1200 | I40: 1624 | J40: 2749 | K40: 3732 | L40: 4778
B41: Receivables | C41: 0 | D41: 7 | E41: -34 | F41: -13 | G41: -32 | H41: -76 | I41: 15 | J41: -123 | K41: -73 | L41: -133
B42: Inventory | C42: -135 | D42: -39 | E42: 45 | F42: -151 | G42: -185 | H42: -47 | I42: -519 | J42: -557 | K42: -160 | L42: -479
B43: Payables | C43: 149 | D43: 0 | E43: 0 | F43: 0 | G43: 0 | H43: 0 | I43: 0 | J43: 0 | K43: 0 | L43: 0
B44: Loans Advances | C44: -56 | D44: 0 | E44: 0 | F44: 0 | G44: 0 | H44: 0 | I44: 0 | J44: 0 | K44: 0 | L44: 0
B45: Other WC items | C45: 0 | D45: 95 | E45: -207 | F45: 114 | G45: 132 | H45: 12 | I45: 236 | J45: 95 | K45: -440 | L45: -57
B46: Working capital changes | C46: -42 | D46: 64 | E46: -197 | F46: -50 | G46: -85 | H46: -111 | I46: -269 | J46: -585 | K46: -673 | L46: -669
B47: Direct taxes | C47: -48 | D47: -58 | E47: -57 | F47: -73 | G47: -120 | H47: -78 | I47: -124 | J47: -373 | K47: -668 | L47: -728
B48: Cash from Operating Activities | C48: 513 | D48: 889 | E48: 423 | F48: 950 | G48: 1223 | H48: 900 | I48: 963 | J48: 1206 | K48: 1718 | L48: 2712
B50: Investing Activities
B51: Fixed assets purchased | C51: -269 | D51: -792 | E51: -533 | F51: -859 | G51: -754 | H51: -560 | I51: -835 | J51: -1801 | K51: -3264 | L51: -3779
B52: Fixed assets sold | C52: 4 | D52: 12 | E52: 17 | F52: 50 | G52: 21 | H52: 24 | I52: 19 | J52: 51 | K52: 70 | L52: 39
B53: Investments purchased | C53: -550 | D53: -35 | E53: -35 | F53: 0 | G53: -73 | H53: 0 | I53: 0 | J53: 0 | K53: 0 | L53: 0
B54: Investments sold | C54: 512 | D54: 35 | E54: 35 | F54: 0 | G54: 73 | H54: 0 | I54: 0 | J54: 0 | K54: 0 | L54: 2
B55: Interest received | C55: 6 | D55: 8 | E55: 5 | F55: 6 | G55: 5 | H55: 9 | I55: 13 | J55: 23 | K55: 22 | L55: 28
B56: Dividends received | C56: 0 | D56: 0 | E56: 0 | F56: 0 | G56: 0 | H56: 0 | I56: 0 | J56: 0 | K56: 0 | L56: 0
B57: Investment in group cos | C57: 0 | D57: 0 | E57: 0 | F57: 0 | G57: 0 | H57: 0 | I57: 0 | J57: 0 | K57: -22 | L57: -40
B58: Acquisition of companies | C58: 0 | D58: -276 | E58: -212 | F58: 0 | G58: -8 | H58: 0 | I58: 0 | J58: 0 | K58: -10 | L58: -200
B59: Other investing items | C59: -4 | D59: 0 | E59: -23 | F59: -134 | G59: -1583 | H59: 55 | I59: -205 | J59: -42 | K59: -85 | L59: -361
B60: Cash from Investing Activities | C60: -301 | D60: -1048 | E60: -746 | F60: -937 | G60: -2319 | H60: -472 | I60: -1008 | J60: -1769 | K60: -3289 | L60: -4311
B62: Financing Activities
B63: Proceeds from shares | C63: 0 | D63: 701 | E63: 4 | F63: 1 | G63: 900 | H63: 0 | I63: 0 | J63: 0 | K63: 4 | L63: 7512
B64: Proceeds from debentures | C64: 320 | D64: 180 | E64: 300 | F64: 0 | G64: 0 | H64: 0 | I64: 0 | J64: 0 | K64: 0 | L64: 0
B65: Redemption of debentures | C65: 0 | D65: -500 | E65: 0 | F65: -300 | G65: 0 | H65: 0 | I65: 0 | J65: 0 | K65: 0 | L65: 0
B66: Proceeds from borrowings | C66: 332 | D66: 0 | E66: 0 | F66: 1400 | G66: 1958 | H66: 1020 | I66: 855 | J66: 1478 | K66: 2783 | L66: 1957
B67: Repayment of borrowings | C67: -997 | D67: 71 | E67: -57 | F67: -644 | G67: -1310 | H67: -1233 | I67: -726 | J67: -1138 | K67: -1277 | L67: -5508
B68: Interest paid fin | C68: -141 | D68: -219 | E68: -156 | F68: -189 | G68: -303 | H68: -277 | I68: -179 | J68: -172 | K68: -269 | L68: -465
B69: Dividends paid | C69: 0 | D69: 0 | E69: -46 | F69: -46 | G69: -69 | H69: -72 | I69: -108 | J69: -162 | K69: -227 | L69: -325
B70: Financial liabilities | C70: 0 | D70: 0 | E70: 0 | F70: 0 | G70: 0 | H70: -11 | I70: -19 | J70: -23 | K70: -30 | L70: -156
B71: Share application money | C71: 0 | D71: 0 | E71: 0 | F71: 0 | G71: 0 | H71: 0 | I71: 0 | J71: 0 | K71: 0 | L71: 0
B72: Application money refund | C72: 0 | D72: -21 | E72: 0 | F72: 0 | G72: 0 | H72: 0 | I72: 0 | J72: 0 | K72: 0 | L72: 0
B73: Other financing items | C73: 250 | D73: 17 | E73: 113 | F73: -308 | G73: -69 | H73: 0 | I73: 0 | J73: 0 | K73: 0 | L73: -61
B74: Cash from Financial Activities | C74: -236 | D74: 229 | E74: 158 | F74: -86 | G74: 1107 | H74: -573 | I74: -177 | J74: -17 | K74: 984 | L74: 2954
B76: Net Cash Flow | C76: -24 | D76: 70 | E76: -165 | F76: -73 | G76: 11 | H76: -145 | I76: -222 | J76: -580 | K76: -587 | L76: 1355

Sheet Data Sheet
A1: COMPANY NAME | B1: TATA CONSUMER PRODUCTS LTD | E1: =IF(B2<>B3, "A NEW VERSION OF THE WORKSHEET IS AVAILABLE", "")
A2: LATEST VERSION | B2: 2.1 | E2: PLEASE DO NOT MAKE ANY CHANGES TO THIS SHEET
A3: CURRENT VERSION | B3: 2.1
A5: META
A6: Number of shares | B6: =IF(B9>0, B9/B8, 0) -> 98.616099
A7: Face Value | B7: 1
A8: Current Price | B8: 1139.2
A9: Market Capitalization | B9: 112343.46
A15: PROFIT & LOSS
A16: Report Date | B16: 42460 | C16: 42825 | D16: 43190 | E16: 43555 | F16: 43921 | G16: 44286 | H16: 44651 | I16: 45016 | J16: 45382 | K16: 45747
A17: Sales | B17: 6636.54 | C17: 6779.55 | D17: 6815.35 | E17: 7251.5 | F17: 9637.42 | G17: 11602.03 | H17: 12425.37 | I17: 13783.16 | J17: 15205.85 | K17: 17618.3
A18: Raw Material Cost | B18: 3601.49 | C18: 3165.65 | D18: 3746.11 | E18: 4022.05 | F18: 5402.9 | G18: 6367.79 | H18: 6323.22 | I18: 7107.06 | J18: 7364.06 | K18: 8986.68
A19: Change in Inventory | B19: -20.11 | C19: 0.69 | D19: 46.8 | E19: 14.41 | F19: -7.78 | G19: 149.54 | H19: 39.78 | I19: 273.88 | J19: 121.6 | K19: 362.49
A20: Power and Fuel | B20: 81.26 | C20: 83.19 | D20: 87.07 | E20: 89.28 | F20: 103.84 | G20: 97.36 | H20: 123.9 | I20: 149.43 | J20: 156.9 | K20: 156.21
A21: Other Mfr. Exp | B21: 190.32 | C21: 597.61 | D21: 194.69 | E21: 209.59 | F21: 238.47 | G21: 941.75 | H21: 1139.59 | I21: 1578.2 | J21: 1696.28 | K21: 1882.25
A22: Employee Cost | B22: 805.06 | C22: 834.95 | D22: 821.37 | E22: 806.3 | F22: 884.8 | G22: 970.23 | H22: 1048 | I22: 1120.36 | J22: 1258.59 | K22: 1430.1
A23: Selling and admin | B23: 922.88 | C23: 926.92 | D23: 857.64 | E23: 968.23 | F23: 1278.16 | G23: 1421.46 | H23: 1691.83 | I23: 1785.26 | J23: 1927.15 | K23: 2253.37
A24: Other Expenses | B24: 649.51 | C24: 380.79 | D24: 316.36 | E24: 384.55 | F24: 429.32 | G24: 409.22 | H24: 419.83 | I24: 460.26 | J24: 640.37 | K24: 792.83
A25: Other Income | B25: 37.54 | C25: 88.4 | D25: 73.02 | E25: 123.84 | F25: -163.2 | G25: 90.73 | H25: 88 | I25: 328.33 | J25: -81.42 | K25: 188.14
A26: Depreciation | B26: 116.79 | C26: 126.04 | D26: 116.04 | E26: 122.57 | F26: 241.71 | G26: 254.74 | H26: 278.01 | I26: 304.08 | J26: 377.15 | K26: 600.74
A27: Interest | B27: 116.9 | C27: 91.53 | D27: 42.76 | E27: 52.47 | F27: 77.86 | G27: 68.69 | H27: 72.78 | I27: 87.16 | J27: 129.81 | K27: 290.2
... A31: Dividend Amount | B31: 142 | C31: 148.31 | D31: 148.31 | E31: 157.78 | F31: 248.83 | G31: 373.25 | H31: 557.57 | I31: 785 | J31: 738.42 | K31: 816.34
A33: EBITDA | B33: =B30+B29+B27+B26 -> 428.18 | C33: =C30+C29+C27+C26 -> 805.32 | D33: =D30+D29+D27+D26 -> 840.23 | E33: =E30+E29+E27+E26 -> 844.11 | F33: =F30+F29+F27+F26 -> 1053.52 | G33: =G30+G29+G27+G26 -> 1497.39 | H33: =H30+H29+H27+H26 -> 1663.61 | I33: =I30+I29+I27+I26 -> 2042.05 | ... K33: =K30+K29+K27+K26 -> 2565.65
A40: Quarters
A41: Report Date | B41: 45199 | C41: 45291 | D41: 45382 | E41: 45473 | F41: 45565 | G41: 45657 | H41: 45747 | I41: 45838 | J41: 45930 | K41: 46022
A42: Sales | B42: 3733.78 | C42: 3803.92 | D42: 3926.94 | E42: 4352.07 | F42: 4214.45 | G42: 4443.56 | H42: 4608.22 | I42: 4778.91 | J42: 4965.9 | K42: 5112
A43: Expenses | B43: 3196.69 | C43: 3231.54 | D43: 3297.34 | E43: 3684.69 | F43: 3588.16 | G43: 3878.83 | H43: 3987.27 | I43: 4171.97 | J43: 4294.12 | K43: 4391.33
A44: Other Income | B44: 75.28 | C44: -31.94 | D44: -177.35 | E44: 22.07 | F44: 18.8 | G44: 45.44 | H44: 101.83 | I44: 41.17 | J44: 38.01 | K44: 10.15
A45: Depreciation | B45: 93.93 | C45: 85.51 | D45: 115.76 | E45: 148 | F45: 149.33 | G45: 150.32 | H45: 153.09 | I45: 148.93 | J45: 153.28 | K45: 159.29
A46: Interest | B46: 27.56 | C46: 33.19 | D46: 42.83 | E46: 93.6 | F46: 98.69 | G46: 57.92 | H46: 39.99 | I46: 33.76 | J46: 33.23 | K46: 31.62
A47: Profit before tax | B47: 490.88 | C47: 421.74 | D47: 293.66 | E47: 447.85 | F47: 397.07 | G47: 401.93 | H47: 529.7 | I47: 465.42 | J47: 523.28 | K47: 539.91
A48: Tax | B48: 131.7 | C48: 106.21 | D48: 25.95 | E48: 133.7 | F48: 37.73 | G48: 102.18 | H48: 122.63 | I48: 118.98 | J48: 126.23 | K48: 137.12
A49: Net profit | B49: 338.24 | C49: 278.87 | D49: 216.63 | E49: 290.32 | F49: 364.42 | G49: 278.88 | H49: 344.85 | I49: 334.15 | J49: 404.46 | K49: 384.61
A50: Operating Profit | B50: 537.09 | C50: 572.38 | D50: 629.6 | E50: 667.38 | F50: 626.29 | G50: 564.73 | H50: 620.95 | I50: 606.94 | J50: 671.78 | K50: 720.67
A55: BALANCE SHEET
A56: Report Date | B56: 42460 | C56: 42825 | D56: 43190 | E56: 43555 | F56: 43921 | G56: 44286 | H56: 44651 | I56: 45016 | J56: 45382 | K56: 45747
A57: Equity Share Capital | B57: 63.11 | C57: 63.11 | D57: 63.11 | E57: 63.11 | F57: 92.16 | G57: 92.16 | H57: 92.16 | I57: 92.9 | J57: 95.28 | K57: 98.95
A58: Reserves | B58: 6184.06 | C58: 6202.39 | D58: 6968.49 | E58: 7268.58 | F58: 13722.7 | G58: 14442.35 | H58: 15049.78 | I58: 16183.81 | J58: 15961.51 | K58: 19902.13
A59: Borrowings | B59: 1354.05 | C59: 786.56 | D59: 1067.58 | E59: 1141.1 | F59: 1586.32 | G59: 1633.55 | H59: 1412.01 | I59: 1600.04 | J59: 3477.22 | K59: 2392.68
A60: Other Liabilities | B60: 2293.54 | C60: 2499.35 | D60: 2361.58 | E60: 2407.89 | F60: 3071.86 | G60: 4049.76 | H60: 4520.92 | I60: 4885.74 | J60: 8344.78 | K60: 9436.86
A61: Total | B61: 9894.76 | C61: 9551.41 | D61: 10460.76 | E61: 10880.68 | F61: 18473.04 | G61: 20217.82 | H61: 21074.87 | I61: 22762.49 | J61: 27878.79 | K61: 31830.62
A62: Net Block | B62: 4661.8 | C62: 4572.59 | D62: 4798.18 | E62: 4913.31 | F62: 11656.04 | G62: 12023.13 | H62: 12599.35 | I62: 13070.04 | J62: 19357.9 | K62: 21476.84
A63: Capital Work in Progress | B63: 39.42 | C63: 63.19 | D63: 135.16 | E63: 424.41 | F63: 95.35 | G63: 112.85 | H63: 246.97 | I63: 294.9 | J63: 189.6 | K63: 218.1
A64: Investments | B64: 1365.94 | C64: 1451.04 | D64: 1161.33 | E64: 1187.66 | F64: 1322.85 | G64: 805.89 | H64: 797.28 | I64: 1432.97 | J64: 870.55 | K64: 968.67
A65: Other Assets | B65: 3827.6 | C65: 3464.59 | D65: 4366.09 | E65: 4355.3 | F65: 5398.8 | G65: 7275.95 | H65: 7431.27 | I65: 7964.58 | J65: 7460.74 | K65: 9167.01
A66: Total | B66: 9894.76 | C66: 9551.41 | D66: 10460.76 | E66: 10880.68 | F66: 18473.04 | G66: 20217.82 | H66: 21074.87 | I66: 22762.49 | J66: 27878.79 | K66: 31830.62
A67: Receivables | B67: 592.43 | C67: 592.45 | D67: 648.28 | E67: 680.55 | F67: 922.41 | G67: 761.32 | H67: 835.15 | I67: 798.33 | J67: 896.75 | K67: 869.79
... A70: No. of Equity Shares | B70: 631129729 | C70: 631129729 | D70: 631129729 | E70: 631129729 | F70: 921551715 | G70: 921551715 | H70: 921551715 | I70: 929011650 | J70: 952834816 | K70: 989498558
A71: New Bonus Shares
A72: Face value | B72: 1 | C72: 1 | D72: 1 | E72: 1 | F72: 1 | G72: 1 | H72: 1 | I72: 1 | J72: 1 | K72: 1
A74: Other Assets | B74: =B65-SUM(B67:B69) -> 1105.13 | C74: =C65-SUM(C67:C69) -> 844.36 | D74: =D65-SUM(D67:D69) -> 1031.36 | E74: =E65-SUM(E67:E69) -> 1032.6 | F74: =F65-SUM(F67:F69) -> 1142.9 | G74: =G65-SUM(G67:G69) -> 1190.59 | H74: =H65-SUM(H67:H69) -> 1729.72 | I74: =I65-SUM(I67:I69) -> 1667.64 | ... K74: =K65-SUM(K67:K69) -> 1879.45
A75: Total Assets | B75: =SUM(B62:B64,B74,B67:B69) -> 9894.76 | C75: =SUM(C62:C64,C74,C67:C69) -> 9551.41 | D75: =SUM(D62:D64,D74,D67:D69) -> 10460.76 | E75: =SUM(E62:E64,E74,E67:E69) -> 10880.68 | F75: =SUM(F62:F64,F74,F67:F69) -> 18473.04 | G75: =SUM(G62:G64,G74,G67:G69) -> 20217.82 | H75: =SUM(H62:H64,H74,H67:H69) -> 21074.87 | I75: =SUM(I62:I64,I74,I67:I69) -> 22762.49 | ... K75: =SUM(K62:K64,K74,K67:K69) -> 31830.62
A80: CASH FLOW:
A81: Report Date | B81: 42460 | C81: 42825 | D81: 43190 | E81: 43555 | F81: 43921 | G81: 44286 | H81: 44651 | I81: 45016 | J81: 45382 | K81: 45747
A82: Cash from Operating Activity | B82: 115.98 | C82: 741.2 | D82: 355.58 | E82: 209.87 | F82: 1082.23 | G82: 1656.37 | H82: 1515.81 | I82: 1461.29 | J82: 1936.68 | K82: 2056.65
A83: Cash from Investing Activity | B83: 144.62 | C83: 145.05 | D83: -31.1 | E83: 53.17 | F83: -622.04 | G83: -346.5 | H83: -1317.11 | I83: -833.61 | J83: -1910.77 | K83: -2303.48
A84: Cash from Financing Activity | B84: -281.8 | C84: -815.84 | D84: -30.39 | E84: -223.73 | F84: -308.33 | G84: -426.03 | H84: -994.77 | I84: -714.4 | J84: 255.55 | K84: 452.7
A85: Net Cash Flow | B85: -21.2 | C85: 70.41 | D85: 294.09 | E85: 39.31 | F85: 151.86 | G85: 883.84 | H85: -796.07 | I85: -86.72 | J85: 281.46 | K85: 205.87
A90: PRICE: | B90: 119.76 | C90: 148.7 | D90: 255.57 | E90: 201.45 | F90: 291.23 | G90: 631.06 | H90: 767.86 | I90: 700.15 | J90: 1082.74 | K90: 1001.9
A92: DERIVED:
A93: Adjusted Equity Shares in Cr | B93: 65.54 | C93: 65.54 | D93: 65.54 | E93: 65.54 | F93: 95.7 | G93: 95.7 | H93: 95.7 | I93: 96.47 | J93: 98.95 | K93: 98.95

Sheet Historical FS
B2: ="Historical Financial Statements -"&'Data Sheet'!B1 -> Historical Financial Statements -TATA CONSUMER PRODUCTS LTD
B3: Years | C3: ='Data Sheet'!B16 -> 42460 | D3: ='Data Sheet'!C16 -> 42825 | E3: ='Data Sheet'!D16 -> 43190 | F3: ='Data Sheet'!E16 -> 43555 | G3: ='Data Sheet'!F16 -> 43921 | H3: ='Data Sheet'!G16 -> 44286 | I3: ='Data Sheet'!H16 -> 44651 | J3: ='Data Sheet'!I16 -> 45016 | ... L3: ='Data Sheet'!K16 -> 45747 | M3: LTM
A5: # | B5: Income Statement
B6: Sales | C6: ='Data Sheet'!B17 -> 6636.54 | D6: ='Data Sheet'!C17 -> 6779.55 | E6: ='Data Sheet'!D17 -> 6815.35 | F6: ='Data Sheet'!E17 -> 7251.5 | G6: ='Data Sheet'!F17 -> 9637.42 | H6: ='Data Sheet'!G17 -> 11602.03 | I6: ='Data Sheet'!H17 -> 12425.37 | J6: ='Data Sheet'!I17 -> 13783.16 | ... L6: ='Data Sheet'!K17 -> 17618.3 | M6: =SUM('Data Sheet'!H42:K42) -> 19465.03
B7: Sales Growth | C7: - | D7: =D6/C6-1 -> 0.021548879 | E7: =E6/D6-1 -> 0.0052805865 | F7: =F6/E6-1 -> 0.063995246 | G7: =G6/F6-1 -> 0.32902434 | H7: =H6/G6-1 -> 0.20385228 | I7: =I6/H6-1 -> 0.070965167 | J7: =J6/I6-1 -> 0.10927562 | K7: =K6/J6-1 -> 0.10321944 | ... M7: =M6/L6-1 -> 0.10481885
B9: COGS | C9: =IFERROR(SUM('Data Sheet'!B18,'Data Sheet'!B20:B21),0) -> 3873.07 | D9: =IFERROR(SUM('Data Sheet'!C18,'Data Sheet'!C20:C21),0) -> 3846.45 | E9: =IFERROR(SUM('Data Sheet'!D18,'Data Sheet'!D20:D21),0) -> 4027.87 | F9: =IFERROR(SUM('Data Sheet'!E18,'Data Sheet'!E20:E21),0) -> 4320.92 | G9: =IFERROR(SUM('Data Sheet'!F18,'Data Sheet'!F20:F21),0) -> 5745.21 | H9: =IFERROR(SUM('Data Sheet'!G18,'Data Sheet'!G20:G21),0) -> 7406.9 | I9: =IFERROR(SUM('Data Sheet'!H18,'Data Sheet'!H20:H21),0) -> 7586.71 | J9: =IFERROR(SUM('Data Sheet'!I18,'Data Sheet'!I20:I21),0) -> 8834.69 | ... L9: =IFERROR(SUM('Data Sheet'!K18,'Data Sheet'!K20:K21),0) -> 11025.14 | M9: =IFERROR(SUM('Data Sheet'!H43:K43),0) -> 16844.69
B10: COGS % Sales | C10: =IFERROR(C9/C6,0) -> 0.58359778 | D10: =IFERROR(D9/D6,0) -> 0.56736067 | E10: =IFERROR(E9/E6,0) -> 0.59099973 | F10: =IFERROR(F9/F6,0) -> 0.59586568 | G10: =IFERROR(G9/G6,0) -> 0.59613569 | H10: =IFERROR(H9/H6,0) -> 0.63841414 | I10: =IFERROR(I9/I6,0) -> 0.61058222 | J10: =IFERROR(J9/J6,0) -> 0.64097711 | ... M10: =IFERROR(M9/M6,0) -> 0.86538218
B12: Gross Profit | C12: =IFERROR(C6-C9,0) -> 2763.47 | D12: =IFERROR(D6-D9,0) -> 2933.1 | E12: =IFERROR(E6-E9,0) -> 2787.48 | F12: =IFERROR(F6-F9,0) -> 2930.58 | G12: =IFERROR(G6-G9,0) -> 3892.21 | H12: =IFERROR(H6-H9,0) -> 4195.13 | I12: =IFERROR(I6-I9,0) -> 4838.66 | J12: =IFERROR(J6-J9,0) -> 4948.47 | ... M12: =IFERROR(M6-M9,0) -> 2620.34
B13: Gross Margins | C13: =IFERROR(C12/C6,0) -> 0.41640222 | D13: =IFERROR(D12/D6,0) -> 0.43263933 | E13: =IFERROR(E12/E6,0) -> 0.40900027 | F13: =IFERROR(F12/F6,0) -> 0.40413432 | G13: =IFERROR(G12/G6,0) -> 0.40386431 | H13: =IFERROR(H12/H6,0) -> 0.36158586 | I13: =IFERROR(I12/I6,0) -> 0.38941778 | J13: =IFERROR(J12/J6,0) -> 0.35902289 | ... M13: =IFERROR(M12/M6,0) -> 0.13461782
B15: Selling & General Expenses | C15: =IFERROR(SUM('Data Sheet'!B23:B24),0) -> 1572.39 | D15: =IFERROR(SUM('Data Sheet'!C23:C24),0) -> 1307.71 | E15: =IFERROR(SUM('Data Sheet'!D23:D24),0) -> 1174 | F15: =IFERROR(SUM('Data Sheet'!E23:E24),0) -> 1352.78 | G15: =IFERROR(SUM('Data Sheet'!F23:F24),0) -> 1707.48 | H15: =IFERROR(SUM('Data Sheet'!G23:G24),0) -> 1830.68 | I15: =IFERROR(SUM('Data Sheet'!H23:H24),0) -> 2111.66 | J15: =IFERROR(SUM('Data Sheet'!I23:I24),0) -> 2245.52 | ... L15: =IFERROR(SUM('Data Sheet'!K23:K24),0) -> 3046.2 | M15: -
B16: S&G Exp % Sales | C16: =IFERROR(C15/C6,0) -> 0.23692918 | D16: =IFERROR(D15/D6,0) -> 0.19289038 | E16: =IFERROR(E15/E6,0) -> 0.17225821 | F16: =IFERROR(F15/F6,0) -> 0.18655175 | G16: =IFERROR(G15/G6,0) -> 0.1771719 | H16: =IFERROR(H15/H6,0) -> 0.15778963 | I16: =IFERROR(I15/I6,0) -> 0.16994745 | J16: =IFERROR(J15/J6,0) -> 0.16291765 | ... M16: =IFERROR(M15/M6,0) -> 0
B18: EBITDA | C18: =IFERROR(C12-C15,0) -> 1191.08 | D18: =IFERROR(D12-D15,0) -> 1625.39 | E18: =IFERROR(E12-E15,0) -> 1613.48 | F18: =IFERROR(F12-F15,0) -> 1577.8 | G18: =IFERROR(G12-G15,0) -> 2184.73 | H18: =IFERROR(H12-H15,0) -> 2364.45 | I18: =IFERROR(I12-I15,0) -> 2727 | J18: =IFERROR(J12-J15,0) -> 2702.95 | ... L18: =IFERROR(L12-L15,0) -> 3546.96 | M18: =IFERROR(SUM('Data Sheet'!H50:K50,'Data Sheet'!H45:K45),0) -> 3234.93
B19: EBITDA Margins | C19: =IFERROR(C18/C6,0) -> 0.17947304 | D19: =IFERROR(D18/D6,0) -> 0.23974895 | E19: =IFERROR(E18/E6,0) -> 0.23674206 | F19: =IFERROR(F18/F6,0) -> 0.21758257 | G19: =IFERROR(G18/G6,0) -> 0.22669241 | H19: =IFERROR(H18/H6,0) -> 0.20379623 | I19: =IFERROR(I18/I6,0) -> 0.21947033 | J19: =IFERROR(J18/J6,0) -> 0.19610525 | ... M19: =IFERROR(M18/M6,0) -> 0.16619188
B21: Interest | C21: =IFERROR('Data Sheet'!B27,0) -> 116.9 | D21: =IFERROR('Data Sheet'!C27,0) -> 91.53 | E21: =IFERROR('Data Sheet'!D27,0) -> 42.76 | F21: =IFERROR('Data Sheet'!E27,0) -> 52.47 | G21: =IFERROR('Data Sheet'!F27,0) -> 77.86 | H21: =IFERROR('Data Sheet'!G27,0) -> 68.69 | I21: =IFERROR('Data Sheet'!H27,0) -> 72.78 | J21: =IFERROR('Data Sheet'!I27,0) -> 87.16 | ... L21: =IFERROR('Data Sheet'!K27,0) -> 290.2 | M21: =IFERROR(SUM('Data Sheet'!H46:K46),0) -> 138.6
B22: Interest % Sales | C22: =IFERROR(C21/C6,0) -> 0.0176146 | D22: =IFERROR(D21/D6,0) -> 0.013500896 | E22: =IFERROR(E21/E6,0) -> 0.0062740725 | F22: =IFERROR(F21/F6,0) -> 0.0072357443 | G22: =IFERROR(G21/G6,0) -> 0.0080789257 | H22: =IFERROR(H21/H6,0) -> 0.0059205156 | I22: =IFERROR(I21/I6,0) -> 0.0058573708 | J22: =IFERROR(J21/J6,0) -> 0.0063236587 | ... M22: =IFERROR(M21/M6,0) -> 0.0071204617
B24: Depreciation | C24: =IFERROR('Data Sheet'!B26,0) -> 116.79 | D24: =IFERROR('Data Sheet'!C26,0) -> 126.04 | E24: =IFERROR('Data Sheet'!D26,0) -> 116.04 | F24: =IFERROR('Data Sheet'!E26,0) -> 122.57 | G24: =IFERROR('Data Sheet'!F26,0) -> 241.71 | H24: =IFERROR('Data Sheet'!G26,0) -> 254.74 | I24: =IFERROR('Data Sheet'!H26,0) -> 278.01 | J24: =IFERROR('Data Sheet'!I26,0) -> 304.08 | ... L24: =IFERROR('Data Sheet'!K26,0) -> 600.74 | M24: =IFERROR(SUM('Data Sheet'!H45:K45),0) -> 614.59
B25: Depreciation % Sales | C25: =IFERROR(C24/C6,0) -> 0.017598025 | D25: =IFERROR(D24/D6,0) -> 0.018591204 | E25: =IFERROR(E24/E6,0) -> 0.017026272 | F25: =IFERROR(F24/F6,0) -> 0.01690271 | G25: =IFERROR(G24/G6,0) -> 0.025080364 | H25: =IFERROR(H24/H6,0) -> 0.021956502 | I25: =IFERROR(I24/I6,0) -> 0.022374384 | J25: =IFERROR(J24/J6,0) -> 0.022061704 | ... M25: =IFERROR(M24/M6,0) -> 0.031574059
B27: Earnings Before Tax | C27: =IFERROR(C18-1*SUM(C24,C21),0) -> 957.39 | D27: =IFERROR(D18-1*SUM(D24,D21),0) -> 1407.82 | E27: =IFERROR(E18-1*SUM(E24,E21),0) -> 1454.68 | F27: =IFERROR(F18-1*SUM(F24,F21),0) -> 1402.76 | G27: =IFERROR(G18-1*SUM(G24,G21),0) -> 1865.16 | H27: =IFERROR(H18-1*SUM(H24,H21),0) -> 2041.02 | I27: =IFERROR(I18-1*SUM(I24,I21),0) -> 2376.21 | J27: =IFERROR(J18-1*SUM(J24,J21),0) -> 2311.71 | ... M27: =IFERROR(M18-1*SUM(M24,M21),0) -> 2481.74
B28: EBT % Sales | C28: =IFERROR(C27/C6,0) -> 0.14426041 | D28: =IFERROR(D27/D6,0) -> 0.20765685 | E28: =IFERROR(E27/E6,0) -> 0.21344172 | F28: =IFERROR(F27/F6,0) -> 0.19344412 | G28: =IFERROR(G27/G6,0) -> 0.19353312 | H28: =IFERROR(H27/H6,0) -> 0.17591921 | I28: =IFERROR(I27/I6,0) -> 0.19123857 | J28: =IFERROR(J27/J6,0) -> 0.16771988 | ... M28: =IFERROR(M27/M6,0) -> 0.12749736
B30: Tax | C30: =IFERROR('Data Sheet'!B29,0) -> 200.01 | D30: =IFERROR('Data Sheet'!C29,0) -> 198.31 | E30: =IFERROR('Data Sheet'!D29,0) -> 185.87 | F30: =IFERROR('Data Sheet'!E29,0) -> 260.88 | G30: =IFERROR('Data Sheet'!F29,0) -> 274.19 | H30: =IFERROR('Data Sheet'!G29,0) -> 317.27 | I30: =IFERROR('Data Sheet'!H29,0) -> 377.04 | J30: =IFERROR('Data Sheet'!I29,0) -> 447.04 | ... L30: =IFERROR('Data Sheet'!K29,0) -> 396.24 | M30: =IFERROR(SUM('Data Sheet'!H48:K48),0) -> 504.96
B31: Effective Tax Rate | C31: =IFERROR(C30/C27,0) -> 0.20891173 | D31: =IFERROR(D30/D27,0) -> 0.14086318 | E31: =IFERROR(E30/E27,0) -> 0.12777381 | F31: =IFERROR(F30/F27,0) -> 0.18597622 | G31: =IFERROR(G30/G27,0) -> 0.14700615 | H31: =IFERROR(H30/H27,0) -> 0.15544679 | I31: =IFERROR(I30/I27,0) -> 0.15867284 | J31: =IFERROR(J30/J27,0) -> 0.19338066 | ... M31: =IFERROR(M30/M27,0) -> 0.20347015
B33: Net Profit | C33: =IFERROR(C27-C30,0) -> 757.38 | D33: =IFERROR(D27-D30,0) -> 1209.51 | E33: =IFERROR(E27-E30,0) -> 1268.81 | F33: =IFERROR(F27-F30,0) -> 1141.88 | G33: =IFERROR(G27-G30,0) -> 1590.97 | H33: =IFERROR(H27-H30,0) -> 1723.75 | I33: =IFERROR(I27-I30,0) -> 1999.17 | J33: =IFERROR(J27-J30,0) -> 1864.67 | ... M33: =IFERROR(M27-M30,0) -> 1976.78
B34: Net Margins | C34: =IFERROR(C33/C6,0) -> 0.11412272 | D34: =IFERROR(D33/D6,0) -> 0.17840565 | E34: =IFERROR(E33/E6,0) -> 0.18616946 | F34: =IFERROR(F33/F6,0) -> 0.15746811 | G34: =IFERROR(G33/G6,0) -> 0.16508256 | H34: =IFERROR(H33/H6,0) -> 0.14857314 | I34: =IFERROR(I33/I6,0) -> 0.1608942 | J34: =IFERROR(J33/J6,0) -> 0.1352861 | ... M34: =IFERROR(M33/M6,0) -> 0.10155546
B36: No. of Equity Shares | C36: =IFERROR('Data Sheet'!B93,0) -> 65.54 | D36: =IFERROR('Data Sheet'!C93,0) -> 65.54 | E36: =IFERROR('Data Sheet'!D93,0) -> 65.54 | F36: =IFERROR('Data Sheet'!E93,0) -> 65.54 | G36: =IFERROR('Data Sheet'!F93,0) -> 95.7 | H36: =IFERROR('Data Sheet'!G93,0) -> 95.7 | I36: =IFERROR('Data Sheet'!H93,0) -> 95.7 | J36: =IFERROR('Data Sheet'!I93,0) -> 96.47 | ... L36: =IFERROR('Data Sheet'!K93,0) -> 98.95 | M36: -
B38: Earnings per Share | C38: =IFERROR(C33/C36,0) -> 11.555996 | D38: =IFERROR(D33/D36,0) -> 18.454532 | E38: =IFERROR(E33/E36,0) -> 19.359323 | F38: =IFERROR(F33/F36,0) -> 17.422643 | G38: =IFERROR(G33/G36,0) -> 16.624556 | H38: =IFERROR(H33/H36,0) -> 18.012017 | I38: =IFERROR(I33/I36,0) -> 20.889969 | J38: =IFERROR(J33/J36,0) -> 19.329014 | ... M38: =IFERROR(M33/M36,0) -> 0
B39: EPS Growth | C39: - | D39: =IFERROR(D38/C38-1,0) -> 0.59696586 | E39: =IFERROR(E38/D38-1,0) -> 0.049028119 | F39: =IFERROR(F38/E38-1,0) -> -0.10003862 | G39: =IFERROR(G38/F38-1,0) -> -0.045807446 | H39: =IFERROR(H38/G38-1,0) -> 0.083458519 | I39: =IFERROR(I38/H38-1,0) -> 0.15977955 | J39: =IFERROR(J38/I38-1,0) -> -0.07472268 | K39: =IFERROR(K38/J38-1,0) -> 0.31726036 | ... M39: =IFERROR(M38/L38-1,0) -> -1
B41: Dividend per Share | C41: =IFERROR('Data Sheet'!B31/'Data Sheet'!B93,0) -> 2.1666158 | D41: =IFERROR('Data Sheet'!C31/'Data Sheet'!C93,0) -> 2.2628929 | E41: =IFERROR('Data Sheet'!D31/'Data Sheet'!D93,0) -> 2.2628929 | F41: =IFERROR('Data Sheet'!E31/'Data Sheet'!E93,0) -> 2.4073848 | G41: =IFERROR('Data Sheet'!F31/'Data Sheet'!F93,0) -> 2.6001045 | H41: =IFERROR('Data Sheet'!G31/'Data Sheet'!G93,0) -> 3.900209 | I41: =IFERROR('Data Sheet'!H31/'Data Sheet'!H93,0) -> 5.8262278 | J41: =IFERROR('Data Sheet'!I31/'Data Sheet'!I93,0) -> 8.1372447 | ... L41: =IFERROR('Data Sheet'!K31/'Data Sheet'!K93,0) -> 8.2500253 | M41: -
B42: Dividend Payout Ratio | C42: =IFERROR(C41/C38,0) -> 0.18748845 | D42: =IFERROR(D41/D38,0) -> 0.1226199 | E42: =IFERROR(E41/E38,0) -> 0.11688905 | F42: =IFERROR(F41/F38,0) -> 0.13817564 | G42: =IFERROR(G41/G38,0) -> 0.15640144 | H42: =IFERROR(H41/H38,0) -> 0.21653372 | I42: =IFERROR(I41/I38,0) -> 0.27890074 | J42: =IFERROR(J41/J38,0) -> 0.42098602 | ... M42: =IFERROR(M41/M38,0) -> 0
B44: Retained Earnings | C44: =IFERROR(IF(C38>C41,1-C42,0),0) -> 0.81251155 | D44: =IFERROR(IF(D38>D41,1-D42,0),0) -> 0.8773801 | E44: =IFERROR(IF(E38>E41,1-E42,0),0) -> 0.88311095 | F44: =IFERROR(IF(F38>F41,1-F42,0),0) -> 0.86182436 | G44: =IFERROR(IF(G38>G41,1-G42,0),0) -> 0.84359856 | H44: =IFERROR(IF(H38>H41,1-H42,0),0) -> 0.78346628 | I44: =IFERROR(IF(I38>I41,1-I42,0),0) -> 0.72109926 | J44: =IFERROR(IF(J38>J41,1-J42,0),0) -> 0.57901398 | ... M44: =IFERROR(IF(M38>M41,1-M42,0),0) -> 0
A46: # | B46: Balance Sheet
B48: ='Data Sheet'!A57 -> Equity Share Capital | C48: =IFERROR('Data Sheet'!B57,0) -> 63.11 | D48: =IFERROR('Data Sheet'!C57,0) -> 63.11 | E48: =IFERROR('Data Sheet'!D57,0) -> 63.11 | F48: =IFERROR('Data Sheet'!E57,0) -> 63.11 | G48: =IFERROR('Data Sheet'!F57,0) -> 92.16 | H48: =IFERROR('Data Sheet'!G57,0) -> 92.16 | I48: =IFERROR('Data Sheet'!H57,0) -> 92.16 | J48: =IFERROR('Data Sheet'!I57,0) -> 92.9 | ... L48: =IFERROR('Data Sheet'!K57,0) -> 98.95
B49: ='Data Sheet'!A58 -> Reserves | C49: =IFERROR('Data Sheet'!B58,0) -> 6184.06 | D49: =IFERROR('Data Sheet'!C58,0) -> 6202.39 | E49: =IFERROR('Data Sheet'!D58,0) -> 6968.49 | F49: =IFERROR('Data Sheet'!E58,0) -> 7268.58 | G49: =IFERROR('Data Sheet'!F58,0) -> 13722.7 | H49: =IFERROR('Data Sheet'!G58,0) -> 14442.35 | I49: =IFERROR('Data Sheet'!H58,0) -> 15049.78 | J49: =IFERROR('Data Sheet'!I58,0) -> 16183.81 | ... L49: =IFERROR('Data Sheet'!K58,0) -> 19902.13
B50: ='Data Sheet'!A59 -> Borrowings | C50: =IFERROR('Data Sheet'!B59,0) -> 1354.05 | D50: =IFERROR('Data Sheet'!C59,0) -> 786.56 | E50: =IFERROR('Data Sheet'!D59,0) -> 1067.58 | F50: =IFERROR('Data Sheet'!E59,0) -> 1141.1 | G50: =IFERROR('Data Sheet'!F59,0) -> 1586.32 | H50: =IFERROR('Data Sheet'!G59,0) -> 1633.55 | I50: =IFERROR('Data Sheet'!H59,0) -> 1412.01 | J50: =IFERROR('Data Sheet'!I59,0) -> 1600.04 | ... L50: =IFERROR('Data Sheet'!K59,0) -> 2392.68
B51: ='Data Sheet'!A60 -> Other Liabilities | C51: =IFERROR('Data Sheet'!B60,0) -> 2293.54 | D51: =IFERROR('Data Sheet'!C60,0) -> 2499.35 | E51: =IFERROR('Data Sheet'!D60,0) -> 2361.58 | F51: =IFERROR('Data Sheet'!E60,0) -> 2407.89 | G51: =IFERROR('Data Sheet'!F60,0) -> 3071.86 | H51: =IFERROR('Data Sheet'!G60,0) -> 4049.76 | I51: =IFERROR('Data Sheet'!H60,0) -> 4520.92 | J51: =IFERROR('Data Sheet'!I60,0) -> 4885.74 | ... L51: =IFERROR('Data Sheet'!K60,0) -> 9436.86
B52: Total Liabilities | C52: =IFERROR('Data Sheet'!B61,0) -> 9894.76 | D52: =IFERROR('Data Sheet'!C61,0) -> 9551.41 | E52: =IFERROR('Data Sheet'!D61,0) -> 10460.76 | F52: =IFERROR('Data Sheet'!E61,0) -> 10880.68 | G52: =IFERROR('Data Sheet'!F61,0) -> 18473.04 | H52: =IFERROR('Data Sheet'!G61,0) -> 20217.82 | I52: =IFERROR('Data Sheet'!H61,0) -> 21074.87 | J52: =IFERROR('Data Sheet'!I61,0) -> 22762.49 | ... L52: =IFERROR('Data Sheet'!K61,0) -> 31830.62
B54: Fixed Assets Net Block | C54: =IFERROR('Data Sheet'!B62,0) -> 4661.8 | D54: =IFERROR('Data Sheet'!C62,0) -> 4572.59 | E54: =IFERROR('Data Sheet'!D62,0) -> 4798.18 | F54: =IFERROR('Data Sheet'!E62,0) -> 4913.31 | G54: =IFERROR('Data Sheet'!F62,0) -> 11656.04 | H54: =IFERROR('Data Sheet'!G62,0) -> 12023.13 | I54: =IFERROR('Data Sheet'!H62,0) -> 12599.35 | J54: =IFERROR('Data Sheet'!I62,0) -> 13070.04 | ... L54: =IFERROR('Data Sheet'!K62,0) -> 21476.84
B55: ='Data Sheet'!A63 -> Capital Work in Progress | C55: =IFERROR('Data Sheet'!B63,0) -> 39.42 | D55: =IFERROR('Data Sheet'!C63,0) -> 63.19 | E55: =IFERROR('Data Sheet'!D63,0) -> 135.16 | F55: =IFERROR('Data Sheet'!E63,0) -> 424.41 | G55: =IFERROR('Data Sheet'!F63,0) -> 95.35 | H55: =IFERROR('Data Sheet'!G63,0) -> 112.85 | I55: =IFERROR('Data Sheet'!H63,0) -> 246.97 | J55: =IFERROR('Data Sheet'!I63,0) -> 294.9 | ... L55: =IFERROR('Data Sheet'!K63,0) -> 218.1
B56: ='Data Sheet'!A64 -> Investments | C56: =IFERROR('Data Sheet'!B64,0) -> 1365.94 | D56: =IFERROR('Data Sheet'!C64,0) -> 1451.04 | E56: =IFERROR('Data Sheet'!D64,0) -> 1161.33 | F56: =IFERROR('Data Sheet'!E64,0) -> 1187.66 | G56: =IFERROR('Data Sheet'!F64,0) -> 1322.85 | H56: =IFERROR('Data Sheet'!G64,0) -> 805.89 | I56: =IFERROR('Data Sheet'!H64,0) -> 797.28 | J56: =IFERROR('Data Sheet'!I64,0) -> 1432.97 | ... L56: =IFERROR('Data Sheet'!K64,0) -> 968.67
B57: ='Data Sheet'!A65 -> Other Assets | C57: =IFERROR('Data Sheet'!B65-1*(SUM('Historical FS'!C60:C62)),0) -> 1105.13 | D57: =IFERROR('Data Sheet'!C65-1*(SUM('Historical FS'!D60:D62)),0) -> 844.36 | E57: =IFERROR('Data Sheet'!D65-1*(SUM('Historical FS'!E60:E62)),0) -> 1031.36 | F57: =IFERROR('Data Sheet'!E65-1*(SUM('Historical FS'!F60:F62)),0) -> 1032.6 | G57: =IFERROR('Data Sheet'!F65-1*(SUM('Historical FS'!G60:G62)),0) -> 1142.9 | H57: =IFERROR('Data Sheet'!G65-1*(SUM('Historical FS'!H60:H62)),0) -> 1190.59 | I57: =IFERROR('Data Sheet'!H65-1*(SUM('Historical FS'!I60:I62)),0) -> 1729.72 | J57: =IFERROR('Data Sheet'!I65-1*(SUM('Historical FS'!J60:J62)),0) -> 1667.64 | ... L57: =IFERROR('Data Sheet'!K65-1*(SUM('Historical FS'!L60:L62)),0) -> 1879.45
B58: Total Non Current Assets | C58: =IFERROR(SUM(C54:C57),0) -> 7172.29 | D58: =IFERROR(SUM(D54:D57),0) -> 6931.18 | E58: =IFERROR(SUM(E54:E57),0) -> 7126.03 | F58: =IFERROR(SUM(F54:F57),0) -> 7557.98 | G58: =IFERROR(SUM(G54:G57),0) -> 14217.14 | H58: =IFERROR(SUM(H54:H57),0) -> 14132.46 | I58: =IFERROR(SUM(I54:I57),0) -> 15373.32 | J58: =IFERROR(SUM(J54:J57),0) -> 16465.55 | ... L58: =IFERROR(SUM(L54:L57),0) -> 24543.06
B60: ='Data Sheet'!A67 -> Receivables | C60: =IFERROR('Data Sheet'!B67,0) -> 592.43 | D60: =IFERROR('Data Sheet'!C67,0) -> 592.45 | E60: =IFERROR('Data Sheet'!D67,0) -> 648.28 | F60: =IFERROR('Data Sheet'!E67,0) -> 680.55 | G60: =IFERROR('Data Sheet'!F67,0) -> 922.41 | H60: =IFERROR('Data Sheet'!G67,0) -> 761.32 | I60: =IFERROR('Data Sheet'!H67,0) -> 835.15 | J60: =IFERROR('Data Sheet'!I67,0) -> 798.33 | ... L60: =IFERROR('Data Sheet'!K67,0) -> 869.79
B61: ='Data Sheet'!A68 -> Inventory | C61: =IFERROR('Data Sheet'!B68,0) -> 1629.01 | D61: =IFERROR('Data Sheet'!C68,0) -> 1452.96 | E61: =IFERROR('Data Sheet'!D68,0) -> 1448.31 | F61: =IFERROR('Data Sheet'!E68,0) -> 1608.54 | G61: =IFERROR('Data Sheet'!F68,0) -> 1712.03 | H61: =IFERROR('Data Sheet'!G68,0) -> 2249.16 | I61: =IFERROR('Data Sheet'!H68,0) -> 2266.51 | J61: =IFERROR('Data Sheet'!I68,0) -> 2701.67 | ... L61: =IFERROR('Data Sheet'!K68,0) -> 3599.91
B62: ='Data Sheet'!A69 -> Cash & Bank | C62: =IFERROR('Data Sheet'!B69,0) -> 501.03 | D62: =IFERROR('Data Sheet'!C69,0) -> 574.82 | E62: =IFERROR('Data Sheet'!D69,0) -> 1238.14 | F62: =IFERROR('Data Sheet'!E69,0) -> 1033.61 | G62: =IFERROR('Data Sheet'!F69,0) -> 1621.46 | H62: =IFERROR('Data Sheet'!G69,0) -> 3074.88 | I62: =IFERROR('Data Sheet'!H69,0) -> 2599.89 | J62: =IFERROR('Data Sheet'!I69,0) -> 2796.94 | ... L62: =IFERROR('Data Sheet'!K69,0) -> 2817.86
B63: Total Current Assets | C63: =IFERROR(SUM(C60:C62),0) -> 2722.47 | D63: =IFERROR(SUM(D60:D62),0) -> 2620.23 | E63: =IFERROR(SUM(E60:E62),0) -> 3334.73 | F63: =IFERROR(SUM(F60:F62),0) -> 3322.7 | G63: =IFERROR(SUM(G60:G62),0) -> 4255.9 | H63: =IFERROR(SUM(H60:H62),0) -> 6085.36 | I63: =IFERROR(SUM(I60:I62),0) -> 5701.55 | J63: =IFERROR(SUM(J60:J62),0) -> 6296.94 | ... L63: =IFERROR(SUM(L60:L62),0) -> 7287.56
B65: Total Assets | C65: =IFERROR(SUM(C63,C58),0) -> 9894.76 | D65: =IFERROR(SUM(D63,D58),0) -> 9551.41 | E65: =IFERROR(SUM(E63,E58),0) -> 10460.76 | F65: =IFERROR(SUM(F63,F58),0) -> 10880.68 | G65: =IFERROR(SUM(G63,G58),0) -> 18473.04 | H65: =IFERROR(SUM(H63,H58),0) -> 20217.82 | I65: =IFERROR(SUM(I63,I58),0) -> 21074.87 | J65: =IFERROR(SUM(J63,J58),0) -> 22762.49 | ... L65: =IFERROR(SUM(L63,L58),0) -> 31830.62
B67: Check | C67: =C65=C52 -> TRUE | D67: =D65=D52 -> TRUE | E67: =E65=E52 -> TRUE | F67: =F65=F52 -> TRUE | G67: =G65=G52 -> TRUE | H67: =H65=H52 -> TRUE | I67: =I65=I52 -> TRUE | J67: =J65=J52 -> TRUE | ... L67: =L65=L52 -> TRUE
A69: # | B69: Cash Flow Statement
B71: Cash Flow from Operating Activities | C71: =IFERROR('Data Sheet'!B82,0) -> 115.98 | D71: =IFERROR('Data Sheet'!C82,0) -> 741.2 | E71: =IFERROR('Data Sheet'!D82,0) -> 355.58 | F71: =IFERROR('Data Sheet'!E82,0) -> 209.87 | G71: =IFERROR('Data Sheet'!F82,0) -> 1082.23 | H71: =IFERROR('Data Sheet'!G82,0) -> 1656.37 | I71: =IFERROR('Data Sheet'!H82,0) -> 1515.81 | J71: =IFERROR('Data Sheet'!I82,0) -> 1461.29 | ... L71: =IFERROR('Data Sheet'!K82,0) -> 2056.65
B73: Cash Flow from Investing Activities | C73: =IFERROR('Data Sheet'!B83,0) -> 144.62 | D73: =IFERROR('Data Sheet'!C83,0) -> 145.05 | E73: =IFERROR('Data Sheet'!D83,0) -> -31.1 | F73: =IFERROR('Data Sheet'!E83,0) -> 53.17 | G73: =IFERROR('Data Sheet'!F83,0) -> -622.04 | H73: =IFERROR('Data Sheet'!G83,0) -> -346.5 | I73: =IFERROR('Data Sheet'!H83,0) -> -1317.11 | J73: =IFERROR('Data Sheet'!I83,0) -> -833.61 | ... L73: =IFERROR('Data Sheet'!K83,0) -> -2303.48
B75: Cash Flow from Financing Activities | C75: =IFERROR('Data Sheet'!B84,0) -> -281.8 | D75: =IFERROR('Data Sheet'!C84,0) -> -815.84 | E75: =IFERROR('Data Sheet'!D84,0) -> -30.39 | F75: =IFERROR('Data Sheet'!E84,0) -> -223.73 | G75: =IFERROR('Data Sheet'!F84,0) -> -308.33 | H75: =IFERROR('Data Sheet'!G84,0) -> -426.03 | I75: =IFERROR('Data Sheet'!H84,0) -> -994.77 | J75: =IFERROR('Data Sheet'!I84,0) -> -714.4 | ... L75: =IFERROR('Data Sheet'!K84,0) -> 452.7
B77: Net Cash Flow | C77: =IFERROR(SUM(C75,C73,C71),0) -> -21.2 | D77: =IFERROR(SUM(D75,D73,D71),0) -> 70.41 | E77: =IFERROR(SUM(E75,E73,E71),0) -> 294.09 | F77: =IFERROR(SUM(F75,F73,F71),0) -> 39.31 | G77: =IFERROR(SUM(G75,G73,G71),0) -> 151.86 | H77: =IFERROR(SUM(H75,H73,H71),0) -> 883.84 | I77: =IFERROR(SUM(I75,I73,I71),0) -> -796.07 | J77: =IFERROR(SUM(J75,J73,J71),0) -> -86.72 | ... L77: =IFERROR(SUM(L75,L73,L71),0) -> 205.87

Sheet Ratio Analysis
B2: ="Ratio Analysis - "&'Data Sheet'!B1 -> Ratio Analysis - TATA CONSUMER PRODUCTS LTD
B3: Years | C3: ='Data Sheet'!B16 -> 42460 | D3: ='Data Sheet'!C16 -> 42825 | E3: ='Data Sheet'!D16 -> 43190 | F3: ='Data Sheet'!E16 -> 43555 | G3: ='Data Sheet'!F16 -> 43921 | H3: ='Data Sheet'!G16 -> 44286 | I3: ='Data Sheet'!H16 -> 44651 | J3: ='Data Sheet'!I16 -> 45016 | K3: ='Data Sheet'!J16 -> 45382 | L3: Trend | M3: Mean | N3: Median
B5: Sales Growth | D5: =IFERROR('Historical FS'!D7,0) -> 0.021548879 | E5: =IFERROR('Historical FS'!E7,0) -> 0.0052805865 | F5: =IFERROR('Historical FS'!F7,0) -> 0.063995246 | G5: =IFERROR('Historical FS'!G7,0) -> 0.32902434 | H5: =IFERROR('Historical FS'!H7,0) -> 0.20385228 | I5: =IFERROR('Historical FS'!I7,0) -> 0.070965167 | J5: =IFERROR('Historical FS'!J7,0) -> 0.10927562 | K5: =IFERROR('Historical FS'!K7,0) -> 0.10321944 | M5: =IFERROR(AVERAGE(D5:K5),0) -> 0.11339519 | N5: =IFERROR(MEDIAN(D5:K5),0) -> 0.087092302
B6: EBITDA Growth | D6: =IFERROR('Historical FS'!D18/'Historical FS'!C18-1,0) -> 0.36463546 | E6: =IFERROR('Historical FS'!E18/'Historical FS'!D18-1,0) -> -0.0073274722 | F6: =IFERROR('Historical FS'!F18/'Historical FS'!E18-1,0) -> -0.022113692 | G6: =IFERROR('Historical FS'!G18/'Historical FS'!F18-1,0) -> 0.38466853 | H6: =IFERROR('Historical FS'!H18/'Historical FS'!G18-1,0) -> 0.082261881 | I6: =IFERROR('Historical FS'!I18/'Historical FS'!H18-1,0) -> 0.15333376 | J6: =IFERROR('Historical FS'!J18/'Historical FS'!I18-1,0) -> -0.0088192153 | K6: =IFERROR('Historical FS'!K18/'Historical FS'!J18-1,0) -> 0.26568749 | M6: =IFERROR(AVERAGE(D6:K6),0) -> 0.15154084 | N6: =IFERROR(MEDIAN(D6:K6),0) -> 0.11779782
B7: EBIT Growth | D7: =IFERROR(('Historical FS'!D18-'Historical FS'!D24)/('Historical FS'!C18-'Historical FS'!C24)-1,0) -> 0.39566597 | E7: =IFERROR(('Historical FS'!E18-'Historical FS'!E24)/('Historical FS'!D18-'Historical FS'!D24)-1,0) -> -0.0012738854 | F7: =IFERROR(('Historical FS'!F18-'Historical FS'!F24)/('Historical FS'!E18-'Historical FS'!E24)-1,0) -> -0.028188108 | G7: =IFERROR(('Historical FS'!G18-'Historical FS'!G24)/('Historical FS'!F18-'Historical FS'!F24)-1,0) -> 0.33519787 | H7: =IFERROR(('Historical FS'!H18-'Historical FS'!H24)/('Historical FS'!G18-'Historical FS'!G24)-1,0) -> 0.085789132 | I7: =IFERROR(('Historical FS'!I18-'Historical FS'!I24)/('Historical FS'!H18-'Historical FS'!H24)-1,0) -> 0.16081831 | J7: =IFERROR(('Historical FS'!J18-'Historical FS'!J24)/('Historical FS'!I18-'Historical FS'!I24)-1,0) -> -0.02046558 | K7: =IFERROR(('Historical FS'!K18-'Historical FS'!K24)/('Historical FS'!J18-'Historical FS'!J24)-1,0) -> 0.26890578 | M7: =IFERROR(AVERAGE(D7:K7),0) -> 0.14955619 | N7: =IFERROR(MEDIAN(D7:K7),0) -> 0.12330372
B8: Net Profit Growth | D8: =IFERROR('Historical FS'!D33/'Historical FS'!C33-1,0) -> 0.59696586 | E8: =IFERROR('Historical FS'!E33/'Historical FS'!D33-1,0) -> 0.049028119 | F8: =IFERROR('Historical FS'!F33/'Historical FS'!E33-1,0) -> -0.10003862 | G8: =IFERROR('Historical FS'!G33/'Historical FS'!F33-1,0) -> 0.39329001 | H8: =IFERROR('Historical FS'!H33/'Historical FS'!G33-1,0) -> 0.083458519 | I8: =IFERROR('Historical FS'!I33/'Historical FS'!H33-1,0) -> 0.15977955 | J8: =IFERROR('Historical FS'!J33/'Historical FS'!I33-1,0) -> -0.06727792 | K8: =IFERROR('Historical FS'!K33/'Historical FS'!J33-1,0) -> 0.35112379 | M8: =IFERROR(AVERAGE(D8:K8),0) -> 0.18329116 | N8: =IFERROR(MEDIAN(D8:K8),0) -> 0.12161903
B9: Dividend Growth | D9: =IFERROR('Historical FS'!D41/'Historical FS'!C41-1,0) -> 0.04443662 | E9: =IFERROR('Historical FS'!E41/'Historical FS'!D41-1,0) -> 0 | F9: =IFERROR('Historical FS'!F41/'Historical FS'!E41-1,0) -> 0.063852741 | G9: =IFERROR('Historical FS'!G41/'Historical FS'!F41-1,0) -> 0.080053546 | H9: =IFERROR('Historical FS'!H41/'Historical FS'!G41-1,0) -> 0.50002009 | I9: =IFERROR('Historical FS'!I41/'Historical FS'!H41-1,0) -> 0.49382451 | J9: =IFERROR('Historical FS'!J41/'Historical FS'!I41-1,0) -> 0.3966575 | K9: =IFERROR('Historical FS'!K41/'Historical FS'!J41-1,0) -> -0.082913555 | M9: =IFERROR(AVERAGE(D9:K9),0) -> 0.18699143 | N9: =IFERROR(MEDIAN(D9:K9),0) -> 0.071953143
B11: Gross Margin | C11: =IFERROR('Historical FS'!C13,0) -> 0.41640222 | D11: =IFERROR('Historical FS'!D13,0) -> 0.43263933 | E11: =IFERROR('Historical FS'!E13,0) -> 0.40900027 | F11: =IFERROR('Historical FS'!F13,0) -> 0.40413432 | G11: =IFERROR('Historical FS'!G13,0) -> 0.40386431 | H11: =IFERROR('Historical FS'!H13,0) -> 0.36158586 | I11: =IFERROR('Historical FS'!I13,0) -> 0.38941778 | J11: =IFERROR('Historical FS'!J13,0) -> 0.35902289 | K11: =IFERROR('Historical FS'!K13,0) -> 0.39383592 | M11: =IFERROR(AVERAGE(D11:K11),0) -> 0.39418759 | N11: =IFERROR(MEDIAN(D11:K11),0) -> 0.39885012
B12: EBITDA Margin | C12: =IFERROR('Historical FS'!C19,0) -> 0.17947304 | D12: =IFERROR('Historical FS'!D19,0) -> 0.23974895 | E12: =IFERROR('Historical FS'!E19,0) -> 0.23674206 | F12: =IFERROR('Historical FS'!F19,0) -> 0.21758257 | G12: =IFERROR('Historical FS'!G19,0) -> 0.22669241 | H12: =IFERROR('Historical FS'!H19,0) -> 0.20379623 | I12: =IFERROR('Historical FS'!I19,0) -> 0.21947033 | J12: =IFERROR('Historical FS'!J19,0) -> 0.19610525 | K12: =IFERROR('Historical FS'!K19,0) -> 0.22498512 | M12: =IFERROR(AVERAGE(D12:K12),0) -> 0.22064036 | N12: =IFERROR(MEDIAN(D12:K12),0) -> 0.22222772
B13: EBIT Margin | C13: =IFERROR(('Historical FS'!C18-'Historical FS'!C24)/'Historical FS'!C6,0) -> 0.16187501 | D13: =IFERROR(('Historical FS'!D18-'Historical FS'!D24)/'Historical FS'!D6,0) -> 0.22115775 | E13: =IFERROR(('Historical FS'!E18-'Historical FS'!E24)/'Historical FS'!E6,0) -> 0.21971579 | F13: =IFERROR(('Historical FS'!F18-'Historical FS'!F24)/'Historical FS'!F6,0) -> 0.20067986 | G13: =IFERROR(('Historical FS'!G18-'Historical FS'!G24)/'Historical FS'!G6,0) -> 0.20161205 | H13: =IFERROR(('Historical FS'!H18-'Historical FS'!H24)/'Historical FS'!H6,0) -> 0.18183973 | I13: =IFERROR(('Historical FS'!I18-'Historical FS'!I24)/'Historical FS'!I6,0) -> 0.19709594 | J13: =IFERROR(('Historical FS'!J18-'Historical FS'!J24)/'Historical FS'!J6,0) -> 0.17404354 | K13: =IFERROR(('Historical FS'!K18-'Historical FS'!K24)/'Historical FS'!K6,0) -> 0.20018217 | M13: =IFERROR(AVERAGE(D13:K13),0) -> 0.19954085 | N13: =IFERROR(MEDIAN(D13:K13),0) -> 0.20043101
B14: EBT Margin | C14: =IFERROR('Historical FS'!C28,0) -> 0.14426041 | D14: =IFERROR('Historical FS'!D28,0) -> 0.20765685 | E14: =IFERROR('Historical FS'!E28,0) -> 0.21344172 | F14: =IFERROR('Historical FS'!F28,0) -> 0.19344412 | G14: =IFERROR('Historical FS'!G28,0) -> 0.19353312 | H14: =IFERROR('Historical FS'!H28,0) -> 0.17591921 | I14: =IFERROR('Historical FS'!I28,0) -> 0.19123857 | J14: =IFERROR('Historical FS'!J28,0) -> 0.16771988 | K14: =IFERROR('Historical FS'!K28,0) -> 0.19164532 | M14: =IFERROR(AVERAGE(D14:K14),0) -> 0.19182485 | N14: =IFERROR(MEDIAN(D14:K14),0) -> 0.19254472
B15: Net Profit Margin | C15: =IFERROR('Historical FS'!C34,0) -> 0.11412272 | D15: =IFERROR('Historical FS'!D34,0) -> 0.17840565 | E15: =IFERROR('Historical FS'!E34,0) -> 0.18616946 | F15: =IFERROR('Historical FS'!F34,0) -> 0.15746811 | G15: =IFERROR('Historical FS'!G34,0) -> 0.16508256 | H15: =IFERROR('Historical FS'!H34,0) -> 0.14857314 | I15: =IFERROR('Historical FS'!I34,0) -> 0.1608942 | J15: =IFERROR('Historical FS'!J34,0) -> 0.1352861 | K15: =IFERROR('Historical FS'!K34,0) -> 0.16568623 | M15: =IFERROR(AVERAGE(D15:K15),0) -> 0.16219568 | N15: =IFERROR(MEDIAN(D15:K15),0) -> 0.16298838
B17: SalesExpense%Sales | C17: =IFERROR('Historical FS'!C16,0) -> 0.23692918 | D17: =IFERROR('Historical FS'!D16,0) -> 0.19289038 | E17: =IFERROR('Historical FS'!E16,0) -> 0.17225821 | F17: =IFERROR('Historical FS'!F16,0) -> 0.18655175 | G17: =IFERROR('Historical FS'!G16,0) -> 0.1771719 | H17: =IFERROR('Historical FS'!H16,0) -> 0.15778963 | I17: =IFERROR('Historical FS'!I16,0) -> 0.16994745 | J17: =IFERROR('Historical FS'!J16,0) -> 0.16291765 | K17: =IFERROR('Historical FS'!K16,0) -> 0.1688508 | M17: =IFERROR(AVERAGE(D17:K17),0) -> 0.17354722 | N17: =IFERROR(MEDIAN(D17:K17),0) -> 0.17110283
B18: Depreciation%Sales | C18: =IFERROR('Historical FS'!C25,0) -> 0.017598025 | D18: =IFERROR('Historical FS'!D25,0) -> 0.018591204 | E18: =IFERROR('Historical FS'!E25,0) -> 0.017026272 | F18: =IFERROR('Historical FS'!F25,0) -> 0.01690271 | G18: =IFERROR('Historical FS'!G25,0) -> 0.025080364 | H18: =IFERROR('Historical FS'!H25,0) -> 0.021956502 | I18: =IFERROR('Historical FS'!I25,0) -> 0.022374384 | J18: =IFERROR('Historical FS'!J25,0) -> 0.022061704 | K18: =IFERROR('Historical FS'!K25,0) -> 0.024802954 | M18: =IFERROR(AVERAGE(D18:K18),0) -> 0.021099512 | N18: =IFERROR(MEDIAN(D18:K18),0) -> 0.022009103
B19: OperatingIncome%Sales | C19: =C13 -> 0.16187501 | D19: =D13 -> 0.22115775 | E19: =E13 -> 0.21971579 | F19: =F13 -> 0.20067986 | G19: =G13 -> 0.20161205 | H19: =H13 -> 0.18183973 | I19: =I13 -> 0.19709594 | J19: =J13 -> 0.17404354 | K19: =K13 -> 0.20018217 | M19: =IFERROR(AVERAGE(D19:K19),0) -> 0.19954085 | N19: =IFERROR(MEDIAN(D19:K19),0) -> 0.20043101
B21: Return on Capital Employed | C21: =IFERROR(('Historical FS'!C18-'Historical FS'!C24)/SUM('Historical FS'!C48:C50),0) -> 0.14133126 | D21: =IFERROR(('Historical FS'!D18-'Historical FS'!D24)/SUM('Historical FS'!D48:D50),0) -> 0.21261163 | E21: =IFERROR(('Historical FS'!E18-'Historical FS'!E24)/SUM('Historical FS'!E48:E50),0) -> 0.18488785 | F21: =IFERROR(('Historical FS'!F18-'Historical FS'!F24)/SUM('Historical FS'!F48:F50),0) -> 0.17175334 | G21: =IFERROR(('Historical FS'!G18-'Historical FS'!G24)/SUM('Historical FS'!G48:G50),0) -> 0.12616046 | H21: =IFERROR(('Historical FS'!H18-'Historical FS'!H24)/SUM('Historical FS'!H48:H50),0) -> 0.13048628 | I21: =IFERROR(('Historical FS'!I18-'Historical FS'!I24)/SUM('Historical FS'!I48:I50),0) -> 0.14793992 | J21: =IFERROR(('Historical FS'!J18-'Historical FS'!J24)/SUM('Historical FS'!J48:J50),0) -> 0.13418938 | K21: =IFERROR(('Historical FS'!K18-'Historical FS'!K24)/SUM('Historical FS'!K48:K50),0) -> 0.15582771 | M21: =IFERROR(AVERAGE(D21:K21),0) -> 0.15798207 | N21: =IFERROR(MEDIAN(D21:K21),0) -> 0.15188381
B22: Retained Earnings% | C22: =IFERROR('Historical FS'!C44,0) -> 0.81251155 | D22: =IFERROR('Historical FS'!D44,0) -> 0.8773801 | E22: =IFERROR('Historical FS'!E44,0) -> 0.88311095 | F22: =IFERROR('Historical FS'!F44,0) -> 0.86182436 | G22: =IFERROR('Historical FS'!G44,0) -> 0.84359856 | H22: =IFERROR('Historical FS'!H44,0) -> 0.78346628 | I22: =IFERROR('Historical FS'!I44,0) -> 0.72109926 | J22: =IFERROR('Historical FS'!J44,0) -> 0.57901398 | K22: =IFERROR('Historical FS'!K44,0) -> 0.70690641 | M22: =IFERROR(AVERAGE(D22:K22),0) -> 0.78204999 | N22: =IFERROR(MEDIAN(D22:K22),0) -> 0.81353242
B23: Return on Equity% | C23: =IFERROR('Historical FS'!C33/SUM('Historical FS'!C48:C49),0) -> 0.1212357 | D23: =IFERROR('Historical FS'!D33/SUM('Historical FS'!D48:D49),0) -> 0.19304285 | E23: =IFERROR('Historical FS'!E33/SUM('Historical FS'!E48:E49),0) -> 0.180444 | F23: =IFERROR('Historical FS'!F33/SUM('Historical FS'!F48:F49),0) -> 0.15574581 | G23: =IFERROR('Historical FS'!G33/SUM('Historical FS'!G48:G49),0) -> 0.11516367 | H23: =IFERROR('Historical FS'!H33/SUM('Historical FS'!H48:H49),0) -> 0.11859705 | I23: =IFERROR('Historical FS'!I33/SUM('Historical FS'!I48:I49),0) -> 0.13202866 | J23: =IFERROR('Historical FS'!J33/SUM('Historical FS'!J48:J49),0) -> 0.11456062 | K23: =IFERROR('Historical FS'!K33/SUM('Historical FS'!K48:K49),0) -> 0.15690558 | M23: =IFERROR(AVERAGE(D23:K23),0) -> 0.14581103 | N23: =IFERROR(MEDIAN(D23:K23),0) -> 0.14388723
B24: Self Sustained Growth | C24: =IFERROR(C23*C22,0) -> 0.098505403 | D24: =IFERROR(D23*D22,0) -> 0.16937196 | E24: =IFERROR(E23*E22,0) -> 0.15935207 | F24: =IFERROR(F23*F22,0) -> 0.13422553 | G24: =IFERROR(G23*G22,0) -> 0.097151907 | H24: =IFERROR(H23*H22,0) -> 0.092916789 | I24: =IFERROR(I23*I22,0) -> 0.095205766 | J24: =IFERROR(J23*J22,0) -> 0.066332201 | K24: =IFERROR(K23*K22,0) -> 0.11091756 | M24: =IFERROR(AVERAGE(D24:K24),0) -> 0.11568422 | N24: =IFERROR(MEDIAN(D24:K24),0) -> 0.10403473
B25: Interest Coverage Ratio | C25: =IFERROR(('Historical FS'!C18-'Historical FS'!C24)/'Historical FS'!C21,0) -> 9.1898204 | D25: =IFERROR(('Historical FS'!D18-'Historical FS'!D24)/'Historical FS'!D21,0) -> 16.380968 | E25: =IFERROR(('Historical FS'!E18-'Historical FS'!E24)/'Historical FS'!E21,0) -> 35.019645 | F25: =IFERROR(('Historical FS'!F18-'Historical FS'!F24)/'Historical FS'!F21,0) -> 27.734515 | G25: =IFERROR(('Historical FS'!G18-'Historical FS'!G24)/'Historical FS'!G21,0) -> 24.955304 | H25: =IFERROR(('Historical FS'!H18-'Historical FS'!H24)/'Historical FS'!H21,0) -> 30.713495 | I25: =IFERROR(('Historical FS'!I18-'Historical FS'!I24)/'Historical FS'!I21,0) -> 33.649217 | J25: =IFERROR(('Historical FS'!J18-'Historical FS'!J24)/'Historical FS'!J21,0) -> 27.522602 | K25: =IFERROR(('Historical FS'!K18-'Historical FS'!K24)/'Historical FS'!K21,0) -> 23.449195 | M25: =IFERROR(AVERAGE(D25:K25),0) -> 27.428118 | N25: =IFERROR(MEDIAN(D25:K25),0) -> 27.628559
B27: Debtor Turnover Ratio | C27: =IFERROR('Historical FS'!C6/'Historical FS'!C60,0) -> 11.202235 | D27: =IFERROR('Historical FS'!D6/'Historical FS'!D60,0) -> 11.443244 | E27: =IFERROR('Historical FS'!E6/'Historical FS'!E60,0) -> 10.512973 | F27: =IFERROR('Historical FS'!F6/'Historical FS'!F60,0) -> 10.655352 | G27: =IFERROR('Historical FS'!G6/'Historical FS'!G60,0) -> 10.448087 | H27: =IFERROR('Historical FS'!H6/'Historical FS'!H60,0) -> 15.239361 | I27: =IFERROR('Historical FS'!I6/'Historical FS'!I60,0) -> 14.87801 | J27: =IFERROR('Historical FS'!J6/'Historical FS'!J60,0) -> 17.264991 | K27: =IFERROR('Historical FS'!K6/'Historical FS'!K60,0) -> 16.956621 | M27: =IFERROR(AVERAGE(D27:K27),0) -> 13.42483 | N27: =IFERROR(MEDIAN(D27:K27),0) -> 13.160627
B28: Creditor Turnover Ratio | C28: =IFERROR('Historical FS'!C9/'Historical FS'!C49,0) -> 0.6262989 | D28: =IFERROR('Historical FS'!D9/'Historical FS'!D49,0) -> 0.6201561 | E28: =IFERROR('Historical FS'!E9/'Historical FS'!E49,0) -> 0.57801188 | F28: =IFERROR('Historical FS'!F9/'Historical FS'!F49,0) -> 0.59446549 | G28: =IFERROR('Historical FS'!G9/'Historical FS'!G49,0) -> 0.41866469 | H28: =IFERROR('Historical FS'!H9/'Historical FS'!H49,0) -> 0.51285975 | I28: =IFERROR('Historical FS'!I9/'Historical FS'!I49,0) -> 0.5041077 | J28: =IFERROR('Historical FS'!J9/'Historical FS'!J49,0) -> 0.54589679 | K28: =IFERROR('Historical FS'!K9/'Historical FS'!K49,0) -> 0.57746667 | M28: =IFERROR(AVERAGE(D28:K28),0) -> 0.54395364 | N28: =IFERROR(MEDIAN(D28:K28),0) -> 0.56168173
B29: Inventory Turnover | C29: =IFERROR('Historical FS'!C9/'Historical FS'!C61,0) -> 2.3775606 | D29: =IFERROR('Historical FS'!D9/'Historical FS'!D61,0) -> 2.64732 | E29: =IFERROR('Historical FS'!E9/'Historical FS'!E61,0) -> 2.7810828 | F29: =IFERROR('Historical FS'!F9/'Historical FS'!F61,0) -> 2.6862372 | G29: =IFERROR('Historical FS'!G9/'Historical FS'!G61,0) -> 3.3557882 | H29: =IFERROR('Historical FS'!H9/'Historical FS'!H61,0) -> 3.293185 | I29: =IFERROR('Historical FS'!I9/'Historical FS'!I61,0) -> 3.3473093 | J29: =IFERROR('Historical FS'!J9/'Historical FS'!J61,0) -> 3.2700848 | K29: =IFERROR('Historical FS'!K9/'Historical FS'!K61,0) -> 3.3283045 | M29: =IFERROR(AVERAGE(D29:K29),0) -> 3.088664 | N29: =IFERROR(MEDIAN(D29:K29),0) -> 3.2816349
B30: Fixed Asset Turnover | C30: =IFERROR('Historical FS'!C6/'Historical FS'!C54,0) -> 1.4236003 | D30: =IFERROR('Historical FS'!D6/'Historical FS'!D54,0) -> 1.4826499 | E30: =IFERROR('Historical FS'!E6/'Historical FS'!E54,0) -> 1.4204032 | F30: =IFERROR('Historical FS'!F6/'Historical FS'!F54,0) -> 1.475889 | G30: =IFERROR('Historical FS'!G6/'Historical FS'!G54,0) -> 0.82681768 | H30: =IFERROR('Historical FS'!H6/'Historical FS'!H54,0) -> 0.96497584 | I30: =IFERROR('Historical FS'!I6/'Historical FS'!I54,0) -> 0.98619135 | J30: =IFERROR('Historical FS'!J6/'Historical FS'!J54,0) -> 1.0545614 | K30: =IFERROR('Historical FS'!K6/'Historical FS'!K54,0) -> 0.78551134 | M30: =IFERROR(AVERAGE(D30:K30),0) -> 1.124625 | N30: =IFERROR(MEDIAN(D30:K30),0) -> 1.0203764
B31: Capital Turnover Ratio | C31: =IFERROR('Historical FS'!C6/SUM('Historical FS'!C48,'Historical FS'!C50),0) -> 4.6829857 | D31: =IFERROR('Historical FS'!D6/SUM('Historical FS'!D48,'Historical FS'!D50),0) -> 7.9790389 | E31: =IFERROR('Historical FS'!E6/SUM('Historical FS'!E48,'Historical FS'!E50),0) -> 6.0276026 | F31: =IFERROR('Historical FS'!F6/SUM('Historical FS'!F48,'Historical FS'!F50),0) -> 6.0217902 | G31: =IFERROR('Historical FS'!G6/SUM('Historical FS'!G48,'Historical FS'!G50),0) -> 5.7417544 | H31: =IFERROR('Historical FS'!H6/SUM('Historical FS'!H48,'Historical FS'!H50),0) -> 6.7230473 | I31: =IFERROR('Historical FS'!I6/SUM('Historical FS'!I48,'Historical FS'!I50),0) -> 8.2606155 | J31: =IFERROR('Historical FS'!J6/SUM('Historical FS'!J48,'Historical FS'!J50),0) -> 8.1415526 | K31: =IFERROR('Historical FS'!K6/SUM('Historical FS'!K48,'Historical FS'!K50),0) -> 4.2563611 | M31: =IFERROR(AVERAGE(D31:K31),0) -> 6.6439703 | N31: =IFERROR(MEDIAN(D31:K31),0) -> 6.375325
B33: Debtor Days | C33: =IFERROR(365/C27,0) -> 32.582784 | D33: =IFERROR(365/D27,0) -> 31.896549 | E33: =IFERROR(365/E27,0) -> 34.719009 | F33: =IFERROR(365/F27,0) -> 34.255085 | G33: =IFERROR(365/G27,0) -> 34.934625 | H33: =IFERROR(365/H27,0) -> 23.951136 | I33: =IFERROR(365/I27,0) -> 24.532851 | J33: =IFERROR(365/J27,0) -> 21.141048 | K33: =IFERROR(365/K27,0) -> 21.525515 | M33: =IFERROR(AVERAGE(D33:K33),0) -> 28.369477 | N33: =IFERROR(MEDIAN(D33:K33),0) -> 28.2147
B34: Payable Days | C34: =IFERROR(365/C28,0) -> 582.78882 | D34: =IFERROR(365/D28,0) -> 588.56149 | E34: =IFERROR(365/E28,0) -> 631.47491 | F34: =IFERROR(365/F28,0) -> 613.99695 | G34: =IFERROR(365/G28,0) -> 871.81939 | H34: =IFERROR(365/H28,0) -> 711.69555 | I34: =IFERROR(365/I28,0) -> 724.05162 | J34: =IFERROR(365/J28,0) -> 668.62455 | K34: =IFERROR(365/K28,0) -> 632.07111 | M34: =IFERROR(AVERAGE(D34:K34),0) -> 680.28695 | N34: =IFERROR(MEDIAN(D34:K34),0) -> 650.34783
B35: Inventory Days | C35: =IFERROR(365/C29,0) -> 153.51869 | D35: =IFERROR(365/D29,0) -> 137.87529 | E35: =IFERROR(365/E29,0) -> 131.24385 | F35: =IFERROR(365/F29,0) -> 135.8778 | G35: =IFERROR(365/G29,0) -> 108.76729 | H35: =IFERROR(365/H29,0) -> 110.83495 | I35: =IFERROR(365/I29,0) -> 109.04281 | J35: =IFERROR(365/J29,0) -> 111.6179 | K35: =IFERROR(365/K29,0) -> 109.66545 | M35: =IFERROR(AVERAGE(D35:K35),0) -> 119.36567 | N35: =IFERROR(MEDIAN(D35:K35),0) -> 111.22643
B36: Cash Conversion Cycle (in Days) | C36: =IFERROR(C33+C35-C34,0) -> -396.68734 | D36: =IFERROR(D33+D35-D34,0) -> -418.78965 | E36: =IFERROR(E33+E35-E34,0) -> -465.51206 | F36: =IFERROR(F33+F35-F34,0) -> -443.86407 | G36: =IFERROR(G33+G35-G34,0) -> -728.11747 | H36: =IFERROR(H33+H35-H34,0) -> -576.90946 | I36: =IFERROR(I33+I35-I34,0) -> -590.47597 | J36: =IFERROR(J33+J35-J34,0) -> -535.8656 | K36: =IFERROR(K33+K35-K34,0) -> -500.88015 | M36: =IFERROR(AVERAGE(D36:K36),0) -> -532.5518 | N36: =IFERROR(MEDIAN(D36:K36),0) -> -518.37288
B38: CFO/Sale | C38: =IFERROR('Historical FS'!C71/'Historical FS'!C6,0) -> 0.017475974 | D38: =IFERROR('Historical FS'!D71/'Historical FS'!D6,0) -> 0.10932879 | E38: =IFERROR('Historical FS'!E71/'Historical FS'!E6,0) -> 0.052173403 | F38: =IFERROR('Historical FS'!F71/'Historical FS'!F6,0) -> 0.028941598 | G38: =IFERROR('Historical FS'!G71/'Historical FS'!G6,0) -> 0.11229458 | H38: =IFERROR('Historical FS'!H71/'Historical FS'!H6,0) -> 0.14276553 | I38: =IFERROR('Historical FS'!I71/'Historical FS'!I6,0) -> 0.12199315 | J38: =IFERROR('Historical FS'!J71/'Historical FS'!J6,0) -> 0.10601995 | K38: =IFERROR('Historical FS'!K71/'Historical FS'!K6,0) -> 0.12736414 | M38: =IFERROR(AVERAGE(D38:K38),0) -> 0.10011014 | N38: =IFERROR(MEDIAN(D38:K38),0) -> 0.11081168
B39: CFO/Total Assets | C39: =IFERROR('Historical FS'!C71/'Historical FS'!C65,0) -> 0.011721356 | D39: =IFERROR('Historical FS'!D71/'Historical FS'!D65,0) -> 0.077601108 | E39: =IFERROR('Historical FS'!E71/'Historical FS'!E65,0) -> 0.033991794 | F39: =IFERROR('Historical FS'!F71/'Historical FS'!F65,0) -> 0.019288317 | G39: =IFERROR('Historical FS'!G71/'Historical FS'!G65,0) -> 0.058584294 | H39: =IFERROR('Historical FS'!H71/'Historical FS'!H65,0) -> 0.081926241 | I39: =IFERROR('Historical FS'!I71/'Historical FS'!I65,0) -> 0.071924999 | J39: =IFERROR('Historical FS'!J71/'Historical FS'!J65,0) -> 0.064197282 | K39: =IFERROR('Historical FS'!K71/'Historical FS'!K65,0) -> 0.069467864 | M39: =IFERROR(AVERAGE(D39:K39),0) -> 0.059622737 | N39: =IFERROR(MEDIAN(D39:K39),0) -> 0.066832573
B40: CFO/Total Debt | C40: =IFERROR('Historical FS'!C71/'Historical FS'!C50,0) -> 0.085654149 | D40: =IFERROR('Historical FS'!D71/'Historical FS'!D50,0) -> 0.94233116 | E40: =IFERROR('Historical FS'!E71/'Historical FS'!E50,0) -> 0.33307106 | F40: =IFERROR('Historical FS'!F71/'Historical FS'!F50,0) -> 0.18391903 | G40: =IFERROR('Historical FS'!G71/'Historical FS'!G50,0) -> 0.68222679 | H40: =IFERROR('Historical FS'!H71/'Historical FS'!H50,0) -> 1.0139696 | I40: =IFERROR('Historical FS'!I71/'Historical FS'!I50,0) -> 1.0735122 | J40: =IFERROR('Historical FS'!J71/'Historical FS'!J50,0) -> 0.91328342 | K40: =IFERROR('Historical FS'!K71/'Historical FS'!K50,0) -> 0.55696217 | M40: =IFERROR(AVERAGE(D40:K40),0) -> 0.71240943 | N40: =IFERROR(MEDIAN(D40:K40),0) -> 0.7977551

Sheet Forecasting
B2: ='Data Sheet'!$B$1&" - "&'Data Sheet'!A17& " Forecasting" -> TATA CONSUMER PRODUCTS LTD - Sales Forecasting | G2: ='Data Sheet'!$B$1&" - "&'Historical FS'!B18& " Forecasting" -> TATA CONSUMER PRODUCTS LTD - EBITDA Forecasting | L2: ='Data Sheet'!$B$1&" - "&'Historical FS'!B38& " Forecasting" -> TATA CONSUMER PRODUCTS LTD - Earnings per Share Forecasting
B3: Year Weight | C3: Year | D3: Sales | E3: Sales Growth | G3: Year Weight | H3: Year | I3: EBITDA | J3: EBITDA Growth | L3: Year Weight | M3: Year | N3: EPS | O3: EPS Growth
B4: 1 | C4: ='Data Sheet'!$B16 -> 42460 | D4: {=TRANSPOSE('Data Sheet'!B17:K17)} -> 6636.54 | G4: 1 | H4: ='Data Sheet'!$B16 -> 42460 | I4: {=TRANSPOSE('Historical FS'!C18:M18)} -> 1191.08 | L4: 1 | M4: ='Data Sheet'!$B16 -> 42460 | N4: {=TRANSPOSE('Historical FS'!C38:L38)} -> 11.555996
B5: 2 | C5: =C4+365 -> 42825 | D5: 6779.55 | E5: =D5/D4-1 -> 0.021548879 | G5: 2 | H5: =H4+365 -> 42825 | I5: 1625.39 | J5: =I5/I4-1 -> 0.36463546 | L5: 2 | M5: =M4+365 -> 42825 | N5: 18.454532 | O5: =N5/N4-1 -> 0.59696586
B6: 3 | C6: =C5+365 -> 43190 | D6: 6815.35 | E6: =D6/D5-1 -> 0.0052805865 | G6: 3 | H6: =H5+365 -> 43190 | I6: 1613.48 | J6: =I6/I5-1 -> -0.0073274722 | L6: 3 | M6: =M5+365 -> 43190 | N6: 19.359323 | O6: =N6/N5-1 -> 0.049028119
B7: 4 | C7: =C6+365 -> 43555 | D7: 7251.5 | E7: =D7/D6-1 -> 0.063995246 | G7: 4 | H7: =H6+365 -> 43555 | I7: 1577.8 | J7: =I7/I6-1 -> -0.022113692 | L7: 4 | M7: =M6+365 -> 43555 | N7: 17.422643 | O7: =N7/N6-1 -> -0.10003862
B8: 5 | C8: =C7+365 -> 43920 | D8: 9637.42 | E8: =D8/D7-1 -> 0.32902434 | G8: 5 | H8: =H7+365 -> 43920 | I8: 2184.73 | J8: =I8/I7-1 -> 0.38466853 | L8: 5 | M8: =M7+365 -> 43920 | N8: 16.624556 | O8: =N8/N7-1 -> -0.045807446
B9: 6 | C9: =C8+365 -> 44285 | D9: 11602.03 | E9: =D9/D8-1 -> 0.20385228 | G9: 6 | H9: =H8+365 -> 44285 | I9: 2364.45 | J9: =I9/I8-1 -> 0.082261881 | L9: 6 | M9: =M8+365 -> 44285 | N9: 18.012017 | O9: =N9/N8-1 -> 0.083458519
B10: 7 | C10: =C9+365 -> 44650 | D10: 12425.37 | E10: =D10/D9-1 -> 0.070965167 | G10: 7 | H10: =H9+365 -> 44650 | I10: 2727 | J10: =I10/I9-1 -> 0.15333376 | L10: 7 | M10: =M9+365 -> 44650 | N10: 20.889969 | O10: =N10/N9-1 -> 0.15977955
B11: 8 | C11: =C10+365 -> 45015 | D11: 13783.16 | E11: =D11/D10-1 -> 0.10927562 | G11: 8 | H11: =H10+365 -> 45015 | I11: 2702.95 | J11: =I11/I10-1 -> -0.0088192153 | L11: 8 | M11: =M10+365 -> 45015 | N11: 19.329014 | O11: =N11/N10-1 -> -0.07472268
B12: 9 | C12: =C11+365 -> 45380 | D12: 15205.85 | E12: =D12/D11-1 -> 0.10321944 | G12: 9 | H12: =H11+365 -> 45380 | I12: 3421.09 | J12: =I12/I11-1 -> 0.26568749 | L12: 9 | M12: =M11+365 -> 45380 | N12: 25.461344 | O12: =N12/N11-1 -> 0.31726036
B13: 10 | C13: =C12+365 -> 45745 | D13: 17618.3 | E13: =D13/D12-1 -> 0.15865276 | G13: 10 | H13: =H12+365 -> 45745 | I13: 3546.96 | J13: =I13/I12-1 -> 0.036792367 | L13: 10 | M13: =M12+365 -> 45745 | N13: 22.837595 | O13: =N13/N12-1 -> -0.10304834
B14: 11 | C14: =C13+365 -> 46110 | D14: =FORECAST(B14,$D$4:$D$13,$B$4:$B$13) -> 17780.347 | E14: =D14/D13-1 -> 0.0091976714 | G14: 11 | H14: =H13+365 -> 46110 | I14: =FORECAST(G14,$I$4:$I$13,$G$4:$G$13) -> 3723.7427 | J14: =I14/I13-1 -> 0.049840615 | L14: 11 | M14: =M13+365 -> 46110 | N14: =FORECAST(L14,$N$4:$N$13,$L$4:$L$13) -> 24.402031 | O14: =N14/N13-1 -> 0.068502676
B15: 12 | C15: =C14+365 -> 46475 | D15: =FORECAST(B15,$D$4:$D$13,$B$4:$B$13) -> 19053.955 | E15: =D15/D14-1 -> 0.071630059 | G15: 12 | H15: =H14+365 -> 46475 | I15: =FORECAST(G15,$I$4:$I$13,$G$4:$G$13) -> 3983.4244 | J15: =I15/I14-1 -> 0.069736762 | L15: 12 | M15: =M14+365 -> 46475 | N15: =FORECAST(L15,$N$4:$N$13,$L$4:$L$13) -> 25.385182 | O15: =N15/N14-1 -> 0.040289734
B16: 13 | C16: =C15+365 -> 46840 | D16: =FORECAST(B16,$D$4:$D$13,$B$4:$B$13) -> 20327.562 | E16: =D16/D15-1 -> 0.066842152 | G16: 13 | H16: =H15+365 -> 46840 | I16: =FORECAST(G16,$I$4:$I$13,$G$4:$G$13) -> 4243.1062 | J16: =I16/I15-1 -> 0.065190582 | L16: 13 | M16: =M15+365 -> 46840 | N16: =FORECAST(L16,$N$4:$N$13,$L$4:$L$13) -> 26.368334 | O16: =N16/N15-1 -> 0.038729339
B17: 14 | C17: =C16+365 -> 47205 | D17: =FORECAST(B17,$D$4:$D$13,$B$4:$B$13) -> 21601.169 | E17: =D17/D16-1 -> 0.06265421 | G17: 14 | H17: =H16+365 -> 47205 | I17: =FORECAST(G17,$I$4:$I$13,$G$4:$G$13) -> 4502.7879 | J17: =I17/I16-1 -> 0.061200862 | L17: 14 | M17: =M16+365 -> 47205 | N17: =FORECAST(L17,$N$4:$N$13,$L$4:$L$13) -> 27.351485 | O17: =N17/N16-1 -> 0.037285304
B18: 15 | C18: =C17+365 -> 47570 | D18: =FORECAST(B18,$D$4:$D$13,$B$4:$B$13) -> 22874.777 | E18: =D18/D17-1 -> 0.058960111 | G18: 15 | H18: =H17+365 -> 47570 | I18: =FORECAST(G18,$I$4:$I$13,$G$4:$G$13) -> 4762.4697 | J18: =I18/I17-1 -> 0.057671327 | L18: 15 | M18: =M17+365 -> 47570 | N18: =FORECAST(L18,$N$4:$N$13,$L$4:$L$13) -> 28.334636 | O18: =N18/N17-1 -> 0.035945081

Sheet WACC
B2: Weighted Average Cost of Capital
B4: All figures are in INR unless stated otherwise.
B6: Peer Comps
G7: Debt/ | H7: Debt/ | I7: Levered | J7: Unlevered
B8: Name of the Comp | C8: Country | D8: Total Debt | E8: Total Equity | F8: Tax Rate 1 | G8: Equity | H8: Capital | I8: Beta 2 | J8: Beta 3
B10: Tata Consumer | C10: India | D10: 2576.11 | E10: 104408.54 | F10: 0.3 | G10: =D10/E10 -> 0.024673365 | H10: =D10/(D10+E10) -> 0.024079249 | I10: ='Beta-Regression'!K12 -> 1.1041091 | J10: =I10/(1+(1-F10)*G10) -> 1.0853634
B11: Hindustan Unilever | C11: India | D11: 1775 | E11: 489913.95 | F11: 0.3 | G11: =D11/E11 -> 0.0036230852 | H11: =D11/(D11+E11) -> 0.0036100059 | I11: ='Beta-Regression'!G76 -> 0.8591114 | J11: =I11/(1+(1-F11)*G11) -> 0.85693807
B12: Nestle India | C12: India | D12: 476.85 | E12: 234423.98 | F12: 0.3 | G12: =D12/E12 -> 0.0020341349 | H12: =D12/(D12+E12) -> 0.0020300056 | I12: ='Beta-Regression'!G140 -> 0.94835109 | J12: =I12/(1+(1-F12)*G12) -> 0.94700266
B13: Britannia India | C13: India | D13: 2196.3 | E13: 133305.91 | F13: 0.3 | G13: =D13/E13 -> 0.016475639 | H13: =D13/(D13+E13) -> 0.016208592 | I13: ='Beta-Regression'!G204 -> 0.98003933 | J13: =I13/(1+(1-F13)*G13) -> 0.96886545
B14: Dabur India | C14: India | D14: 1301.43 | E14: 73403.95 | F14: 0.3 | G14: =D14/E14 -> 0.0177297 | H14: =D14/(D14+E14) -> 0.017420834 | I14: ='Beta-Regression'!G268 -> 0.87170002 | J14: =I14/(1+(1-F14)*G14) -> 0.86101415
B15: Godrej Consumer | C15: India | D15: 4113.49 | E15: 102518.84 | F15: 0.3 | G15: =D15/E15 -> 0.040124235 | H15: =D15/(D15+E15) -> 0.038576387 | I15: ='Beta-Regression'!G332 -> 1.1039214 | J15: =I15/(1+(1-F15)*G15) -> 1.0737627
B16: Marico | C16: India | D16: 575 | E16: 97406.98 | F16: 0.3 | G16: =D16/E16 -> 0.0059030677 | H16: =D16/(D16+E16) -> 0.005868426 | I16: ='Beta-Regression'!G396 -> 0.72500091 | J16: =I16/(1+(1-F16)*G16) -> 0.72201743
E18: Average | F18: =AVERAGE(F10:F16) -> 0.3 | G18: =AVERAGE(G10:G16) -> 0.015794747 | H18: =AVERAGE(H10:H16) -> 0.015399071 | I18: =AVERAGE(I10:I16) -> 0.9417476 | J18: =AVERAGE(J10:J16) -> 0.93070911
E19: Median | F19: =MEDIAN(F10:F16) -> 0.3 | G19: =MEDIAN(G10:G16) -> 0.016475639 | H19: =MEDIAN(H10:H16) -> 0.016208592 | I19: =MEDIAN(I10:I16) -> 0.94835109 | J19: =MEDIAN(J10:J16) -> 0.94700266
B22: Cost of Debt | G22: Cost of Equity
B24: Pre-tax Cost of Debt | E24: =290/D10 -> 0.11257283 | G24: Risk Free Rate | J24: 0.07043
B25: Tax Rate | E25: =F19 -> 0.3 | G25: Equity Risk Premium | J25: =Rm!G7-WACC!J24 -> 0.093862308
B26: After Tax Cost of Debt | E26: =E24*(1-E25) -> 0.078800983 | G26: Levered Beta 4 | J26: =J35 -> 0.95774737
G27: Cost of Equity | J27: =J24+(J25*J26) -> 0.16032638
B30: Capital Structure | G30: Levered Beta
D32: Current | E32: Target | G32: Comps Median Unlevered Beta | J32: =J19 -> 0.94700266
B33: Total Debt | C33: =D10 -> 2576.11 | D33: =C33/$C$35 -> 0.024079249 | E33: =H19 -> 0.016208592 | G33: Target Debt/Equity | J33: =E33 -> 0.016208592
B34: Market Capitalization | C34: =E10 -> 104408.54 | D34: =C34/$C$35 -> 0.97592075 | E34: =E35-E33 -> 0.98379141 | G34: Tax Rate | J34: =F19 -> 0.3
B35: Total Capitalization | C35: =SUM(C33:C34) -> 106984.65 | D35: =SUM(D33:D34) -> 1 | E35: 1 | G35: Levered Beta | J35: =J32*(1+(1-J34)*J33) -> 0.95774737
G37: Weighted Average Cost of Capital
B38: 1. Tax Rate considered as the Marginal Tax Rate for the country.
B39: 2. Levered Beta is based on 5 year Monthly data. | G39: Cost of Equity | J39: =J27 -> 0.16032638
B40: 3. Unlevered Beta = Levered Beta/(1+(1-Tax Rate)*(Debt/equity)) | G40: Equity Weight | J40: =E34 -> 0.98379141
B41: 4. Levered Beta = Unlevered Beta*(1+(1-Tax Rate)*(Debt/equity))
G42: Cost of Debt | J42: =E26 -> 0.078800983
G43: Debt Weight | J43: =E33 -> 0.016208592
G45: WACC | J45: =(J39*J40)+(J42*J43) -> 0.15900497

Sheet Beta-Regression
B2: Regression Beta
B4: Tata Consumer Monthly Returns | F4: NIFTY Returns | J4: Beta Drifting | M4: Beta | N4: =N31 -> 1.1388121
B6: Closing Date | C6: Adj Close | D6: Return | F6: Closing Date | G6: Adj Close | H6: Return | J6: Levered Raw Beta | K6: =N4 -> 1.1388121
B7: 44287 | C7: 644.09 | F7: 44287 | G7: 14631.1 | J7: Raw Beta Weight | K7: 0.75
B8: 44317 | C8: 638.65 | D8: =C8/C7-1 -> -0.0084460246 | F8: 44317 | G8: 15582.8 | H8: =G8/G7-1 -> 0.065046374
B9: 44348 | C9: 725.77 | D9: =C9/C8-1 -> 0.13641275 | F9: 44348 | G9: 15721.5 | H9: =G9/G8-1 -> 0.0089008394 | J9: Market Beta | K9: 1
B10: 44378 | C10: 731.71 | D10: =C10/C9-1 -> 0.008184411 | F10: 44378 | G10: 15763.05 | H10: =G10/G9-1 -> 0.0026428776 | J10: Market Beta weight | K10: 0.25
B11: 44409 | C11: 836.88 | D11: =C11/C10-1 -> 0.14373181 | F11: 44409 | G11: 17132.2 | H11: =G11/G10-1 -> 0.086858191
B12: 44440 | C12: 787.2 | D12: =C12/C11-1 -> -0.05936335 | F12: 44440 | G12: 17618.15 | H12: =G12/G11-1 -> 0.028364717 | J12: Adjusted Beta | K12: =(K6*K7)+(K9*K10) -> 1.1041091
B13: 44470 | C13: 783.23 | D13: =C13/C12-1 -> -0.0050431911 | F13: 44470 | G13: 17671.65 | H13: =G13/G12-1 -> 0.0030366412
B14: 44501 | C14: 753.33 | D14: =C14/C13-1 -> -0.038175249 | F14: 44501 | G14: 16983.2 | H14: =G14/G13-1 -> -0.038957879 | M14: SUMMARY OUTPUT
B15: 44531 | C15: 719.33 | D15: =C15/C14-1 -> -0.045132943 | F15: 44531 | G15: 17354.05 | H15: =G15/G14-1 -> 0.021836285
B16: 44562 | C16: 703.7 | D16: =C16/C15-1 -> -0.021728553 | F16: 44562 | G16: 17339.85 | H16: =G16/G15-1 -> -0.0008182528 | M16: Regression Statistics
B17: 44593 | C17: 695.28 | D17: =C17/C16-1 -> -0.011965326 | F17: 44593 | G17: 16793.9 | H17: =G17/G16-1 -> -0.031485278 | M17: Multiple R | N17: 0.65471179
B18: 44621 | C18: 752.17 | D18: =C18/C17-1 -> 0.08182315 | F18: 44621 | G18: 17464.75 | H18: =G18/G17-1 -> 0.039946052 | M18: R Square | N18: 0.42864752
B19: 44652 | C19: 797.02 | D19: =C19/C18-1 -> 0.059627478 | F19: 44652 | G19: 17102.55 | H19: =G19/G18-1 -> -0.020738917 | M19: Adjusted R Square | N19: 0.4186238
B20: 44682 | C20: 735.1 | D20: =C20/C19-1 -> -0.077689393 | F20: 44682 | G20: 16584.55 | H20: =G20/G19-1 -> -0.030287881 | M20: Standard Error | N20: 0.051806116
B21: 44713 | C21: 683.43 | D21: =C21/C20-1 -> -0.070289756 | F21: 44713 | G21: 15780.25 | H21: =G21/G20-1 -> -0.048496944 | M21: Observations | N21: 59
B22: 44743 | C22: 791.56 | D22: =C22/C21-1 -> 0.15821664 | F22: 44743 | G22: 17158.25 | H22: =G22/G21-1 -> 0.087324345
B23: 44774 | C23: 789.61 | D23: =C23/C22-1 -> -0.0024634898 | F23: 44774 | G23: 17759.3 | H23: =G23/G22-1 -> 0.035029796 | M23: ANOVA
B24: 44805 | C24: 782.98 | D24: =C24/C23-1 -> -0.0083965502 | F24: 44805 | G24: 17094.35 | H24: =G24/G23-1 -> -0.037442354 | N24: df | O24: SS | P24: MS | Q24: F | R24: Significance F
B25: 44835 | C25: 751.09 | D25: =C25/C24-1 -> -0.04072901 | F25: 44835 | G25: 18012.2 | H25: =G25/G24-1 -> 0.053693179 | M25: Regression | N25: 1 | O25: 0.11477126 | P25: 0.11477126 | Q25: 42.763285 | R25: 1.8556133e-08
B26: 44866 | C26: 797.8 | D26: =C26/C25-1 -> 0.062189618 | F26: 44866 | G26: 18758.35 | H26: =G26/G25-1 -> 0.041424701 | M26: Residual | N26: 57 | O26: 0.1529808 | P26: 0.0026838737
B27: 44896 | C27: 747.97 | D27: =C27/C26-1 -> -0.062459263 | F27: 44896 | G27: 18105.3 | H27: =G27/G26-1 -> -0.03481383 | M27: Total | N27: 58 | O27: 0.26775206
B28: 44927 | C28: 711.44 | D28: =C28/C27-1 -> -0.048838857 | F28: 44927 | G28: 17662.15 | H28: =G28/G27-1 -> -0.024476258
B29: 44958 | C29: 697.59 | D29: =C29/C28-1 -> -0.019467559 | F29: 44958 | G29: 17303.95 | H29: =G29/G28-1 -> -0.020280657 | N29: Coefficients | O29: Standard Error | P29: t Stat | Q29: P-value | R29: Lower 95% | S29: Upper 95% | T29: Lower 95.0% | U29: Upper 95.0%
B30: 44986 | C30: 691.3 | D30: =C30/C29-1 -> -0.0090167577 | F30: 44986 | G30: 17359.75 | H30: =G30/G29-1 -> 0.0032246973 | M30: Intercept | N30: 0.0009123456 | O30: 0.0068849802 | P30: 0.13251245 | Q30: 0.89504566 | R30: -0.012874589 | S30: 0.014699281 | T30: -0.012874589 | U30: 0.014699281
B31: 45017 | C31: 744.94 | D31: =C31/C30-1 -> 0.077592941 | F31: 45017 | G31: 18065 | H31: =G31/G30-1 -> 0.040625585 | M31: X Variable 1 | N31: 1.1388121 | O31: 0.17414722 | P31: 6.5393643 | Q31: 1.8556133e-08 | R31: 0.79008831 | S31: 1.4875359 | T31: 0.79008831 | U31: 1.4875359
B32: 45047 | C32: 778.88 | D32: =C32/C31-1 -> 0.045560716 | F32: 45047 | G32: 18534.4 | H32: =G32/G31-1 -> 0.025983947
B33: 45078 | C33: 848.72 | D33: =C33/C32-1 -> 0.089667214 | F33: 45078 | G33: 19189.05 | H33: =G33/G32-1 -> 0.035320809
B34: 45108 | C34: 847.14 | D34: =C34/C33-1 -> -0.0018616269 | F34: 45108 | G34: 19753.8 | H34: =G34/G33-1 -> 0.029430847
B35: 45139 | C35: 822.54 | D35: =C35/C34-1 -> -0.029038884 | F35: 45139 | G35: 19253.8 | H35: =G35/G34-1 -> -0.025311586
B36: 45170 | C36: 864.49 | D36: =C36/C35-1 -> 0.051000559 | F36: 45170 | G36: 19638.3 | H36: =G36/G35-1 -> 0.019970084
B37: 45200 | C37: 887.75 | D37: =C37/C36-1 -> 0.026906037 | F37: 45200 | G37: 19079.6 | H37: =G37/G36-1 -> -0.028449509
B38: 45231 | C38: 927.43 | D38: =C38/C37-1 -> 0.044697268 | F38: 45231 | G38: 20133.15 | H38: =G38/G37-1 -> 0.055218663
B39: 45261 | C39: 1071.42 | D39: =C39/C38-1 -> 0.155257 | F39: 45261 | G39: 21731.4 | H39: =G39/G38-1 -> 0.079384001
B40: 45292 | C40: 1102.18 | D40: =C40/C39-1 -> 0.028709563 | F40: 45292 | G40: 21725.7 | H40: =G40/G39-1 -> -0.00026229327
B41: 45323 | C41: 1173.21 | D41: =C41/C40-1 -> 0.064445009 | F41: 45323 | G41: 21982.8 | H41: =G41/G40-1 -> 0.011833911
B42: 45352 | C42: 1080.68 | D42: =C42/C41-1 -> -0.078869086 | F42: 45352 | G42: 22326.9 | H42: =G42/G41-1 -> 0.015653147
B43: 45383 | C43: 1092.66 | D43: =C43/C42-1 -> 0.011085613 | F43: 45383 | G43: 22604.85 | H43: =G43/G42-1 -> 0.012449108
... B66: 46082 | C66: 1014.8 | D66: =C66/C65-1 -> -0.11060473 | F66: 46082 | G66: 22331.4 | H66: =G66/G65-1 -> -0.11308192
B68: Hindustan Unilever Monthly Returns | F68: Beta Drifting | I68: Beta | J68: =K91 -> 0.81214854
B70: Closing Date | C70: Adj Close | D70: Return | F70: Levered Raw Beta | G70: =J68 -> 0.81214854
B71: 44287 | C71: 2164.52 | F71: Raw Beta Weight | G71: 0.75
B72: 44317 | C72: 2151.92 | D72: =C72/C71-1 -> -0.005821152
B73: 44348 | C73: 2272.62 | D73: =C73/C72-1 -> 0.056089446 | F73: Market Beta | G73: 1
B74: 44378 | C74: 2161.24 | D74: =C74/C73-1 -> -0.049009513 | F74: Market Beta weight | G74: 0.25 | J74: SUMMARY OUTPUT
B75: 44409 | C75: 2523.22 | D75: =C75/C74-1 -> 0.16748718
B76: 44440 | C76: 2502.57 | D76: =C76/C75-1 -> -0.0081839871 | F76: Adjusted Beta | G76: =(G70*G71)+(G73*G74) -> 0.8591114 | J76: Regression Statistics
B77: 44470 | C77: 2216.68 | D77: =C77/C76-1 -> -0.11423856 | J77: Multiple R | K77: 0.49024764
B78: 44501 | C78: 2159.84 | D78: =C78/C77-1 -> -0.025641951 | J78: R Square | K78: 0.24034275
B79: 44531 | C79: 2199.55 | D79: =C79/C78-1 -> 0.018385621 | J79: Adjusted R Square | K79: 0.22701543
B80: 44562 | C80: 2119.02 | D80: =C80/C79-1 -> -0.036612034 | J80: Standard Error | K80: 0.056892611
B81: 44593 | C81: 2024.29 | D81: =C81/C80-1 -> -0.044704628 | J81: Observations | K81: 59
B82: 44621 | C82: 1909.24 | D82: =C82/C81-1 -> -0.056834742
B83: 44652 | C83: 2082.77 | D83: =C83/C82-1 -> 0.090889569 | J83: ANOVA
B84: 44682 | C84: 2193.11 | D84: =C84/C83-1 -> 0.052977525 | K84: df | L84: SS | M84: MS | N84: F | O84: Significance F
B85: 44713 | C85: 2078.81 | D85: =C85/C84-1 -> -0.052117769 | J85: Regression | K85: 1 | L85: 0.058371375 | M85: 0.058371375 | N85: 18.03384 | O85: 8.0995078e-05
B86: 44743 | C86: 2479.63 | D86: =C86/C85-1 -> 0.19281223 | J86: Residual | K86: 57 | L86: 0.18449584 | M86: 0.0032367691
B87: 44774 | C87: 2500.74 | D87: =C87/C86-1 -> 0.0085133669 | J87: Total | K87: 58 | L87: 0.24286722
B88: 44805 | C88: 2535.15 | D88: =C88/C87-1 -> 0.013759927
B89: 44835 | C89: 2398.12 | D89: =C89/C88-1 -> -0.054052028 | K89: Coefficients | L89: Standard Error | M89: t Stat | N89: P-value | O89: Lower 95% | P89: Upper 95% | Q89: Lower 95.0% | R89: Upper 95.0%
B90: 44866 | C90: 2523.77 | D90: =C90/C89-1 -> 0.05239521 | J90: Intercept | K90: -0.0052987831 | L90: 0.0075609701 | M90: -0.7008073 | N90: 0.48627437 | O90: -0.020439365 | P90: 0.0098417985 | Q90: -0.020439365 | R90: 0.0098417985
B91: 44896 | C91: 2424 | D91: =C91/C90-1 -> -0.039532129 | J91: X Variable 1 | K91: 0.81214854 | L91: 0.19124556 | M91: 4.2466268 | N91: 8.0995078e-05 | O91: 0.4291859 | P91: 1.1951112 | Q91: 0.4291859 | R91: 1.1951112
B92: 44927 | C92: 2438.86 | D92: =C92/C91-1 -> 0.006130363
B93: 44958 | C93: 2328.98 | D93: =C93/C92-1 -> -0.045053837
B94: 44986 | C94: 2423.34 | D94: =C94/C93-1 -> 0.040515591
B95: 45017 | C95: 2325.8 | D95: =C95/C94-1 -> -0.040250233
B96: 45047 | C96: 2524.8 | D96: =C96/C95-1 -> 0.085561957
B97: 45078 | C97: 2534.84 | D97: =C97/C96-1 -> 0.0039765526
B98: 45108 | C98: 2443.56 | D98: =C98/C97-1 -> -0.036010162
B99: 45139 | C99: 2390.36 | D99: =C99/C98-1 -> -0.021771514
B100: 45170 | C100: 2352.72 | D100: =C100/C99-1 -> -0.015746582
B101: 45200 | C101: 2370.28 | D101: =C101/C100-1 -> 0.0074637016
B102: 45231 | C102: 2429.01 | D102: =C102/C101-1 -> 0.024777663
B103: 45261 | C103: 2560.63 | D103: =C103/C102-1 -> 0.054186685
... B130: 46082 | C130: 2055.2 | D130: =C130/C129-1 -> -0.12099568
B132: Nestle India Monthly Returns | F132: Beta Drifting | I132: Beta | J132: =K155 -> 0.93113479
B134: Closing Date | C134: Adj Close | D134: Return | F134: Levered Raw Beta | G134: =J132 -> 0.93113479
B135: 44287 | C135: 770.98 | F135: Raw Beta Weight | G135: 0.75
B136: 44317 | C136: 841.07 | D136: =C136/C135-1 -> 0.09091027
B137: 44348 | C137: 838.1 | D137: =C137/C136-1 -> -0.0035312162 | F137: Market Beta | G137: 1
B138: 44378 | C138: 841.41 | D138: =C138/C137-1 -> 0.0039494094 | F138: Market Beta weight | G138: 0.25 | J138: SUMMARY OUTPUT
B139: 44409 | C139: 925.3 | D139: =C139/C138-1 -> 0.099701691
B140: 44440 | C140: 924.25 | D140: =C140/C139-1 -> -0.0011347671 | F140: Adjusted Beta | G140: =(G134*G135)+(G137*G138) -> 0.94835109 | J140: Regression Statistics
B141: 44470 | C141: 903.08 | D141: =C141/C140-1 -> -0.022905058 | J141: Multiple R | K141: 0.66332802
B142: 44501 | C142: 915.71 | D142: =C142/C141-1 -> 0.013985472 | J142: R Square | K142: 0.44000406
B143: 44531 | C143: 942.15 | D143: =C143/C142-1 -> 0.02887377 | J143: Adjusted R Square | K143: 0.43017957
B144: 44562 | C144: 885.54 | D144: =C144/C143-1 -> -0.060085974 | J144: Standard Error | K144: 0.04139079
B145: 44593 | C145: 843.35 | D145: =C145/C144-1 -> -0.047643246 | J145: Observations | K145: 59
B146: 44621 | C146: 830.99 | D146: =C146/C145-1 -> -0.014655837
B147: 44652 | C147: 876.4 | D147: =C147/C146-1 -> 0.054645664 | J147: ANOVA
B148: 44682 | C148: 850.03 | D148: =C148/C147-1 -> -0.030089 | K148: df | L148: SS | M148: MS | N148: F | O148: Significance F
B149: 44713 | C149: 839.39 | D149: =C149/C148-1 -> -0.012517205 | J149: Regression | K149: 1 | L149: 0.076728039 | M149: 0.076728039 | N149: 44.786452 | O149: 1.0344592e-08
B150: 44743 | C150: 930.16 | D150: =C150/C149-1 -> 0.10813805 | J150: Residual | K150: 57 | L150: 0.097652259 | M150: 0.0017131975
B151: 44774 | C151: 957.39 | D151: =C151/C150-1 -> 0.029274533 | J151: Total | K151: 58 | L151: 0.1743803
B152: 44805 | C152: 919.86 | D152: =C152/C151-1 -> -0.039200326
B153: 44835 | C153: 978.41 | D153: =C153/C152-1 -> 0.06365099 | K153: Coefficients | L153: Standard Error | M153: t Stat | N153: P-value | O153: Lower 95% | P153: Upper 95% | Q153: Lower 95.0% | R153: Upper 95.0%
B154: 44866 | C154: 975.56 | D154: =C154/C153-1 -> -0.0029128893 | J154: Intercept | K154: 0.0012491331 | L154: 0.005500794 | M154: 0.22708233 | N154: 0.82117221 | O154: -0.0097660168 | P154: 0.012264283 | Q154: -0.0097660168 | R154: 0.012264283
B155: 44896 | C155: 947.63 | D155: =C155/C154-1 -> -0.02862971 | J155: X Variable 1 | K155: 0.93113479 | L155: 0.13913591 | M155: 6.6922681 | N155: 1.0344592e-08 | O155: 0.65251994 | P155: 1.2097496 | Q155: 0.65251994 | R155: 1.2097496
...

Sheet Rm
B2: Return on Markets
B4: Year | C4: Annual
B5: 2000 | C5: -0.1465 | E5: Average Return | G5: =AVERAGE(C5:C30) -> 0.15149231
B6: 2001 | C6: -0.1618 | E6: Dividend Yield | G6: 0.0128
B7: 2002 | C7: 0.0325 | E7: Total Market Returns | G7: =SUM(G5:G6) -> 0.16429231
B8: 2003 | C8: 0.719
B9: 2004 | C9: 0.1068
B10: 2005 | C10: 0.3634
B11: 2006 | C11: 0.3983
B12: 2007 | C12: 0.5477
B13: 2008 | C13: -0.5179
B14: 2009 | C14: 0.7576
B15: 2010 | C15: 0.1795
B16: 2011 | C16: -0.2462
B17: 2012 | C17: 0.277
B18: 2013 | C18: 0.0676
B19: 2014 | C19: 0.3139
... B30: 2025 | C30: 0.1051

Sheet Common Size Statement
B2: ="Common Size Income Statement"&" - "&'Data Sheet'!$B$1 -> Common Size Income Statement - TATA CONSUMER PRODUCTS LTD
B4: Particulars | C4: ='Data Sheet'!B$16 -> 42460 | D4: ='Data Sheet'!C$16 -> 42825 | E4: ='Data Sheet'!D$16 -> 43190 | F4: ='Data Sheet'!E$16 -> 43555 | G4: ='Data Sheet'!F$16 -> 43921 | H4: ='Data Sheet'!G$16 -> 44286 | I4: ='Data Sheet'!H$16 -> 44651 | J4: ='Data Sheet'!I$16 -> 45016 | ... L4: ='Data Sheet'!K$16 -> 45747
B6: ='Data Sheet'!A17 -> Sales | C6: ='Data Sheet'!B17/'Data Sheet'!B$17 -> 1 | D6: ='Data Sheet'!C17/'Data Sheet'!C$17 -> 1 | E6: ='Data Sheet'!D17/'Data Sheet'!D$17 -> 1 | F6: ='Data Sheet'!E17/'Data Sheet'!E$17 -> 1 | G6: ='Data Sheet'!F17/'Data Sheet'!F$17 -> 1 | H6: ='Data Sheet'!G17/'Data Sheet'!G$17 -> 1 | I6: ='Data Sheet'!H17/'Data Sheet'!H$17 -> 1 | J6: ='Data Sheet'!I17/'Data Sheet'!I$17 -> 1 | ... L6: ='Data Sheet'!K17/'Data Sheet'!K$17 -> 1
B7: ='Data Sheet'!A18 -> Raw Material Cost | C7: ='Data Sheet'!B18/'Data Sheet'!B$17 -> 0.54267585 | D7: ='Data Sheet'!C18/'Data Sheet'!C$17 -> 0.46694102 | E7: ='Data Sheet'!D18/'Data Sheet'!D$17 -> 0.54965776 | F7: ='Data Sheet'!E18/'Data Sheet'!E$17 -> 0.55465076 | G7: ='Data Sheet'!F18/'Data Sheet'!F$17 -> 0.56061685 | H7: ='Data Sheet'!G18/'Data Sheet'!G$17 -> 0.54885136 | I7: ='Data Sheet'!H18/'Data Sheet'!H$17 -> 0.50889591 | J7: ='Data Sheet'!I18/'Data Sheet'!I$17 -> 0.51563357 | ... L7: ='Data Sheet'!K18/'Data Sheet'!K$17 -> 0.51007645
B8: ='Data Sheet'!A19 -> Change in Inventory | C8: ='Data Sheet'!B19/'Data Sheet'!B$17 -> -0.0030301934 | D8: ='Data Sheet'!C19/'Data Sheet'!C$17 -> 0.00010177667 | E8: ='Data Sheet'!D19/'Data Sheet'!D$17 -> 0.006866852 | F8: ='Data Sheet'!E19/'Data Sheet'!E$17 -> 0.0019871751 | G8: ='Data Sheet'!F19/'Data Sheet'!F$17 -> -0.00080727 | H8: ='Data Sheet'!G19/'Data Sheet'!G$17 -> 0.012889124 | I8: ='Data Sheet'!H19/'Data Sheet'!H$17 -> 0.0032015143 | J8: ='Data Sheet'!I19/'Data Sheet'!I$17 -> 0.019870625 | ... L8: ='Data Sheet'!K19/'Data Sheet'!K$17 -> 0.02057463
B9: ='Data Sheet'!A20 -> Power and Fuel | C9: ='Data Sheet'!B20/'Data Sheet'!B$17 -> 0.012244332 | D9: ='Data Sheet'!C20/'Data Sheet'!C$17 -> 0.012270726 | E9: ='Data Sheet'!D20/'Data Sheet'!D$17 -> 0.012775573 | F9: ='Data Sheet'!E20/'Data Sheet'!E$17 -> 0.012311935 | G9: ='Data Sheet'!F20/'Data Sheet'!F$17 -> 0.010774668 | H9: ='Data Sheet'!G20/'Data Sheet'!G$17 -> 0.0083916349 | I9: ='Data Sheet'!H20/'Data Sheet'!H$17 -> 0.009971534 | J9: ='Data Sheet'!I20/'Data Sheet'!I$17 -> 0.010841491 | ... L9: ='Data Sheet'!K20/'Data Sheet'!K$17 -> 0.0088663492
B10: ='Data Sheet'!A21 -> Other Mfr. Exp | C10: ='Data Sheet'!B21/'Data Sheet'!B$17 -> 0.028677594 | D10: ='Data Sheet'!C21/'Data Sheet'!C$17 -> 0.088148918 | E10: ='Data Sheet'!D21/'Data Sheet'!D$17 -> 0.028566398 | F10: ='Data Sheet'!E21/'Data Sheet'!E$17 -> 0.028902986 | G10: ='Data Sheet'!F21/'Data Sheet'!F$17 -> 0.024744174 | H10: ='Data Sheet'!G21/'Data Sheet'!G$17 -> 0.08117114 | I10: ='Data Sheet'!H21/'Data Sheet'!H$17 -> 0.091714774 | J10: ='Data Sheet'!I21/'Data Sheet'!I$17 -> 0.11450204 | ... L10: ='Data Sheet'!K21/'Data Sheet'!K$17 -> 0.10683494
B11: ='Data Sheet'!A22 -> Employee Cost | C11: ='Data Sheet'!B22/'Data Sheet'!B$17 -> 0.12130719 | D11: ='Data Sheet'!C22/'Data Sheet'!C$17 -> 0.12315714 | E11: ='Data Sheet'!D22/'Data Sheet'!D$17 -> 0.12051765 | F11: ='Data Sheet'!E22/'Data Sheet'!E$17 -> 0.11119079 | G11: ='Data Sheet'!F22/'Data Sheet'!F$17 -> 0.091808804 | H11: ='Data Sheet'!G22/'Data Sheet'!G$17 -> 0.083625883 | I11: ='Data Sheet'!H22/'Data Sheet'!H$17 -> 0.084343565 | J11: ='Data Sheet'!I22/'Data Sheet'!I$17 -> 0.081284698 | ... L11: ='Data Sheet'!K22/'Data Sheet'!K$17 -> 0.081171282
B12: ='Data Sheet'!A23 -> Selling and admin | C12: ='Data Sheet'!B23/'Data Sheet'!B$17 -> 0.13906041 | D12: ='Data Sheet'!C23/'Data Sheet'!C$17 -> 0.13672294 | E12: ='Data Sheet'!D23/'Data Sheet'!D$17 -> 0.12583947 | F12: ='Data Sheet'!E23/'Data Sheet'!E$17 -> 0.13352134 | G12: ='Data Sheet'!F23/'Data Sheet'!F$17 -> 0.13262471 | H12: ='Data Sheet'!G23/'Data Sheet'!G$17 -> 0.12251821 | I12: ='Data Sheet'!H23/'Data Sheet'!H$17 -> 0.13615933 | J12: ='Data Sheet'!I23/'Data Sheet'!I$17 -> 0.12952472 | ... L12: ='Data Sheet'!K23/'Data Sheet'!K$17 -> 0.1278994
B13: ='Data Sheet'!A24 -> Other Expenses | C13: ='Data Sheet'!B24/'Data Sheet'!B$17 -> 0.097868769 | D13: ='Data Sheet'!C24/'Data Sheet'!C$17 -> 0.056167445 | E13: ='Data Sheet'!D24/'Data Sheet'!D$17 -> 0.046418746 | F13: ='Data Sheet'!E24/'Data Sheet'!E$17 -> 0.053030408 | G13: ='Data Sheet'!F24/'Data Sheet'!F$17 -> 0.044547192 | H13: ='Data Sheet'!G24/'Data Sheet'!G$17 -> 0.035271414 | I13: ='Data Sheet'!H24/'Data Sheet'!H$17 -> 0.033788129 | J13: ='Data Sheet'!I24/'Data Sheet'!I$17 -> 0.033392923 | ... L13: ='Data Sheet'!K24/'Data Sheet'!K$17 -> 0.045000369
B14: ='Data Sheet'!A25 -> Other Income | C14: ='Data Sheet'!B25/'Data Sheet'!B$17 -> 0.005656562 | D14: ='Data Sheet'!C25/'Data Sheet'!C$17 -> 0.013039214 | E14: ='Data Sheet'!D25/'Data Sheet'!D$17 -> 0.01071405 | F14: ='Data Sheet'!E25/'Data Sheet'!E$17 -> 0.017077846 | G14: ='Data Sheet'!F25/'Data Sheet'!F$17 -> -0.016933993 | H14: ='Data Sheet'!G25/'Data Sheet'!G$17 -> 0.0078201832 | I14: ='Data Sheet'!H25/'Data Sheet'!H$17 -> 0.0070822841 | J14: ='Data Sheet'!I25/'Data Sheet'!I$17 -> 0.023821098 | ... L14: ='Data Sheet'!K25/'Data Sheet'!K$17 -> 0.010678669
B15: ='Data Sheet'!A26 -> Depreciation | C15: ='Data Sheet'!B26/'Data Sheet'!B$17 -> 0.017598025 | D15: ='Data Sheet'!C26/'Data Sheet'!C$17 -> 0.018591204 | E15: ='Data Sheet'!D26/'Data Sheet'!D$17 -> 0.017026272 | F15: ='Data Sheet'!E26/'Data Sheet'!E$17 -> 0.01690271 | G15: ='Data Sheet'!F26/'Data Sheet'!F$17 -> 0.025080364 | H15: ='Data Sheet'!G26/'Data Sheet'!G$17 -> 0.021956502 | I15: ='Data Sheet'!H26/'Data Sheet'!H$17 -> 0.022374384 | J15: ='Data Sheet'!I26/'Data Sheet'!I$17 -> 0.022061704 | ... L15: ='Data Sheet'!K26/'Data Sheet'!K$17 -> 0.034097501
B16: ='Data Sheet'!A27 -> Interest | C16: ='Data Sheet'!B27/'Data Sheet'!B$17 -> 0.0176146 | D16: ='Data Sheet'!C27/'Data Sheet'!C$17 -> 0.013500896 | E16: ='Data Sheet'!D27/'Data Sheet'!D$17 -> 0.0062740725 | F16: ='Data Sheet'!E27/'Data Sheet'!E$17 -> 0.0072357443 | G16: ='Data Sheet'!F27/'Data Sheet'!F$17 -> 0.0080789257 | H16: ='Data Sheet'!G27/'Data Sheet'!G$17 -> 0.0059205156 | I16: ='Data Sheet'!H27/'Data Sheet'!H$17 -> 0.0058573708 | J16: ='Data Sheet'!I27/'Data Sheet'!I$17 -> 0.0063236587 | ... L16: ='Data Sheet'!K27/'Data Sheet'!K$17 -> 0.01647151
B17: ='Data Sheet'!A28 -> Profit before tax | C17: ='Data Sheet'!B28/'Data Sheet'!B$17 -> 0.025579594 | D17: ='Data Sheet'!C28/'Data Sheet'!C$17 -> 0.097640699 | E17: ='Data Sheet'!D28/'Data Sheet'!D$17 -> 0.11050496 | F17: ='Data Sheet'!E28/'Data Sheet'!E$17 -> 0.10131835 | G17: ='Data Sheet'!F28/'Data Sheet'!F$17 -> 0.083983058 | H17: ='Data Sheet'!G28/'Data Sheet'!G$17 -> 0.11300264 | I17: ='Data Sheet'!H28/'Data Sheet'!H$17 -> 0.1171788 | J17: ='Data Sheet'!I28/'Data Sheet'!I$17 -> 0.13012691 | ... L17: ='Data Sheet'!K28/'Data Sheet'!K$17 -> 0.10083549
... B20: ='Data Sheet'!A31 -> Dividend Amount | C20: ='Data Sheet'!B31/'Data Sheet'!B$17 -> 0.021396692 | D20: ='Data Sheet'!C31/'Data Sheet'!C$17 -> 0.021876083 | E20: ='Data Sheet'!D31/'Data Sheet'!D$17 -> 0.021761171 | F20: ='Data Sheet'!E31/'Data Sheet'!E$17 -> 0.021758257 | G20: ='Data Sheet'!F31/'Data Sheet'!F$17 -> 0.025819151 | H20: ='Data Sheet'!G31/'Data Sheet'!G$17 -> 0.032171094 | I20: ='Data Sheet'!H31/'Data Sheet'!H$17 -> 0.044873513 | J20: ='Data Sheet'!I31/'Data Sheet'!I$17 -> 0.056953558 | ... L20: ='Data Sheet'!K31/'Data Sheet'!K$17 -> 0.046334777
B21: ='Data Sheet'!A33&"(Operating)" -> EBITDA(Operating) | C21: ='Data Sheet'!B33/'Data Sheet'!B$17 -> 0.064518559 | D21: ='Data Sheet'!C33/'Data Sheet'!C$17 -> 0.11878665 | E21: ='Data Sheet'!D33/'Data Sheet'!D$17 -> 0.12328494 | F21: ='Data Sheet'!E33/'Data Sheet'!E$17 -> 0.11640488 | G21: ='Data Sheet'!F33/'Data Sheet'!F$17 -> 0.10931556 | H21: ='Data Sheet'!G33/'Data Sheet'!G$17 -> 0.12906276 | I21: ='Data Sheet'!H33/'Data Sheet'!H$17 -> 0.13388817 | J21: ='Data Sheet'!I33/'Data Sheet'!I$17 -> 0.14815543 | ... L21: ='Data Sheet'!K33/'Data Sheet'!K$17 -> 0.14562415
B23: ="Common Size Balance Sheet"&" - "&'Data Sheet'!$B$1 -> Common Size Balance Sheet - TATA CONSUMER PRODUCTS LTD
B25: Particulars | C25: ='Data Sheet'!B$16 -> 42460 | D25: ='Data Sheet'!C$16 -> 42825 | E25: ='Data Sheet'!D$16 -> 43190 | F25: ='Data Sheet'!E$16 -> 43555 | G25: ='Data Sheet'!F$16 -> 43921 | H25: ='Data Sheet'!G$16 -> 44286 | I25: ='Data Sheet'!H$16 -> 44651 | J25: ='Data Sheet'!I$16 -> 45016 | ... L25: ='Data Sheet'!K$16 -> 45747
B27: ='Data Sheet'!A61&" Liabilities" -> Total Liabilities | C27: ='Data Sheet'!B61/'Data Sheet'!B$61 -> 1 | D27: ='Data Sheet'!C61/'Data Sheet'!C$61 -> 1 | E27: ='Data Sheet'!D61/'Data Sheet'!D$61 -> 1 | F27: ='Data Sheet'!E61/'Data Sheet'!E$61 -> 1 | G27: ='Data Sheet'!F61/'Data Sheet'!F$61 -> 1 | H27: ='Data Sheet'!G61/'Data Sheet'!G$61 -> 1 | I27: ='Data Sheet'!H61/'Data Sheet'!H$61 -> 1 | J27: ='Data Sheet'!I61/'Data Sheet'!I$61 -> 1 | ... L27: ='Data Sheet'!K61/'Data Sheet'!K$61 -> 1
B28: ='Data Sheet'!A57 -> Equity Share Capital | C28: ='Data Sheet'!B57/'Data Sheet'!B$61 -> 0.0063781234 | D28: ='Data Sheet'!C57/'Data Sheet'!C$61 -> 0.0066074014 | E28: ='Data Sheet'!D57/'Data Sheet'!D$61 -> 0.0060330225 | F28: ='Data Sheet'!E57/'Data Sheet'!E$61 -> 0.005800189 | G28: ='Data Sheet'!F57/'Data Sheet'!F$61 -> 0.0049888919 | H28: ='Data Sheet'!G57/'Data Sheet'!G$61 -> 0.004558355 | I28: ='Data Sheet'!H57/'Data Sheet'!H$61 -> 0.0043729807 | J28: ='Data Sheet'!I57/'Data Sheet'!I$61 -> 0.0040812758 | ... L28: ='Data Sheet'!K57/'Data Sheet'!K$61 -> 0.0031086419
B29: ='Data Sheet'!A58 -> Reserves | C29: ='Data Sheet'!B58/'Data Sheet'!B$61 -> 0.62498332 | D29: ='Data Sheet'!C58/'Data Sheet'!C$61 -> 0.64936905 | E29: ='Data Sheet'!D58/'Data Sheet'!D$61 -> 0.66615523 | F29: ='Data Sheet'!E58/'Data Sheet'!E$61 -> 0.66802626 | G29: ='Data Sheet'!F58/'Data Sheet'!F$61 -> 0.74285012 | H29: ='Data Sheet'!G58/'Data Sheet'!G$61 -> 0.71433765 | I29: ='Data Sheet'!H58/'Data Sheet'!H$61 -> 0.71411022 | J29: ='Data Sheet'!I58/'Data Sheet'!I$61 -> 0.71098592 | ... L29: ='Data Sheet'!K58/'Data Sheet'!K$61 -> 0.62525109
B30: ='Data Sheet'!A59 -> Borrowings | C30: ='Data Sheet'!B59/'Data Sheet'!B$61 -> 0.13684516 | D30: ='Data Sheet'!C59/'Data Sheet'!C$61 -> 0.082350145 | E30: ='Data Sheet'!D59/'Data Sheet'!D$61 -> 0.10205568 | F30: ='Data Sheet'!E59/'Data Sheet'!E$61 -> 0.10487396 | G30: ='Data Sheet'!F59/'Data Sheet'!F$61 -> 0.085872168 | H30: ='Data Sheet'!G59/'Data Sheet'!G$61 -> 0.080797534 | I30: ='Data Sheet'!H59/'Data Sheet'!H$61 -> 0.066999702 | J30: ='Data Sheet'!I59/'Data Sheet'!I$61 -> 0.070292837 | ... L30: ='Data Sheet'!K59/'Data Sheet'!K$61 -> 0.07516913
B31: ='Data Sheet'!A60 -> Other Liabilities | C31: ='Data Sheet'!B60/'Data Sheet'!B$61 -> 0.23179339 | D31: ='Data Sheet'!C60/'Data Sheet'!C$61 -> 0.26167341 | E31: ='Data Sheet'!D60/'Data Sheet'!D$61 -> 0.22575606 | F31: ='Data Sheet'!E60/'Data Sheet'!E$61 -> 0.22129959 | G31: ='Data Sheet'!F60/'Data Sheet'!F$61 -> 0.16628882 | H31: ='Data Sheet'!G60/'Data Sheet'!G$61 -> 0.20030646 | I31: ='Data Sheet'!H60/'Data Sheet'!H$61 -> 0.2145171 | J31: ='Data Sheet'!I60/'Data Sheet'!I$61 -> 0.21463996 | ... L31: ='Data Sheet'!K60/'Data Sheet'!K$61 -> 0.29647113
B33: ='Data Sheet'!A66&" Assets" -> Total Assets | C33: ='Data Sheet'!B75/'Data Sheet'!B$75 -> 1 | D33: ='Data Sheet'!C75/'Data Sheet'!C$75 -> 1 | E33: ='Data Sheet'!D75/'Data Sheet'!D$75 -> 1 | F33: ='Data Sheet'!E75/'Data Sheet'!E$75 -> 1 | G33: ='Data Sheet'!F75/'Data Sheet'!F$75 -> 1 | H33: ='Data Sheet'!G75/'Data Sheet'!G$75 -> 1 | I33: ='Data Sheet'!H75/'Data Sheet'!H$75 -> 1 | J33: ='Data Sheet'!I75/'Data Sheet'!I$75 -> 1 | ... L33: ='Data Sheet'!K75/'Data Sheet'!K$75 -> 1
B34: ="Fixed Assets"&" "&'Data Sheet'!A62 -> Fixed Assets Net Block | C34: ='Data Sheet'!B62/'Data Sheet'!B$75 -> 0.47113826 | D34: ='Data Sheet'!C62/'Data Sheet'!C$75 -> 0.47873455 | E34: ='Data Sheet'!D62/'Data Sheet'!D$75 -> 0.45868369 | F34: ='Data Sheet'!E62/'Data Sheet'!E$75 -> 0.45156277 | G34: ='Data Sheet'!F62/'Data Sheet'!F$75 -> 0.63097574 | H34: ='Data Sheet'!G62/'Data Sheet'!G$75 -> 0.59467984 | I34: ='Data Sheet'!H62/'Data Sheet'!H$75 -> 0.59783761 | J34: ='Data Sheet'!I62/'Data Sheet'!I$75 -> 0.57419202 | ... L34: ='Data Sheet'!K62/'Data Sheet'!K$75 -> 0.67472264
B35: ='Data Sheet'!A63 -> Capital Work in Progress | C35: ='Data Sheet'!B63/'Data Sheet'!B$75 -> 0.0039839268 | D35: ='Data Sheet'!C63/'Data Sheet'!C$75 -> 0.0066157771 | E35: ='Data Sheet'!D63/'Data Sheet'!D$75 -> 0.012920667 | F35: ='Data Sheet'!E63/'Data Sheet'!E$75 -> 0.039005834 | G35: ='Data Sheet'!F63/'Data Sheet'!F$75 -> 0.005161576 | H35: ='Data Sheet'!G63/'Data Sheet'!G$75 -> 0.0055817096 | I35: ='Data Sheet'!H63/'Data Sheet'!H$75 -> 0.011718696 | J35: ='Data Sheet'!I63/'Data Sheet'!I$75 -> 0.012955525 | ... L35: ='Data Sheet'!K63/'Data Sheet'!K$75 -> 0.0068518929
B36: ='Data Sheet'!A64 -> Investments | C36: ='Data Sheet'!B64/'Data Sheet'!B$75 -> 0.1380468 | D36: ='Data Sheet'!C64/'Data Sheet'!C$75 -> 0.15191893 | E36: ='Data Sheet'!D64/'Data Sheet'!D$75 -> 0.11101775 | F36: ='Data Sheet'!E64/'Data Sheet'!E$75 -> 0.1091531 | G36: ='Data Sheet'!F64/'Data Sheet'!F$75 -> 0.071609762 | H36: ='Data Sheet'!G64/'Data Sheet'!G$75 -> 0.039860381 | I36: ='Data Sheet'!H64/'Data Sheet'!H$75 -> 0.037830838 | J36: ='Data Sheet'!I64/'Data Sheet'!I$75 -> 0.06295313 | ... L36: ='Data Sheet'!K64/'Data Sheet'!K$75 -> 0.030432018
B37: ='Data Sheet'!A65 -> Other Assets | C37: ='Data Sheet'!B74/'Data Sheet'!B$75 -> 0.11168841 | D37: ='Data Sheet'!C74/'Data Sheet'!C$75 -> 0.088401608 | E37: ='Data Sheet'!D74/'Data Sheet'!D$75 -> 0.098593219 | F37: ='Data Sheet'!E74/'Data Sheet'!E$75 -> 0.094902157 | G37: ='Data Sheet'!F74/'Data Sheet'!F$75 -> 0.061868539 | H37: ='Data Sheet'!G74/'Data Sheet'!G$75 -> 0.058888149 | I37: ='Data Sheet'!H74/'Data Sheet'!H$75 -> 0.082075002 | J37: ='Data Sheet'!I74/'Data Sheet'!I$75 -> 0.073262635 | ... L37: ='Data Sheet'!K74/'Data Sheet'!K$75 -> 0.059045347
B38: ='Data Sheet'!A67 -> Receivables | C38: ='Data Sheet'!B67/'Data Sheet'!B$75 -> 0.059873105 | D38: ='Data Sheet'!C67/'Data Sheet'!C$75 -> 0.062027491 | E38: ='Data Sheet'!D67/'Data Sheet'!D$75 -> 0.061972553 | F38: ='Data Sheet'!E67/'Data Sheet'!E$75 -> 0.062546642 | G38: ='Data Sheet'!F67/'Data Sheet'!F$75 -> 0.049932767 | H38: ='Data Sheet'!G67/'Data Sheet'!G$75 -> 0.03765589 | I38: ='Data Sheet'!H67/'Data Sheet'!H$75 -> 0.039627765 | J38: ='Data Sheet'!I67/'Data Sheet'!I$75 -> 0.035072174 | ... L38: ='Data Sheet'!K67/'Data Sheet'!K$75 -> 0.027325575
B39: ='Data Sheet'!A68 -> Inventory | C39: ='Data Sheet'!B68/'Data Sheet'!B$75 -> 0.1646336 | D39: ='Data Sheet'!C68/'Data Sheet'!C$75 -> 0.15211995 | E39: ='Data Sheet'!D68/'Data Sheet'!D$75 -> 0.1384517 | F39: ='Data Sheet'!E68/'Data Sheet'!E$75 -> 0.14783451 | G39: ='Data Sheet'!F68/'Data Sheet'!F$75 -> 0.09267722 | H39: ='Data Sheet'!G68/'Data Sheet'!G$75 -> 0.11124642 | I39: ='Data Sheet'!H68/'Data Sheet'!H$75 -> 0.10754562 | J39: ='Data Sheet'!I68/'Data Sheet'!I$75 -> 0.11868956 | ... L39: ='Data Sheet'!K68/'Data Sheet'!K$75 -> 0.11309582
B40: ='Data Sheet'!A69 -> Cash & Bank | C40: ='Data Sheet'!B69/'Data Sheet'!B$75 -> 0.050635892 | D40: ='Data Sheet'!C69/'Data Sheet'!C$75 -> 0.06018169 | E40: ='Data Sheet'!D69/'Data Sheet'!D$75 -> 0.11836043 | F40: ='Data Sheet'!E69/'Data Sheet'!E$75 -> 0.094994982 | G40: ='Data Sheet'!F69/'Data Sheet'!F$75 -> 0.0877744 | H40: ='Data Sheet'!G69/'Data Sheet'!G$75 -> 0.15208761 | I40: ='Data Sheet'!H69/'Data Sheet'!H$75 -> 0.12336446 | J40: ='Data Sheet'!I69/'Data Sheet'!I$75 -> 0.12287496 | ... L40: ='Data Sheet'!K69/'Data Sheet'!K$75 -> 0.088526708

Sheet Raw FS
B2: Particulars | C2: 41699 | D2: 42064 | E2: 42430 | F2: 42795 | G2: 43160 | H2: 43525 | I2: 43891 | J2: 44256 | K2: 44621 | L2: 44986 | M2: 45352 | N2: 45717
B4: Equity Capital | C4: 62 | D4: 62 | E4: 63 | F4: 63 | G4: 63 | H4: 63 | I4: 92 | J4: 92 | K4: 92 | L4: 93 | M4: 95 | N4: 99
B5: Reserves | C5: 5787 | D5: 5431 | E5: 6184 | F5: 6202 | G5: 6968 | H5: 7269 | I5: 13723 | J5: 14442 | K5: 15050 | L5: 16184 | M5: 15962 | N5: 19902
B6: Borrowings - | C6: 1438 | D6: 1324 | E6: 1354 | F6: 787 | G6: 1068 | H6: 1141 | I6: 1586 | J6: 1634 | K6: 1412 | L6: 1600 | M6: 3477 | N6: 2393
B7: Long term Borrowings
B8: Short term Borrowings | C8: 348 | D8: 382 | E8: 409 | F8: 320 | G8: 400 | H8: 330 | I8: 388 | J8: 919 | K8: 769 | L8: 977 | M8: 2786 | N8: 1658
B9: Lease Liabilities | C9: 0 | D9: 0 | E9: 0 | F9: 0 | G9: 0 | H9: 0 | I9: 330 | J9: 427 | K9: 401 | L9: 417 | M9: 523 | N9: 544
B10: Other Borrowings | C10: 37 | D10: 58 | E10: 441 | F10: 16 | G10: 11 | H10: 24 | I10: 74 | J10: 0 | K10: 0 | L10: 0 | M10: 0 | N10: 0
B11: Other Liabilities -
B12: Non controlling int | C12: 924 | D12: 876 | E12: 862 | F12: 920 | G12: 1009 | H12: 1028 | I12: 1092 | J12: 1093 | K12: 1152 | L12: 850 | M12: 1379 | N12: 1389
B13: Trade Payables | C13: 769 | D13: 759 | E13: 677 | F13: 738 | G13: 706 | H13: 665 | I13: 944 | J13: 1625 | K13: 1916 | L13: 2348 | M13: 2707 | N13: 3508
B14: Advance from Customers | C14: 0 | D14: 0 | E14: 3 | F14: 6 | G14: 9 | H14: 6 | I14: 13 | J14: 41 | K14: 44 | L14: 52 | M14: 64 | N14: 65
B15: Other liability items | C15: 932 | D15: 1005 | E15: 751 | F15: 836 | G15: 638 | H15: 710 | I15: 1022 | J15: 1291 | K15: 1409 | L15: 1636 | M15: 4195 | N15: 4474
B16: Total Liabilities | C16: 9911 | D16: 9458 | E16: 9895 | F16: 9551 | G16: 10461 | H16: 10881 | I16: 18473 | J16: 20218 | K16: 21075 | L16: 22762 | M16: 27879 | N16: 31831
B18: Fixed Assets -
B19: Land | C19: 60 | D19: 60 | E19: 68 | F19: 60 | G19: 59 | H19: 63 | I19: 150 | J19: 146 | K19: 168 | L19: 172 | M19: 204 | N19: 192
B20: Building | C20: 238 | D20: 251 | E20: 266 | F20: 229 | G20: 254 | H20: 316 | I20: 528 | J20: 640 | K20: 714 | L20: 728 | M20: 963 | N20: 1027
B21: Estates | C21: 8 | D21: 8 | E21: 0 | F21: 0 | G21: 0 | H21: 0 | I21: 0 | J21: 0 | K21: 0 | L21: 0 | M21: 0 | N21: 0
B22: Plant Machinery | C22: 1313 | D22: 1366 | E22: 1387 | F22: 1305 | G22: 1409 | H22: 1465 | I22: 1956 | J22: 2054 | K22: 2273 | L22: 2442 | M22: 2811 | N22: 2785
B23: Equipments | C23: 7 | D23: 9 | E23: 9 | F23: 5 | G23: 7 | H23: 7 | I23: 8 | J23: 10 | K23: 9 | L23: 7 | M23: 0 | N23: 0
B24: Furniture n fittings | C24: 255 | D24: 283 | E24: 171 | F24: 165 | G24: 178 | H24: 190 | I24: 217 | J24: 229 | K24: 229 | L24: 246 | M24: 264 | N24: 295
B25: Vehicles | C25: 26 | D25: 27 | E25: 23 | F25: 24 | G25: 23 | H25: 22 | I25: 27 | J25: 25 | K25: 23 | L25: 20 | M25: 27 | N25: 34
B26: Intangible Assets | C26: 4243 | D26: 3892 | E26: 4408 | F26: 4173 | G26: 4408 | H26: 4485 | I26: 10566 | J26: 10812 | K26: 11008 | L26: 11405 | M26: 17596 | N26: 19944
B27: Other fixed assets | C27: 348 | D27: 386 | E27: 149 | F27: 327 | G27: 331 | H27: 349 | I27: 668 | J27: 576 | K27: 802 | L27: 881 | M27: 646 | N27: 720
B28: Gross Block | C28: 6498 | D28: 6283 | E28: 6480 | F28: 6287 | G28: 6669 | H28: 6898 | I28: 14120 | J28: 14492 | K28: 15226 | L28: 15900 | M28: 22510 | N28: 24997
B29: Accumulated Depreciation | C29: 1317 | D29: 1361 | E29: 1818 | F29: 1715 | G29: 1870 | H29: 1984 | I29: 2464 | J29: 2469 | K29: 2627 | L29: 2830 | M29: 3152 | N29: 3520
B30: Net Block | C30: =C28-C29 -> 5181 | D30: =D28-D29 -> 4922 | E30: =E28-E29 -> 4662 | F30: =F28-F29 -> 4572 | G30: =G28-G29 -> 4799 | H30: =H28-H29 -> 4914 | I30: =I28-I29 -> 11656 | J30: =J28-J29 -> 12023 | ... N30: =N28-N29 -> 21477
B32: CWIP | C32: 60 | D32: 47 | E32: 39 | F32: 63 | G32: 135 | H32: 424 | I32: 95 | J32: 113 | K32: 247 | L32: 295 | M32: 190 | N32: 218
B33: Investments | C33: 611 | D33: 622 | E33: 1366 | F33: 1451 | G33: 1161 | H33: 1188 | I33: 1323 | J33: 806 | K33: 797 | L33: 1433 | M33: 871 | N33: 969
B35: Other Assets -
B36: Inventories | C36: 1518 | D36: 1625 | E36: 1629 | F36: 1453 | G36: 1448 | H36: 1609 | I36: 1712 | J36: 2249 | K36: 2267 | L36: 2702 | M36: 2769 | N36: 3600
B37: Trade receivables - | C37: 654 | D37: 616 | E37: 592 | F37: 592 | G37: 648 | H37: 681 | I37: 922 | J37: 761 | K37: 835 | L37: 798 | M37: 897 | N37: 870
B38: Receivables over 6m | C38: 8 | D38: 10 | E38: 0 | F38: 0 | G38: 0 | H38: 0 | I38: 0 | J38: 0 | K38: 37 | L38: 73 | M38: 76 | N38: 85
B39: Receivables under 6m | C39: 656 | D39: 615 | E39: 599 | F39: 599 | G39: 661 | H39: 687 | I39: 937 | J39: 799 | K39: 838 | L39: 765 | M39: 861 | N39: 848
B40: Prov for Doubtful | C40: -10 | D40: -9 | E40: -6 | F40: -7 | G40: -13 | H40: -7 | I40: -15 | J40: -38 | K40: -39 | L40: -40 | M40: -41 | N40: -64
B41: Cash Equivalents | C41: 725 | D41: 544 | E41: 501 | F41: 575 | G41: 1238 | H41: 1034 | I41: 1621 | J41: 3075 | K41: 2600 | L41: 2797 | M41: 2454 | N41: 2818
B42: Loans n Advances | C42: 81 | D42: 39 | E42: 241 | F42: 428 | G42: 333 | H42: 108 | I42: 133 | J42: 207 | K42: 235 | L42: 235 | M42: 591 | N42: 737
B43: Other asset items | C43: 1081 | D43: 1042 | E43: 864 | F43: 417 | G43: 698 | H43: 925 | I43: 1010 | J43: 983 | K43: 1495 | L43: 1433 | M43: 749 | N43: 1143
B44: Total Assets | C44: 9911 | D44: 9458 | E44: 9895 | F44: 9551 | G44: 10461 | H44: 10881 | I44: 18473 | J44: 20218 | K44: 21075 | L44: 22762 | M44: 27879 | N44: 31831
B47: Cash from Operating Activity -
B48: Profit from operations | D48: 718 | E48: 650 | F48: 803 | G48: 794 | H48: 799 | I48: 1293 | J48: 1579 | K48: 1749 | L48: 1875 | M48: 2323 | N48: 2514
B49: Receivables | D49: -19 | E49: -48 | F49: -60 | G49: -114 | H49: -133 | I49: -177 | J49: 186 | K49: -149 | L49: -36 | M49: -45 | N49: 36
B50: Inventory | D50: -136 | E50: -70 | F50: 158 | G50: -13 | H50: -156 | I50: 81 | J50: -533 | K50: -1 | L50: -368 | M50: -3 | N50: -734
B51: Payables | D51: 23 | E51: -153 | F51: 51 | G51: -12 | H51: -133 | I51: 14 | J51: 531 | K51: 152 | L51: 379 | M51: 60 | N51: 704
B52: Other WC items | D52: 0 | E52: 0 | F52: 0 | G52: 0 | H52: 0 | I52: 0 | J52: 0 | K52: 0 | L52: 0 | M52: 0 | N52: 0
B53: Working capital changes | D53: -132 | E53: -272 | F53: 148 | G53: -139 | H53: -422 | I53: -82 | J53: 183 | K53: 2 | L53: -25 | M53: 11 | N53: 5
B54: Direct taxes | D54: -169 | E54: -234 | F54: -211 | G54: -299 | H54: -167 | I54: -128 | J54: -106 | K54: -235 | L54: -389 | M54: -398 | N54: -462
B55: Other operating items | D55: 0 | E55: -28 | F55: 0 | G55: 0 | H55: 0 | I55: 0 | J55: 0 | K55: 0 | L55: 0 | M55: 0 | N55: 0
B57: Cash from Investing Activity -
B58: Fixed assets purchased | D58: -179 | E58: -154 | F58: -138 | G58: -359 | H58: -282 | I58: -160 | J58: -211 | K58: -273 | L58: -312 | M58: -335 | N58: -460
B59: Fixed assets sold | D59: 0 | E59: 8 | F59: 6 | G59: 9 | H59: 26 | I59: 9 | J59: 32 | K59: 27 | L59: 172 | M59: 24 | N59: 45
B60: Investments purchased | D60: -75 | E60: 0 | F60: 0 | G60: -372 | H60: 0 | I60: -222 | J60: 0 | K60: 0 | L60: -533 | M60: 0 | N60: -29
B61: Investments sold | D61: 0 | E61: 175 | F61: 14 | G61: 811 | H61: 26 | I61: 65 | J61: 523 | K61: 136 | L61: 4 | M61: 710 | N61: 0
B62: Investment income | D62: 0 | E62: 0 | F62: 0 | G62: 0 | H62: 0 | I62: 0 | J62: 0 | K62: 0 | L62: 0 | M62: 0 | N62: 0
B63: Interest received | D63: 37 | E63: 17 | F63: 29 | G63: 33 | H63: 49 | I63: 51 | J63: 68 | K63: 75 | L63: 109 | M63: 187 | N63: 111
B64: Dividends received | D64: 24 | E64: 53 | F64: 29 | G64: 16 | H64: 5 | I64: 5 | J64: 5 | K64: 13 | L64: 13 | M64: 4 | N64: 7
B65: Invest in subsidiaries | D65: -93 | E65: 0 | F65: 0 | G65: 0 | H65: 0 | I65: 0 | J65: 0 | K65: 0 | L65: 0 | M65: 0 | N65: 0
B66: Investment in group cos | D66: 0 | E66: -51 | F66: -28 | G66: -13 | H66: -36 | I66: -53 | J66: -112 | K66: -236 | L66: -150 | M66: -25 | N66: -125
B67: Redemp n Canc of Shares | D67: 0 | E67: 0 | F67: 0 | G67: 51 | H67: 0 | I67: 30 | J67: 57 | K67: 11 | L67: 9 | M67: 0 | N67: 0
B68: Acquisition of companies | D68: 0 | E68: 0 | F68: 0 | G68: 0 | H68: 0 | I68: 0 | J68: -169 | K68: -511 | L68: -55 | M68: -3859 | N68: -1809
B69: Inter corporate deposits | D69: 111 | E69: 73 | F69: 313 | G69: 44 | H69: 44 | I69: 132 | J69: -73 | K69: -499 | L69: 70 | M69: 232 | N69: -144
B70: Other investing items | D70: -32 | E70: 24 | F70: -79 | G70: -250 | H70: 222 | I70: -481 | J70: -467 | K70: -61 | L70: -160 | M70: 1152 | N70: 99
B72: Cash from Financing Activity -
B73: Proceeds from shares | D73: 0 | E73: 0 | F73: 0 | G73: 0 | H73: 0 | I73: 0 | J73: 0 | K73: 0 | L73: 0 | M73: 0 | N73: 2981
B74: Redemption of debentures | D74: 0 | E74: 0 | F74: -398 | G74: 0 | H74: 0 | I74: 0 | J74: 0 | K74: 0 | L74: 0 | M74: 0 | N74: 0
B75: Proceeds from borrowings | D75: 50 | E75: 0 | F75: 0 | G75: 216 | H75: 101 | I75: 50 | J75: 12 | K75: 0 | L75: 53 | M75: 1327 | N75: 60
B76: Repayment of borrowings | D76: -181 | E76: -80 | F76: -87 | G76: 0 | H76: -65 | I76: -18 | J76: -69 | K76: -495 | L76: -56 | M76: -73 | N76: -1511
B77: Interest paid fin | D77: -82 | E77: -66 | F77: -61 | G77: -28 | H77: -44 | I77: -70 | J77: -65 | K77: -63 | L77: -82 | M77: -118 | N77: -261
B78: Dividends paid | D78: -161 | E78: -187 | F78: -189 | G78: -212 | H78: -216 | I78: -222 | J78: -267 | K78: -398 | L78: -573 | M78: -809 | N78: -741
B79: Financial liabilities | D79: 0 | E79: 0 | F79: 0 | G79: 0 | H79: 0 | I79: -49 | J79: -45 | K79: -53 | L79: -56 | M79: -71 | N79: -75
B80: Other financing items | D80: -18 | E80: 51 | F80: -81 | G80: -6 | H80: 0 | I80: 0 | J80: 9 | K80: 13 | L80: 0 | M80: 0 | N80: 0
B82: Net Cash Flow | D82: -182 | E82: -21 | F82: 70 | G82: 294 | H82: 39 | I82: 152 | J82: 884 | K82: -796 | L82: -87 | M82: 281 | N82: 206
B83: Free Cash Flow | D83: 239 | E83: -30 | F83: 609 | G83: 6 | H83: -47 | I83: 931 | J83: 1477 | K83: 1270 | L83: 1321 | M83: 1626 | N83: 1643
B84: CFO/OP | D84: 0.74 | E84: 0.96 | F84: 1.2 | G84: 0.78 | H84: 0.48 | I84: 0.94 | J84: 1.14 | K84: 1.02 | L84: 1 | M84: 1.02 | N84: 1.02

Sheet Intrinsic Growth
A2: # | B2: Calculation of ROIC | G2: ='Raw FS'!J2 -> 44256 | H2: ='Raw FS'!K2 -> 44621 | I2: ='Raw FS'!L2 -> 44986 | J2: ='Raw FS'!M2 -> 45352 | K2: ='Raw FS'!N2 -> 45717
B4: Current Assets
B5: ='Raw FS'!B36 -> Inventories | G5: ='Raw FS'!J36 -> 2249 | H5: ='Raw FS'!K36 -> 2267 | I5: ='Raw FS'!L36 -> 2702 | J5: ='Raw FS'!M36 -> 2769 | K5: ='Raw FS'!N36 -> 3600
B6: ='Raw FS'!B37 -> Trade receivables - | G6: ='Raw FS'!J37 -> 761 | H6: ='Raw FS'!K37 -> 835 | I6: ='Raw FS'!L37 -> 798 | J6: ='Raw FS'!M37 -> 897 | K6: ='Raw FS'!N37 -> 870
B7: ='Raw FS'!B42 -> Loans n Advances | G7: ='Raw FS'!J42 -> 207 | H7: ='Raw FS'!K42 -> 235 | I7: ='Raw FS'!L42 -> 235 | J7: ='Raw FS'!M42 -> 591 | K7: ='Raw FS'!N42 -> 737
B8: ='Raw FS'!B43 -> Other asset items | G8: ='Raw FS'!J43 -> 983 | H8: ='Raw FS'!K43 -> 1495 | I8: ='Raw FS'!L43 -> 1433 | J8: ='Raw FS'!M43 -> 749 | K8: ='Raw FS'!N43 -> 1143
B9: Total Current Assets | G9: =SUM(G5:G8) -> 4200 | H9: =SUM(H5:H8) -> 4832 | I9: =SUM(I5:I8) -> 5168 | J9: =SUM(J5:J8) -> 5006 | K9: =SUM(K5:K8) -> 6350
B11: Current Liabilities
B12: ='Raw FS'!B13 -> Trade Payables | G12: ='Raw FS'!J13 -> 1625 | H12: ='Raw FS'!K13 -> 1916 | I12: ='Raw FS'!L13 -> 2348 | J12: ='Raw FS'!M13 -> 2707 | K12: ='Raw FS'!N13 -> 3508
B13: ='Raw FS'!B14 -> Advance from Customers | G13: ='Raw FS'!J14 -> 41 | H13: ='Raw FS'!K14 -> 44 | I13: ='Raw FS'!L14 -> 52 | J13: ='Raw FS'!M14 -> 64 | K13: ='Raw FS'!N14 -> 65
B14: ='Raw FS'!B15 -> Other liability items | G14: ='Raw FS'!J15 -> 1291 | H14: ='Raw FS'!K15 -> 1409 | I14: ='Raw FS'!L15 -> 1636 | J14: ='Raw FS'!M15 -> 4195 | K14: ='Raw FS'!N15 -> 4474
B15: Total Current Liabilities | G15: =SUM(G12:G14) -> 2957 | H15: =SUM(H12:H14) -> 3369 | I15: =SUM(I12:I14) -> 4036 | J15: =SUM(J12:J14) -> 6966 | K15: =SUM(K12:K14) -> 8047
A17: # | B17: Net Working Capital | G17: =G9-G15 -> 1243 | H17: =H9-H15 -> 1463 | I17: =I9-I15 -> 1132 | J17: =J9-J15 -> -1960 | K17: =K9-K15 -> -1697
B19: Non Current Assets
B20: ='Raw FS'!B19 -> Land | G20: ='Raw FS'!J19 -> 146 | H20: ='Raw FS'!K19 -> 168 | I20: ='Raw FS'!L19 -> 172 | J20: ='Raw FS'!M19 -> 204 | K20: ='Raw FS'!N19 -> 192
B21: ='Raw FS'!B20 -> Building | G21: ='Raw FS'!J20 -> 640 | H21: ='Raw FS'!K20 -> 714 | I21: ='Raw FS'!L20 -> 728 | J21: ='Raw FS'!M20 -> 963 | K21: ='Raw FS'!N20 -> 1027
B22: ='Raw FS'!B21 -> Estates | G22: ='Raw FS'!J21 -> 0 | H22: ='Raw FS'!K21 -> 0 | I22: ='Raw FS'!L21 -> 0 | J22: ='Raw FS'!M21 -> 0 | K22: ='Raw FS'!N21 -> 0
B23: ='Raw FS'!B22 -> Plant Machinery | G23: ='Raw FS'!J22 -> 2054 | H23: ='Raw FS'!K22 -> 2273 | I23: ='Raw FS'!L22 -> 2442 | J23: ='Raw FS'!M22 -> 2811 | K23: ='Raw FS'!N22 -> 2785
B24: ='Raw FS'!B23 -> Equipments | G24: ='Raw FS'!J23 -> 10 | H24: ='Raw FS'!K23 -> 9 | I24: ='Raw FS'!L23 -> 7 | J24: ='Raw FS'!M23 -> 0 | K24: ='Raw FS'!N23 -> 0
B25: ='Raw FS'!B24 -> Furniture n fittings | G25: ='Raw FS'!J24 -> 229 | H25: ='Raw FS'!K24 -> 229 | I25: ='Raw FS'!L24 -> 246 | J25: ='Raw FS'!M24 -> 264 | K25: ='Raw FS'!N24 -> 295
B26: ='Raw FS'!B25 -> Vehicles | G26: ='Raw FS'!J25 -> 25 | H26: ='Raw FS'!K25 -> 23 | I26: ='Raw FS'!L25 -> 20 | J26: ='Raw FS'!M25 -> 27 | K26: ='Raw FS'!N25 -> 34
B27: ='Raw FS'!B26 -> Intangible Assets | G27: ='Raw FS'!J26 -> 10812 | H27: ='Raw FS'!K26 -> 11008 | I27: ='Raw FS'!L26 -> 11405 | J27: ='Raw FS'!M26 -> 17596 | K27: ='Raw FS'!N26 -> 19944
B28: ='Raw FS'!B27 -> Other fixed assets | G28: ='Raw FS'!J27 -> 576 | H28: ='Raw FS'!K27 -> 802 | I28: ='Raw FS'!L27 -> 881 | J28: ='Raw FS'!M27 -> 646 | K28: ='Raw FS'!N27 -> 720
B30: Gross Block | G30: =SUM(G20:G28) -> 14492 | H30: =SUM(H20:H28) -> 15226 | I30: =SUM(I20:I28) -> 15901 | J30: =SUM(J20:J28) -> 22511 | K30: =SUM(K20:K28) -> 24997
B31: Accumulated Depreciation | G31: =-'Raw FS'!J29 -> -2469 | H31: =-'Raw FS'!K29 -> -2627 | I31: =-'Raw FS'!L29 -> -2830 | J31: =-'Raw FS'!M29 -> -3152 | K31: =-'Raw FS'!N29 -> -3520
A32: # | B32: Net Non Current Assets | G32: =SUM(G30:G31) -> 12023 | H32: =SUM(H30:H31) -> 12599 | I32: =SUM(I30:I31) -> 13071 | J32: =SUM(J30:J31) -> 19359 | K32: =SUM(K30:K31) -> 21477
A34: # | B34: Invested Capital | G34: =SUM(G32,G17) -> 13266 | H34: =SUM(H32,H17) -> 14062 | I34: =SUM(I32,I17) -> 14203 | J34: =SUM(J32,J17) -> 17399 | K34: =SUM(K32,K17) -> 19780
B35: EBIT | G35: ='Historical FS'!H27+'Historical FS'!H21 -> 2109.71 | H35: ='Historical FS'!I27+'Historical FS'!I21 -> 2448.99 | I35: ='Historical FS'!J27+'Historical FS'!J21 -> 2398.87 | J35: ='Historical FS'!K27+'Historical FS'!K21 -> 3043.94 | K35: ='Historical FS'!L27+'Historical FS'!L21 -> 2946.22
B36: Marginal Tax Rate | G36: 0.25 | H36: 0.25 | I36: 0.25 | J36: 0.25 | K36: 0.25
B37: NOPAT | G37: =G35*(1-G36) -> 1582.2825 | H37: =H35*(1-H36) -> 1836.7425 | I37: =I35*(1-I36) -> 1799.1525 | J37: =J35*(1-J36) -> 2282.955 | K37: =K35*(1-K36) -> 2209.665
A39: # | B39: ROIC | G39: =G37/G34 -> 0.11927352 | H39: =H37/H34 -> 0.13061744 | I39: =I37/I34 -> 0.12667412 | J39: =J37/J34 -> 0.13121185 | K39: =K37/K34 -> 0.11171208
A41: # | B41: Calculation of Reinvestment Rate | G41: =G2 -> 44256 | H41: =H2 -> 44621 | I41: =I2 -> 44986 | J41: =J2 -> 45352 | K41: =K2 -> 45717
B43: Net Capex | G43: =-SUM('Raw FS'!J58:J59) -> 179 | H43: =-SUM('Raw FS'!K58:K59) -> 246 | I43: =-SUM('Raw FS'!L58:L59) -> 140 | J43: =-SUM('Raw FS'!M58:M59) -> 311 | K43: =-SUM('Raw FS'!N58:N59) -> 415
B44: Change in Working Capital | H44: =H17-G17 -> 220 | I44: =I17-H17 -> -331 | J44: =J17-I17 -> -3092 | K44: =K17-J17 -> 263
B46: EBIT | G46: =G35 -> 2109.71 | H46: =H35 -> 2448.99 | I46: =I35 -> 2398.87 | J46: =J35 -> 3043.94 | K46: =K35 -> 2946.22
B47: Marginal Tax Rate | G47: =G36 -> 0.25 | H47: =H36 -> 0.25 | I47: =I36 -> 0.25 | J47: =J36 -> 0.25 | K47: =K36 -> 0.25
B48: NOPAT | G48: =G37 -> 1582.2825 | H48: =H37 -> 1836.7425 | I48: =I37 -> 1799.1525 | J48: =J37 -> 2282.955 | K48: =K37 -> 2209.665
B50: Reinvestment | H50: =SUM(H43:H44) -> 466 | I50: =SUM(I43:I44) -> -191 | J50: =SUM(J43:J44) -> -2781 | K50: =SUM(K43:K44) -> 678
B52: Reinvestment Rate | H52: =H50/H48 -> 0.25371003 | I52: =I50/I48 -> -0.1061611 | J52: =J50/J48 -> -1.218158 | K52: =K50/K48 -> 0.30683384
I54: 4 Year Average | K54: =AVERAGE(H52:K52) -> -0.19094382
I55: 4 Year Median | K55: =MEDIAN(H52:K52) -> 0.073774469
A57: # | B57: Calculation of Growth Rate | G57: =G41 -> 44256 | H57: =H41 -> 44621 | I57: =I41 -> 44986 | J57: =J41 -> 45352 | K57: =K41 -> 45717
B59: Reinvestment Rate | H59: =H52 -> 0.25371003 | I59: =I52 -> -0.1061611 | J59: =J52 -> -1.218158 | K59: =K52 -> 0.30683384
B60: ROIC | H60: =H39 -> 0.13061744 | I60: =I39 -> 0.12667412 | J60: =J39 -> 0.13121185 | K60: =K39 -> 0.11171208
A62: # | B62: Intrinsic Growth | H62: =H59*H60 -> 0.033138956 | I62: =I59*I60 -> -0.013447863 | J62: =J59*J60 -> -0.15983677 | K62: =K59*K60 -> 0.034277048
I64: 4 Year Average | K64: =AVERAGE(H62:K62) -> -0.026467158
I65: 4 Year Median | K65: =MEDIAN(H62:K62) -> 0.0098455465

Sheet DCF
A2: # | B2: Calculation of PV of FCFF | E2: ='Data Sheet'!K16 -> 45747 | F2: =E2+365 -> 46112 | G2: =F2+365 -> 46477 | H2: =G2+365 -> 46842 | I2: =H2+365 -> 47207 | J2: =I2+365 -> 47572
B4: EBIT | E4: ='Data Sheet'!K33+'Data Sheet'!K27 -> 2855.85 | F4: =E4*(1+$E$14) -> 2883.9674 | G4: =F4*(1+$E$14) -> 2912.3616 | H4: =G4*(1+$E$14) -> 2941.0354 | I4: =H4*(1+$E$14) -> 2969.9915 | J4: =I4*(1+$E$14) -> 2999.2327
B5: Tax Rate | E5: 0.25 | F5: =E5 -> 0.25 | G5: =F5 -> 0.25 | H5: =G5 -> 0.25 | I5: =H5 -> 0.25 | J5: =I5 -> 0.25
B6: EBIT(1-T) | E6: =E4*(1-E5) -> 2141.8875 | F6: =F4*(1-F5) -> 2162.9756 | G6: =G4*(1-G5) -> 2184.2712 | H6: =H4*(1-H5) -> 2205.7766 | I6: =I4*(1-I5) -> 2227.4936 | J6: =J4*(1-J5) -> 2249.4245
B7: Less:Reinvestment Rate | E7: ='Intrinsic Growth'!K55 -> 0.073774469 | F7: =E7+(($J$7-$F$76)/4) -> 0.17799947 | G7: =F7+(($J$7-$F$76)/4) -> 0.28222447 | H7: =G7+(($J$7-$F$76)/4) -> 0.38644947 | I7: =H7+(($J$7-$F$76)/4) -> 0.49067447 | J7: 0.4169
B8: Free Cash Flow to Firm (FCFF) | E8: =E6*(1-E7) -> 1983.8709 | F8: =F6*(1-F7) -> 1777.9671 | G8: =G6*(1-G7) -> 1567.8164 | H8: =H6*(1-H7) -> 1353.3554 | I8: =I6*(1-I7) -> 1134.5194 | J8: =J6*(1-J7) -> 1311.6394
B9: Mid Year Convention | F9: 0.5 | G9: =F9+1 -> 1.5 | H9: =G9+1 -> 2.5 | I9: =H9+1 -> 3.5 | J9: =I9+1 -> 4.5
B10: Discounting Factor | F10: =1/(1+$E$16)^F9 -> 0.92887517 | G10: =1/(1+$E$16)^G9 -> 0.80144192 | H10: =1/(1+$E$16)^H9 -> 0.69149136 | I10: =1/(1+$E$16)^I9 -> 0.59662502 | J10: =1/(1+$E$16)^J9 -> 0.51477348
B12: PV of FCFF | F12: =F8*F10 -> 1651.5094 | G12: =G8*G10 -> 1256.5138 | H12: =H8*H10 -> 935.83356 | I12: =I8*I10 -> 676.88265 | J12: =J8*J10 -> 675.1972
B14: Expected Growth | E14: ='Intrinsic Growth'!K65 -> 0.0098455465
B15: Terminal Growth | E15: 0.069
B16: WACC | E16: =WACC!J45 -> 0.15900497
B18: Calculation of Terminal Value | G18: Sensitivity Analysis - Share Price
G19: =D37 -> 98.861049 | H19: 0.14 | I19: 0.159 | J19: 0.16 | K19: 0.17
B20: FCFF(n+1) | D20: =J12*(1+E15) -> 721.78581 | G20: 0.05 | H20: 98.863359 | I20: 91.566075 | J20: 91.251837 | K20: 88.397517
B21: WACC | D21: =E16 -> 0.15900497 | G21: 0.069 | H21: 110.06623 | I21: 98.863359 | J21: 98.403322 | K21: 94.303982
B22: Terminal Growth Rate | D22: =E15 -> 0.069 | G22: 0.07 | H22: 110.82432 | I22: 99.333734 | J22: 98.863359 | K22: 94.677022
G23: 0.08 | H23: 119.79504 | I23: 104.69244 | J23: 104.09628 | K23: 98.863359
B24: Terminal Value | D24: =D20/(D21-D22) -> 8019.3998
B26: Calculation of Equity Value per Share
B28: PV of FCFF | D28: =SUM(E12:J12) -> 5195.9367
B29: PV of Terminal Value | D29: =D24*J10 -> 4128.1743
B30: Value of Operating Assets | D30: =SUM(D28:D29) -> 9324.111
B32: Add: Cash | D32: ='Data Sheet'!K69 -> 2817.86
B33: Less: Debt | D33: ='Data Sheet'!K59 -> 2392.68
B34: Value of Equity | D34: =D30+D32-D33 -> 9749.291
B35: No. of Shares | D35: ='Data Sheet'!B6 -> 98.616099
B37: Equity Value per Share | D37: =D34/D35 -> 98.861049
B39: Share Price | D39: 1196
B40: Discount/Premium | D40: =D39/D37-1 -> 11.097788

Sheet Data Room>
B3: S.No. | C3: Name | D3: CMP Rs. | E3: No. Eq. Shares Cr. | F3: Market Cap | G3: Debt Rs.Cr. | H3: Cash End Rs.Cr. | I3: Net Debt | J3: EV | K3: Sales Rs.Cr. | L3: EBITDA | M3: NP 12M Rs.Cr. | O3: Date
B4: 1 | C4: Hind. Unilever | D4: 2177.1 | E4: 234.96 | F4: =D4*E4 -> 511531.42 | G4: 1478 | H4: 3248 | I4: =G4-H4 -> -1770 | J4: =F4+G4-H4 -> 509761.42 | K4: 64468 | L4: 14827.64 | M4: 15059 | P4: Adj Close
B5: 2 | C5: ITC | D5: 288.65 | E5: 1252.95 | F5: =D5*E5 -> 361664.02 | G5: 2399.06 | H5: 3008.79 | I5: =G5-H5 -> -609.73 | J5: =F5+G5-H5 -> 361054.29 | K5: 78868.4 | L5: 27603.94 | M5: 21018.15 | O5: 35065 | P5: 16.24
B6: 3 | C6: Nestle India | D6: 1423.25 | E6: 192.83 | F6: =D6*E6 -> 274445.3 | G6: 444.16 | H6: 1340.87 | I6: =G6-H6 -> -896.71 | J6: =F6+G6-H6 -> 273548.59 | K6: 23154.6 | L6: 5325.558 | M6: 3544.6 | O6: 35066 | P6: 15.97
B7: 4 | C7: Varun Beverages | D7: 536.65 | E7: 338.23 | F7: =D7*E7 -> 181511.13 | G7: 2508.18 | H7: 1998.49 | I7: =G7-H7 -> 509.69 | J7: =F7+G7-H7 -> 182020.82 | K7: 22692.63 | L7: 5219.3049 | M7: 3209.4 | O7: 35067 | P7: 16.09
B8: 5 | C8: Britannia Inds. | D8: 5265 | E8: 24.09 | F8: =D8*E8 -> 126833.85 | G8: 1380.28 | H8: 352.44 | I8: =G8-H8 -> 1027.84 | J8: =F8+G8-H8 -> 127861.69 | K8: 19151.59 | L8: 3447.2862 | M8: 2537.01 | O8: 35068 | P8: 16.06
B9: 6 | C9: Tata Consumer | D9: 1196 | E9: 98.96 | F9: =D9*E9 -> 118356.16 | G9: 2819.51 | H9: 3420.49 | I9: =G9-H9 -> -600.98 | J9: =F9+G9-H9 -> 117755.18 | K9: 20290.43 | L9: 2840.6602 | M9: 1546.8 | O9: 35069 | P9: 15.99
B10: 7 | C10: Marico | D10: 834.45 | E10: 129.83 | F10: =D10*E10 -> 108336.64 | G10: 557 | H10: 493 | I10: =G10-H10 -> 64 | J10: =F10+G10-H10 -> 108400.64 | K10: 13611 | L10: 2313.87 | M10: 1813 | O10: 35072 | P10: 15.7
B11: 8 | C11: Godrej Consumer | D11: 1038.8 | E11: 102.32 | F11: =D11*E11 -> 106290.02 | G11: 4415.81 | H11: 1005.41 | I11: =G11-H11 -> 3410.4 | J11: =F11+G11-H11 -> 109700.42 | K11: 15177.9 | L11: 3187.359 | M11: 1861.47 | O11: 35073 | P11: 15.4
B12: 9 | C12: United Spirits | D12: 1285.5 | E12: 72.74 | F12: =D12*E12 -> 93507.27 | G12: 413 | H12: 1977 | I12: =G12-H12 -> -1564 | J12: =F12+G12-H12 -> 91943.27 | K12: 12467 | L12: 2244.06 | M12: 1838 | O12: 35074 | P12: 15.41
B13: 10 | C13: Dabur India | D13: 445.4 | E13: 177.37 | F13: =D13*E13 -> 79000.598 | G13: 1287.32 | H13: 562.07 | I13: =G13-H13 -> 725.25 | J13: =F13+G13-H13 -> 79725.848 | K13: 13192.57 | L13: 2506.5883 | M13: 1868.69 | O13: 35075 | P13: 15.55
O14: 35076 | P14: 15.71
O15: 35079 | P15: 15.48
O16: 35080 | P16: 15.43
O17: 35081 | P17: 15.4
O18: 35082 | P18: 15.31
O19: 35083 | P19: 15.22
O20: 35086 | P20: 15.09
O21: 35087 | P21: 14.34
B22: 11 | C22: Colgate-Palmoliv | D22: 2090 | E22: 27.2 | F22: =D22*E22 -> 56848 | G22: 47.41 | H22: 1468.82 | I22: =G22-H22 -> -1421.41 | J22: =F22+G22-H22 -> 55426.59 | K22: 6035.04 | L22: 1870.8624 | M22: 1325.31 | O22: 35088 | P22: 14.42
B23: 12 | C23: Patanjali Foods | D23: 457.05 | E23: 108.81 | F23: =D23*E23 -> 49731.611 | G23: 2895.22 | H23: 275.3 | I23: =G23-H23 -> 2619.92 | J23: =F23+G23-H23 -> 52351.531 | K23: 38718.82 | L23: 1935.941 | M23: 1649.39 | O23: 35089 | P23: 14.55
B24: 13 | C24: Radico Khaitan | D24: 3512 | E24: 13.39 | F24: =D24*E24 -> 47025.68 | G24: 498.44 | H24: 88.33 | I24: =G24-H24 -> 410.11 | J24: =F24+G24-H24 -> 47435.79 | K24: 6050.43 | L24: 1028.5731 | M24: 604.48 | O24: 35090 | P24: 14.55
B25: 14 | C25: Godfrey Phillips | D25: 2300.9 | E25: 15.6 | F25: =D25*E25 -> 35894.04 | G25: 233.68 | H25: 32.61 | I25: =G25-H25 -> 201.07 | J25: =F25+G25-H25 -> 36095.11 | K25: 6391.11 | L25: 1597.7775 | M25: 1526.02 | O25: 35093 | P25: 14.99
B26: 15 | C26: United Breweries | D26: 1326 | E26: 26.44 | F26: =D26*E26 -> 35059.44 | G26: 1316.53 | H26: 571.56 | I26: =G26-H26 -> 744.97 | J26: =F26+G26-H26 -> 35804.41 | K26: 9239.94 | L26: 831.5946 | M26: 413.39 | O26: 35094 | P26: 15.07
B27: 16 | C27: P & G Hygiene | D27: 9725.15 | E27: 3.25 | F27: =D27*E27 -> 31606.737 | G27: 0.87 | H27: 567.94 | I27: =G27-H27 -> -567.07 | J27: =F27+G27-H27 -> 31039.667 | K27: 4290.42 | L27: 1158.4134 | M27: 856.5 | O27: 35095 | P27: 15.13
B28: 17 | C28: Gillette India | D28: 8123.9 | E28: 3.26 | F28: =D28*E28 -> 26483.914 | G28: 0.02 | H28: 269.26 | I28: =G28-H28 -> -269.24 | J28: =F28+G28-H28 -> 26214.674 | K28: 3099.53 | L28: 929.859 | M28: 654.31 | O28: 35096 | P28: 15.48
B29: 18 | C29: AWL Agri Busine. | D29: 193.25 | E29: 129.97 | F29: =D29*E29 -> 25116.702 | G29: 1109.27 | H29: 1719.31 | I29: =G29-H29 -> -610.04 | J29: =F29+G29-H29 -> 24506.662 | K29: 74730.67 | L29: 2241.9201 | M29: 1044.89 | O29: 35097 | P29: 16.25
B30: 19 | C30: Hatsun Agro | D30: 908.25 | E30: 22.27 | F30: =D30*E30 -> 20226.728 | G30: 1838.25 | H30: 51.19 | I30: =G30-H30 -> 1787.06 | J30: =F30+G30-H30 -> 22013.788 | K30: 9959.22 | L30: 1195.1064 | M30: 356.2 | O30: 35100 | P30: 16.2
B31: 20 | C31: Cupid | D31: 129.25 | E31: 134.47 | F31: =D31*E31 -> 17380.248 | G31: 56.38 | H31: 186.45 | I31: =G31-H31 -> -130.07 | J31: =F31+G31-H31 -> 17250.178 | K31: 391.4 | L31: 148.732 | M31: 108.26 | O31: 35101 | P31: 15.75
B32: 21 | C32: Emami | D32: 394.45 | E32: 43.65 | F32: =D32*E32 -> 17217.743 | G32: 161.92 | H32: 409.84 | I32: =G32-H32 -> -247.92 | J32: =F32+G32-H32 -> 16969.822 | K32: 3779.51 | L32: 944.8775 | M32: 775.26 | O32: 35102 | P32: 16.19
B33: 22 | C33: Avanti Feeds | D33: 1203.85 | E33: 13.62 | F33: =D33*E33 -> 16396.437 | G33: 13.23 | H33: 437.97 | I33: =G33-H33 -> -424.74 | J33: =F33+G33-H33 -> 15971.697 | K33: 6065.86 | L33: 727.9032 | M33: 656.8 | O33: 35103 | P33: 16.88
... B41: 30 | C41: DOMS Industries | D41: 2197.6 | E41: 6.07 | F41: =D41*E41 -> 13339.432 | G41: 141.26 | H41: 61.79 | I41: =G41-H41 -> 79.47 | J41: =F41+G41-H41 -> 13418.902 | K41: 2326.37 | L41: 395.4829 | M41: 239.56 | O41: 35115 | P41: 16.96
O42: 35116 | P42: 16.96
O43: 35117 | P43: 17.93
C44: Company | D44: Yahoo Finance Ticker | O44: 35118 | P44: 17.98
C45: Tata Consumer | D45: TATACONSUM.NS | O45: 35121 | P45: 17.87
C46: Hindustan Unilever | D46: HINDUNILVR.NS | O46: 35122 | P46: 17.69
C47: ITC | D47: ITC.NS | O47: 35123 | P47: 17.53
C48: Nestlé India | D48: NESTLEIND.NS | O48: 35124 | P48: 17.17
C49: Varun Beverages | D49: VBL.NS | O49: 35125 | P49: 17.25
C50: Britannia Industries | D50: BRITANNIA.NS | O50: 35128 | P50: 17.25
C51: Marico | D51: MARICO.NS | O51: 35129 | P51: 17.25
C52: Godrej Consumer | D52: GODREJCP.NS | O52: 35130 | P52: 17.38
C53: United Spirits | D53: UNITDSPR.NS | O53: 35131 | P53: 17.44
C54: Dabur India | D54: DABUR.NS | O54: 35132 | P54: 17.35
O55: 35135 | P55: 17.23
O56: 35136 | P56: 17
O57: 35137 | P57: 17.38
O58: 35138 | P58: 17.09
O59: 35139 | P59: 16.82
O60: 35142 | P60: 16.06
O61: 35143 | P61: 15.99
O62: 35144 | P62: 15.99
O63: 35145 | P63: 16.36
O64: 35146 | P64: 16.18
O65: 35149 | P65: 16.18
O66: 35150 | P66: 16.07
... O7638: 46176 | P7638: 1144

Sheet Comps Val
B2: Amount in Crores
B3: Comparable Company Valuation
D5: Market Data | K5: Financials | O5: Valuation
B6: Company | C6: Ticker | D6: Share Price | E6: Shares Outstanding | F6: Equity Value | G6: Net Debt | H6: Enterprise Value | K6: Revenue | L6: EBITDA | M6: Net Income | O6: EV/Revenue | P6: EV/EBITDA | Q6: P/E
B8: ='Data Room>'!C9 -> Tata Consumer | C8: TATACONSUM.NS | D8: ='Data Room>'!D9 -> 1196 | E8: ='Data Room>'!E9 -> 98.96 | F8: =D8*E8 -> 118356.16 | G8: ='Data Room>'!I9 -> -600.98 | H8: =F8+G8 -> 117755.18 | K8: ='Data Room>'!K9 -> 20290.43 | L8: ='Data Room>'!L9 -> 2840.6602 | M8: ='Data Room>'!M9 -> 1546.8 | O8: =$H8/K8 -> 5.8034837 | P8: =$H8/L8 -> 41.453455 | Q8: =F8/M8 -> 76.516783
B9: ='Data Room>'!C4 -> Hind. Unilever | C9: HINDUNILVR.NS | D9: ='Data Room>'!D4 -> 2177.1 | E9: ='Data Room>'!E4 -> 234.96 | F9: =D9*E9 -> 511531.42 | G9: ='Data Room>'!I4 -> -1770 | H9: =F9+G9 -> 509761.42 | K9: ='Data Room>'!K4 -> 64468 | L9: ='Data Room>'!L4 -> 14827.64 | M9: ='Data Room>'!M4 -> 15059 | O9: =$H9/K9 -> 7.9072007 | P9: =$H9/L9 -> 34.379134 | Q9: =F9/M9 -> 33.968485
B10: ='Data Room>'!C5 -> ITC | C10: ITC.NS | D10: ='Data Room>'!D5 -> 288.65 | E10: ='Data Room>'!E5 -> 1252.95 | F10: =D10*E10 -> 361664.02 | G10: ='Data Room>'!I5 -> -609.73 | H10: =F10+G10 -> 361054.29 | K10: ='Data Room>'!K5 -> 78868.4 | L10: ='Data Room>'!L5 -> 27603.94 | M10: ='Data Room>'!M5 -> 21018.15 | O10: =$H10/K10 -> 4.5779335 | P10: =$H10/L10 -> 13.07981 | Q10: =F10/M10 -> 17.207224
B11: ='Data Room>'!C6 -> Nestle India | C11: NESTLEIND.NS | D11: ='Data Room>'!D6 -> 1423.25 | E11: ='Data Room>'!E6 -> 192.83 | F11: =D11*E11 -> 274445.3 | G11: ='Data Room>'!I6 -> -896.71 | H11: =F11+G11 -> 273548.59 | K11: ='Data Room>'!K6 -> 23154.6 | L11: ='Data Room>'!L6 -> 5325.558 | M11: ='Data Room>'!M6 -> 3544.6 | O11: =$H11/K11 -> 11.814006 | P11: =$H11/L11 -> 51.365244 | Q11: =F11/M11 -> 77.42631
B12: ='Data Room>'!C8 -> Britannia Inds. | C12: BRITANNIA.NS | D12: ='Data Room>'!D8 -> 5265 | E12: ='Data Room>'!E8 -> 24.09 | F12: =D12*E12 -> 126833.85 | G12: ='Data Room>'!I8 -> 1027.84 | H12: =F12+G12 -> 127861.69 | K12: ='Data Room>'!K8 -> 19151.59 | L12: ='Data Room>'!L8 -> 3447.2862 | M12: ='Data Room>'!M8 -> 2537.01 | O12: =$H12/K12 -> 6.6762963 | P12: =$H12/L12 -> 37.090535 | Q12: =F12/M12 -> 49.993437
B13: ='Data Room>'!C10 -> Marico | C13: MARICO.NS | D13: ='Data Room>'!D10 -> 834.45 | E13: ='Data Room>'!E10 -> 129.83 | F13: =D13*E13 -> 108336.64 | G13: ='Data Room>'!I10 -> 64 | H13: =F13+G13 -> 108400.64 | K13: ='Data Room>'!K10 -> 13611 | L13: ='Data Room>'!L10 -> 2313.87 | M13: ='Data Room>'!M10 -> 1813 | O13: =$H13/K13 -> 7.9641939 | P13: =$H13/L13 -> 46.8482 | Q13: =F13/M13 -> 59.755457
B14: ='Data Room>'!C11 -> Godrej Consumer | C14: GODREJCP.NS | D14: ='Data Room>'!D11 -> 1038.8 | E14: ='Data Room>'!E11 -> 102.32 | F14: =D14*E14 -> 106290.02 | G14: ='Data Room>'!I11 -> 3410.4 | H14: =F14+G14 -> 109700.42 | K14: ='Data Room>'!K11 -> 15177.9 | L14: ='Data Room>'!L11 -> 3187.359 | M14: ='Data Room>'!M11 -> 1861.47 | O14: =$H14/K14 -> 7.2276412 | P14: =$H14/L14 -> 34.417339 | Q14: =F14/M14 -> 57.100042
B15: ='Data Room>'!C22 -> Colgate-Palmoliv | C15: UNITDSPR.NS | D15: ='Data Room>'!D22 -> 2090 | E15: ='Data Room>'!E22 -> 27.2 | F15: =D15*E15 -> 56848 | G15: ='Data Room>'!I22 -> -1421.41 | H15: =F15+G15 -> 55426.59 | K15: ='Data Room>'!K22 -> 6035.04 | L15: ='Data Room>'!L22 -> 1870.8624 | M15: ='Data Room>'!M22 -> 1325.31 | O15: =$H15/K15 -> 9.1841297 | P15: =$H15/L15 -> 29.626225 | Q15: =F15/M15 -> 42.894115
B16: ='Data Room>'!C13 -> Dabur India | C16: DABUR.NS | D16: ='Data Room>'!D13 -> 445.4 | E16: ='Data Room>'!E13 -> 177.37 | F16: =D16*E16 -> 79000.598 | G16: ='Data Room>'!I13 -> 725.25 | H16: =F16+G16 -> 79725.848 | K16: ='Data Room>'!K13 -> 13192.57 | L16: ='Data Room>'!L13 -> 2506.5883 | M16: ='Data Room>'!M13 -> 1868.69 | O16: =$H16/K16 -> 6.0432386 | P16: =$H16/L16 -> 31.806519 | Q16: =F16/M16 -> 42.275925
B18: High | O18: =MAX(O8:O16) -> 11.814006 | P18: =MAX(P8:P16) -> 51.365244 | Q18: =MAX(Q8:Q16) -> 77.42631
B19: 75th Percentile | O19: =QUARTILE(O8:O16,3) -> 7.9641939 | P19: =QUARTILE(P8:P16,3) -> 41.453455 | Q19: =QUARTILE(Q8:Q16,3) -> 59.755457
B20: Average | O20: =AVERAGE(O8:O16) -> 7.4664582 | P20: =AVERAGE(P8:P16) -> 35.56294 | Q20: =AVERAGE(Q8:Q16) -> 50.793087
B21: Median | O21: =MEDIAN(O8:O16) -> 7.2276412 | P21: =MEDIAN(P8:P16) -> 34.417339 | Q21: =MEDIAN(Q8:Q16) -> 49.993437
B22: 25th Percentile | O22: =QUARTILE(O8:O16,1) -> 6.0432386 | P22: =QUARTILE(P8:P16,1) -> 31.806519 | Q22: =QUARTILE(Q8:Q16,1) -> 42.275925
B23: Low | O23: =MIN(O8:O16) -> 4.5779335 | P23: =MIN(P8:P16) -> 13.07981 | Q23: =MIN(Q8:Q16) -> 17.207224
B25: Tata Consumer Comparable Valuation | O25: EV/Revenue | P25: EV/EBITDA | Q25: P/E
B27: Implied Enterprise Value | O27: =$K8*O21 -> 146651.95 | P27: =$L8*P21 -> 97767.966 | Q27: =Q29+Q28 -> 76728.869
B28: Net Debt | O28: =$G$8 -> -600.98 | P28: =$G$8 -> -600.98 | Q28: =$G$8 -> -600.98
B29: Implied Market Value | O29: =O27+O28 -> 146050.97 | P29: =P27+P28 -> 97166.986 | Q29: =Q21*M8 -> 77329.849
B30: Shares Outstanding | O30: =$E$8 -> 98.96 | P30: =$E$8 -> 98.96 | Q30: =$E$8 -> 98.96
B32: Implied Value per Share | O32: =O29/O30 -> 1475.8586 | P32: =P29/P30 -> 981.88142 | Q32: =Q29/Q30 -> 781.42531
O35: =IF(O32>$D$8,"Undervalued","Overvalued") -> Undervalued | P35: =IF(P32>$D$8,"Undervalued","Overvalued") -> Overvalued | Q35: =IF(Q32>$D$8,"Undervalued","Overvalued") -> Overvalued

Sheet Football Field
L2: Football Field Analysis - Data
N3: OpenLow | O3: Low | P3: OpenHigh | Q3: High
L4: Comps | N4: =O4 -> 781.42531 | O4: =MIN('Comps Val'!O32:Q32) -> 781.42531 | P4: =MAX('Comps Val'!O32:Q32) -> 1475.8586 | Q4: =P4 -> 1475.8586
L5: DCF Bear | N5: =O5 -> 88.397517 | O5: =MIN(DCF!K20:K23) -> 88.397517 | P5: =Q5 -> 98.863359 | Q5: =MAX(DCF!K20:K23) -> 98.863359
L6: DCF Base | N6: =O6 -> 91.566075 | O6: =MIN(DCF!I20:I23) -> 91.566075 | P6: =Q6 -> 98.863359 | Q6: =MAX(DCF!K20:K23) -> 98.863359
L7: DCF Bull | N7: =O7 -> 98.863359 | O7: =MIN(DCF!H20:H23) -> 98.863359 | P7: =Q7 -> 119.79504 | Q7: =MAX(DCF!H20:H23) -> 119.79504
L8: 52 Weeks H/L | N8: =O8 -> 1007.2 | O8: 1007.2 | P8: =Q8 -> 1282.7 | Q8: 1282.7

Sheet Historical App
B2: Date | C2: Adj Close | D2: Returns | E2: Sorted Returns | G2: Calculation of Value at Risk- Tata Consumer (Historical)
B4: 39197 | C4: 56.98 | D4: =C4/C5-1 -> 3.3496183 | E4: 0.1460177 | G4: Mean | K4: =AVERAGE(E4:E7636) -> 0.0008028854
B5: 36964 | C5: 13.1 | D5: =C5/C6-1 -> -0.45665699 | E5: 0.12833764 | G5: Std Deviation | K5: =_xlfn.STDEV.S(E4:E7636) -> 0.022201492
B6: 38126 | C6: 24.11 | D6: =C6/C7-1 -> 0.63679566 | E6: 0.12716223 | G6: Min | K6: =MIN(E4:E7636) -> -0.14267445
B7: 36965 | C7: 14.73 | D7: =C7/C8-1 -> -0.10781345 | E7: 0.12442748 | G7: Max | K7: =MAX(E4:E7636) -> 0.1460177
B8: 36950 | C8: 16.51 | D8: =C8/C9-1 -> -0.93710237 | E8: 0.11780636 | G8: CMP | K8: ='Comps Val'!D8 -> 1196
B9: 43915 | C9: 262.49 | D9: =C9/C10-1 -> 0.78309897 | E9: 0.11285878
B10: 41796 | C10: 147.21 | D10: =C10/C11-1 -> 11.789748 | E10: 0.11068357 | G10: Percentile | H10: Confidence | I10: VaR % | J10: Stock Price | K10: VaR (INR)
B11: 36831 | C11: 11.51 | D11: =C11/C12-1 -> -0.94436119 | E11: 0.1088632 | G11: 0.05 | H11: =1-G11 -> 0.95 | I11: =_xlfn.PERCENTILE.INC($E$4:$E$7636,$G11) -> -0.031596062 | J11: =$K$8*(1-ABS($I11)) -> 1158.2111 | K11: =$K$8-J11 -> 37.78889
B12: 43601 | C12: 206.87 | D12: =C12/C13-1 -> 6.5693377 | E12: 0.10815299 | G12: 0.01 | H12: =1-G12 -> 0.99 | I12: =_xlfn.PERCENTILE.INC($E$4:$E$7636,$G12) -> -0.057746805 | J12: =$K$8*(1-ABS($I12)) -> 1126.9348 | K12: =$K$8-J12 -> 69.065179
B13: 36220 | C13: 27.33 | D13: =C13/C14-1 -> -0.92593295 | E13: 0.10647773 | G13: 0.005 | H13: =1-G13 -> 0.995 | I13: =_xlfn.PERCENTILE.INC($E$4:$E$7636,$G13) -> -0.070136596 | J13: =$K$8*(1-ABS($I13)) -> 1112.1166 | K13: =$K$8-J13 -> 83.883369
B14: 43844 | C14: 368.99 | D14: =C14/C15-1 -> 3.1117673 | E14: 0.10386813 | G14: 0.1 | H14: =1-G14 -> 0.9 | I14: =_xlfn.PERCENTILE.INC($E$4:$E$7636,$G14) -> -0.022863035 | J14: =$K$8*(1-ABS($I14)) -> 1168.6558 | K14: =$K$8-J14 -> 27.34419
B15: 40939 | C15: 89.74 | D15: =C15/C16-1 -> -0.61953619 | E15: 0.10056414
B16: 43914 | C16: 235.87 | D16: =C16/C17-1 -> 22.610611 | E16: 0.09952452
B17: 37195 | C17: 9.99 | D17: =C17/C18-1 -> -0.22797527 | E17: 0.097802198
B18: 37319 | C18: 12.94 | D18: =C18/C19-1 -> -0.29940444 | E18: 0.096610169
B19: 35159 | C19: 18.47 | D19: =C19/C20-1 -> -0.59698887 | E19: 0.096142433
B20: 38883 | C20: 45.83 | D20: =C20/C21-1 -> 3.3606089 | E20: 0.094055861
B21: 37102 | C21: 10.51 | D21: =C21/C22-1 -> -0.83062047 | E21: 0.091381101
B22: 39967 | C22: 62.05 | D22: =C22/C23-1 -> 0.040060342 | E22: 0.091084931
B23: 39472 | C23: 59.66 | D23: =C23/C24-1 -> -0.64045079 | E23: 0.088884833
B24: 42961 | C24: 165.93 | D24: =C24/C25-1 -> 0.66362543 | E24: 0.088636662
B25: 40942 | C25: 99.74 | D25: =C25/C26-1 -> 0.95606982 | E25: 0.088626937
B26: 39470 | C26: 50.99 | D26: =C26/C27-1 -> 2.2854381 | E26: 0.088367129
... B7636: 43913 | C7636: 214.52 | D7636: =C7636/C7637-1 -> #DIV/0! | E7636: -0.14267445

Sheet Monte Carlo Simulation
B2: Date | C2: Adj Close | D2: Returns | E2: Sorted Returns | F2: Replication | G2: Simulated Returns | I2: Calculation of Value at Risk- Tata Consumer (Simulation)
B4: 39197 | C4: 56.98 | D4: =C4/C5-1 -> 3.3496183 | E4: 0.1460177 | F4: 1 | G4: =_xlfn.NORM.INV(RAND(),M$5,M$6) -> 0.029128684 | I4: Historical Approach
B5: 36964 | C5: 13.1 | D5: =C5/C6-1 -> -0.45665699 | E5: 0.12833764 | F5: 2 | G5: =_xlfn.NORM.INV(RAND(),M$5,M$6) -> -0.03517755 | I5: Mean | M5: =AVERAGE(E4:E7636) -> 0.0008028854
B6: 38126 | C6: 24.11 | D6: =C6/C7-1 -> 0.63679566 | E6: 0.12716223 | F6: 3 | G6: =_xlfn.NORM.INV(RAND(),M$5,M$6) -> 0.0043639201 | I6: Std Deviation | M6: =_xlfn.STDEV.S(E4:E7636) -> 0.022201492
B7: 36965 | C7: 14.73 | D7: =C7/C8-1 -> -0.10781345 | E7: 0.12442748 | F7: 4 | G7: =_xlfn.NORM.INV(RAND(),M$5,M$6) -> 0.021079134 | I7: Min | M7: =MIN(E4:E7636) -> -0.14267445
B8: 36950 | C8: 16.51 | D8: =C8/C9-1 -> -0.93710237 | E8: 0.11780636 | F8: 5 | G8: =_xlfn.NORM.INV(RAND(),M$5,M$6) -> 0.012522846 | I8: Max | M8: =MAX(E4:E7636) -> 0.1460177
B9: 43915 | C9: 262.49 | D9: =C9/C10-1 -> 0.78309897 | E9: 0.11285878 | F9: 6 | G9: =_xlfn.NORM.INV(RAND(),M$5,M$6) -> 0.0062686717 | I9: CMP | M9: ='Comps Val'!D8 -> 1196
B10: 41796 | C10: 147.21 | D10: =C10/C11-1 -> 11.789748 | E10: 0.11068357 | F10: 7 | G10: =_xlfn.NORM.INV(RAND(),M$5,M$6) -> 0.016302422
B11: 36831 | C11: 11.51 | D11: =C11/C12-1 -> -0.94436119 | E11: 0.1088632 | F11: 8 | G11: =_xlfn.NORM.INV(RAND(),M$5,M$6) -> -0.021092237 | I11: Monte Carlo Simulation
B12: 43601 | C12: 206.87 | D12: =C12/C13-1 -> 6.5693377 | E12: 0.10815299 | F12: 9 | G12: =_xlfn.NORM.INV(RAND(),M$5,M$6) -> 0.00050889 | I12: Mean | M12: =AVERAGE(G4:G10003) -> 0.001047949
B13: 36220 | C13: 27.33 | D13: =C13/C14-1 -> -0.92593295 | E13: 0.10647773 | F13: 10 | G13: =_xlfn.NORM.INV(RAND(),M$5,M$6) -> 0.021154488 | I13: Std Deviation | M13: =_xlfn.STDEV.S(G4:G10003) -> 0.02219559
B14: 43844 | C14: 368.99 | D14: =C14/C15-1 -> 3.1117673 | E14: 0.10386813 | F14: 11 | G14: =_xlfn.NORM.INV(RAND(),M$5,M$6) -> 0.011841049 | I14: Min | M14: =MIN(G4:G10003) -> -0.077949261
B15: 40939 | C15: 89.74 | D15: =C15/C16-1 -> -0.61953619 | E15: 0.10056414 | F15: 12 | G15: =_xlfn.NORM.INV(RAND(),M$5,M$6) -> -0.014243692 | I15: Max | M15: =MAX(G4:G10003) -> 0.083093206
B16: 43914 | C16: 235.87 | D16: =C16/C17-1 -> 22.610611 | E16: 0.09952452 | F16: 13 | G16: =_xlfn.NORM.INV(RAND(),M$5,M$6) -> 0.024975981 | I16: CMP | M16: =M9 -> 1196
B17: 37195 | C17: 9.99 | D17: =C17/C18-1 -> -0.22797527 | E17: 0.097802198 | F17: 14 | G17: =_xlfn.NORM.INV(RAND(),M$5,M$6) -> 0.029547921
B18: 37319 | C18: 12.94 | D18: =C18/C19-1 -> -0.29940444 | E18: 0.096610169 | F18: 15 | G18: =_xlfn.NORM.INV(RAND(),M$5,M$6) -> 0.0011436737 | I18: Percentile | J18: Confidence | K18: VaR % | L18: Stock Price | M18: VaR (INR)
B19: 35159 | C19: 18.47 | D19: =C19/C20-1 -> -0.59698887 | E19: 0.096142433 | F19: 16 | G19: =_xlfn.NORM.INV(RAND(),M$5,M$6) -> -0.018949015 | I19: 0.05 | J19: =1-I19 -> 0.95 | K19: =_xlfn.PERCENTILE.INC(G4:G10003,$I19) -> -0.035580818 | L19: =$M$9*(1-ABS($K19)) -> 1153.4453 | M19: =$M$9-L19 -> 42.554659
B20: 38883 | C20: 45.83 | D20: =C20/C21-1 -> 3.3606089 | E20: 0.094055861 | F20: 17 | G20: =_xlfn.NORM.INV(RAND(),M$5,M$6) -> -0.0063850516 | I20: 0.01 | J20: =1-I20 -> 0.99 | K20: =_xlfn.PERCENTILE.INC(G5:G10004,$I20) -> -0.051637471 | L20: =$M$9*(1-ABS($K20)) -> 1134.2416 | M20: =$M$9-L20 -> 61.758415
B21: 37102 | C21: 10.51 | D21: =C21/C22-1 -> -0.83062047 | E21: 0.091381101 | F21: 18 | G21: =_xlfn.NORM.INV(RAND(),M$5,M$6) -> -0.036697104 | I21: 0.005 | J21: =1-I21 -> 0.995 | K21: =_xlfn.PERCENTILE.INC(G6:G10005,$I21) -> -0.057408012 | L21: =$M$9*(1-ABS($K21)) -> 1127.34 | M21: =$M$9-L21 -> 68.659982
B22: 39967 | C22: 62.05 | D22: =C22/C23-1 -> 0.040060342 | E22: 0.091084931 | F22: 19 | G22: =_xlfn.NORM.INV(RAND(),M$5,M$6) -> -0.029480565 | I22: 0.1 | J22: =1-I22 -> 0.9 | K22: =_xlfn.PERCENTILE.INC(G7:G10006,$I22) -> -0.027269293 | L22: =$M$9*(1-ABS($K22)) -> 1163.3859 | M22: =$M$9-L22 -> 32.614074
B23: 39472 | C23: 59.66 | D23: =C23/C24-1 -> -0.64045079 | E23: 0.088884833 | F23: 20 | G23: =_xlfn.NORM.INV(RAND(),M$5,M$6) -> -0.0184302
B24: 42961 | C24: 165.93 | D24: =C24/C25-1 -> 0.66362543 | E24: 0.088636662 | F24: 21 | G24: =_xlfn.NORM.INV(RAND(),M$5,M$6) -> 0.011964924
B25: 40942 | C25: 99.74 | D25: =C25/C26-1 -> 0.95606982 | E25: 0.088626937 | F25: 22 | G25: =_xlfn.NORM.INV(RAND(),M$5,M$6) -> -0.0013581624
B26: 39470 | C26: 50.99 | D26: =C26/C27-1 -> 2.2854381 | E26: 0.088367129 | F26: 23 | G26: =_xlfn.NORM.INV(RAND(),M$5,M$6) -> 0.022520456
B27: 36775 | C27: 15.52 | D27: =C27/C28-1 -> -0.16198704 | E27: 0.088359046 | F27: 24 | G27: =_xlfn.NORM.INV(RAND(),M$5,M$6) -> 0.034434492
B28: 35983 | C28: 18.52 | D28: =C28/C29-1 -> 0.27548209 | E28: 0.08813161 | F28: 25 | G28: =_xlfn.NORM.INV(RAND(),M$5,M$6) -> -0.024243867
B29: 36978 | C29: 14.52 | D29: =C29/C30-1 -> -0.62490313 | E29: 0.086826347 | F29: 26 | G29: =_xlfn.NORM.INV(RAND(),M$5,M$6) -> 0.022495617
B30: 39777 | C30: 38.71 | D30: =C30/C31-1 -> -0.87106552 | E30: 0.086749017 | F30: 27 | G30: =_xlfn.NORM.INV(RAND(),M$5,M$6) -> 0.052290762
B31: 43769 | C31: 300.23 | D31: =C31/C32-1 -> 16.598476 | E31: 0.086569433 | F31: 28 | G31: =_xlfn.NORM.INV(RAND(),M$5,M$6) -> 0.010485778
B32: 35963 | C32: 17.06 | D32: =C32/C33-1 -> 0.14573539 | E32: 0.085932527 | F32: 29 | G32: =_xlfn.NORM.INV(RAND(),M$5,M$6) -> 0.004565128
B33: 35492 | C33: 14.89 | D33: =C33/C34-1 -> -0.87689128 | E33: 0.085276968 | F33: 30 | G33: =_xlfn.NORM.INV(RAND(),M$5,M$6) -> 0.0043338826
B34: 41180 | C34: 120.95 | D34: =C34/C35-1 -> 1.9025678 | E34: 0.085045304 | F34: 31 | G34: =_xlfn.NORM.INV(RAND(),M$5,M$6) -> -0.005172594
... B7636: 43913 | C7636: 214.52 | D7636: =C7636/C7637-1 -> #DIV/0! | E7636: -0.14267445 | F7636: 7633 | G7636: =_xlfn.NORM.INV(RAND(),M$5,M$6) -> -0.037248582
F7637: 7634 | G7637: =_xlfn.NORM.INV(RAND(),M$5,M$6) -> -0.028529025
F7638: 7635 | G7638: =_xlfn.NORM.INV(RAND(),M$5,M$6) -> 0.018324527
F7639: 7636 | G7639: =_xlfn.NORM.INV(RAND(),M$5,M$6) -> 0.063121902
F7640: 7637 | G7640: =_xlfn.NORM.INV(RAND(),M$5,M$6) -> 0.00021405432
F7641: 7638 | G7641: =_xlfn.NORM.INV(RAND(),M$5,M$6) -> -0.0038487953
F7642: 7639 | G7642: =_xlfn.NORM.INV(RAND(),M$5,M$6) -> 0.0056088836
F7643: 7640 | G7643: =_xlfn.NORM.INV(RAND(),M$5,M$6) -> 0.024493494
F7644: 7641 | G7644: =_xlfn.NORM.INV(RAND(),M$5,M$6) -> 0.00391588
F7645: 7642 | G7645: =_xlfn.NORM.INV(RAND(),M$5,M$6) -> 0.016500606
F7646: 7643 | G7646: =_xlfn.NORM.INV(RAND(),M$5,M$6) -> -0.0083750728
F7647: 7644 | G7647: =_xlfn.NORM.INV(RAND(),M$5,M$6) -> 0.028762177
F7648: 7645 | G7648: =_xlfn.NORM.INV(RAND(),M$5,M$6) -> 0.016304212
... F10003: 10000 | G10003: =_xlfn.NORM.INV(RAND(),M$5,M$6) -> -0.024040902
